Workbook
Name Slicer_PaymentMethod: #N/A

Sheet Instructions
A1: {=A1:B72} -> 0 | B1: KhanaChahiyo Data Analyst Project
B2: Food delivery order data | 6 months | 8 cities across Nepal
B4: You've just joined KhanaChahiyo, a Nepali food delivery startup, as their first Data Analyst.
B5: The Operations Head has handed you 6 months of raw order data and one instruction: "Tell me what's going on, why, what's coming, and what we should do about it."
B6: Assume today's date is 1 February 2026.
B7: Expect this to take a few hours, not minutes. Google things. Get stuck. That's normal, that's the job.
B9: How this maps to Module 1:
B10: 5 Stages: Collection (already done) -> Cleanup (Part A) -> Exploration (Part B) -> Visualization (Part C, D) -> Statistics (Part E, F)
B11: 4 Types of Analytics: Descriptive - what happened (Part C) -> Diagnostic - why (Part D) -> Predictive - what's next (Part E) -> Prescriptive - what to do (Part F)
B13: Sheets already in this file (don't edit these 5): Orders_Raw, Menu_Price_List, Rider_Directory, Promo_Codes, City_Delivery_Fee.
B14: Sheets YOU will create as you go: Orders_Working, Dashboard, Forecast, WhatIf. The instructions tell you when.
B15: When you're done, save this file as YourName_KhanaChahiyo_Project.xlsx and send it back.
B17: WARM-UP THOUGHT (Collection stage)
A18: W1 | B18: This data was already collected for you by the time you got it. If you were designing KhanaChahiyo's checkout screen from scratch, name ONE more piece of data you'd capture that isn't in this sheet, and why it would help you later. 1-2 lines.
B20: PART 0: QUICK LOOK (before you touch anything)
A21: P0.1 | B21: What's the earliest and the latest Order Date in Orders_Raw?
A22: P0.2 | B22: What's the highest and the lowest Delivery Time Taken recorded?
A23: P0.3 | B23: How many rows have a Customer Rating filled in? How many rows are there in total? What does the gap between those two numbers tell you?
A24: P0.4 | B24: What's the average Customer Rating, ignoring the blanks?
B25: Keep these four answers somewhere safe on this sheet — you'll revisit them at the end of Part A.
B27: PART A: CLEAN-UP
A28: A0 | B28: Right-click the Orders_Raw tab -> Move or Copy -> tick 'Create a copy' -> rename the copy Orders_Working. Do every task below inside Orders_Working. Never touch Orders_Raw again, it's your backup.
A29: A1 | B29: Customer Name has random capitals and extra spacing. Fix it so every name looks like a proper name, e.g. 'Suresh Thapa'.
A30: A2 | B30: Customer Phone is inconsistent, some numbers have '+977-' in front, some don't. Remove the country code from all of them, then insert a dash after the first 4 digits, e.g. 9841-234567.
A31: A3 | B31: Look closely at City. Kathmandu is not always spelled the same way. Find out how many different versions exist in this column — one function you learned lists every distinct value in a range. Then make every city spelled one consistent way, not just Kathmandu.
A32: A4 | B32: Two Order IDs each appear twice in the sheet. Find both pairs and highlight all four rows. Don't delete anything, in a nearby cell or comment, note which row in each pair looks like the more complete / correct entry, and why you think so.
A33: A5 | B33: A few rows have no Order Status at all. Add a new column and mark just these rows 'Needs Review'. Leave every other row's status exactly as it is.
A34: A6 | B34: A few Delivery Time Taken values look impossible for a scooter delivery. Use conditional formatting to highlight anything unrealistic. You decide the cutoff, write it in a cell along with one line on your reasoning.
A35: A7 | B35: Add a column called Customer Type. Work out the number of days between Customer Signup Date and this Order Date. If that gap is 2 days or less, label the row 'New'. Otherwise, 'Returning'.
A36: A8 | B36: Convert your cleaned range into a proper Excel Table. Add a dropdown (Data Validation) on Order Status, limited to Delivered, Cancelled, Returned, nothing else should be typeable there anymore.
A37: A9 | B37: Marketing wants one column that reads like 'ORD-1123 | Kathmandu | Chicken Momo' — Order ID, City and Item Name joined into a single line. Build it.
A38: A10 | B38: Marketing also asked (don't ask why) for City in ALL CAPS in one column, and Payment Method in lowercase in another.
A39: A11 | B39: Go back to your four Part 0 answers. Recalculate all four, now on your cleaned Orders_Working data. Did any of them change? Should the average rating have changed? 1-2 lines.
B41: PART B: EXPLORATION (lookups & formulas)
A42: B1 | B42: Bring in the correct Unit Price for every order from Menu_Price_List, matched on Item Name. A plain lookup will fail on a handful of rows, find out why before you fix it.
A43: B2 | B43: Using Unit Price x Quantity, calculate an Order Amount column.
A44: B3 | B44: Bring in the correct Delivery Fee for every order from City_Delivery_Fee, matched on City.
A45: B4 | B45: Some orders used a Promo Code, some didn't (blank). For the ones that did, calculate a Discount Amount, but check Promo_Codes first, because some codes are a percentage off and others are a flat Rupee amount off. A blank code means 0 discount.
A46: B5 | B46: Calculate Final Amount = Order Amount + Delivery Fee - Discount Amount.
A47: B6 | B47: In Rider_Directory, Rider ID is the LAST column, not the first. Still bring each order's Rider City/Zone and Vehicle Type into Orders_Working, matched on Rider ID. (One lookup function you learned doesn't care which side of the table the match column sits on, that's the one you want here.)
A48: B7 | B48: Sort every order into a Value Tier — 'Small' under Rs 500, 'Medium' Rs 500-1000, 'Large' above Rs 1000 — using one formula that checks multiple conditions at once.
A49: B8 | B49: Without building a Pivot Table: find the total Final Amount of Cancelled orders in Pokhara only. (Two conditions, one formula.)
A50: B9 | B50: Without building a Pivot Table: count how many Delivered orders each Rider has completed.
A51: B10 | B51: Filter Orders_Working down to one city. With the filter still applied, get the sum of Final Amount for just the visible rows. SUM will quietly give you the wrong number here, a different function won't.
A52: B11 | B52: Get a clean, sorted, no-repeats list of every Restaurant Partner that has at least one Cancelled order against it — nest three array functions together to do it in one formula.
A53: B12 | B53: BONUS: A few orders used a promo code after it had already expired (check Valid To in Promo_Codes). Find these rows. How many are there, and what should happen to the discount they were given?
B55: PART C: DESCRIPTIVE ANALYTICS - what happened?
A56: C1 | B56: On a new sheet called Dashboard, build a Pivot Table of total Final Amount by City and by Month. Add a Slicer for Payment Method.
A57: C2 | B57: From your pivot table: which city brought in the most revenue overall? Which single month was the strongest, across all cities combined?
A58: C3 | B58: Build 3 KPI cards on Dashboard: Total Revenue vs a target of Rs 1,50,000; Average Rating vs a target of 4.3; Cancellation Rate vs a target of under 8%. Each card should show at a glance whether the target was hit.
A59: C4 | B59: Build a Pivot Chart of Total Orders by Payment Method. Guess, in one line, why one payment method trails the rest — trust, access, habit? You don't have enough data here to be certain, and that's fine to say.
B61: PART D: DIAGNOSTIC ANALYTICS - why did it happen?
A62: D1 | B62: One city's average rating is noticeably lower than the rest. Which one? Check whether it also has a longer average Delivery Time Taken, or fewer active riders in Rider_Directory. Is your data enough to explain the 'why', or would you need more? 2-3 lines.
A63: D2 | B63: Build a Waterfall chart that starts at total Order Amount, steps down through Discounts Given and Cancelled/Returned Order Value, and ends at Final Revenue Collected. Where is KhanaChahiyo losing the most money?
A64: D3 | B64: Build a Combo Chart — Total Orders as columns, Average Delivery Time as a line, both by City. Do busier cities deliver faster or slower? What might explain that?
A65: D4 | B65: Orders clearly spike for a stretch of the data. Find the exact dates. What was happening in Nepal around then? (You won't find this answer inside the spreadsheet.)
B67: PART E: PREDICTIVE ANALYTICS - what's coming next?
A68: E1 | B68: On a new sheet called Forecast, summarize your data into Total Orders per week, across the full 6 months.
A69: E2 | B69: Use Excel's Forecast Sheet tool to project the next 3 months of weekly order volume. Note the confidence interval it shows you.
A70: E3 | B70: Now do it a second way, with a formula instead. Use one of the two straight-trend-line functions you learned, for the same future weeks.
A71: E4 | B71: Compare E2 and E3. They won't match exactly. Which one handles the festival spike better, and why? Which one would you actually hand to your manager? 2-3 lines.
B73: PART F: PRESCRIPTIVE ANALYTICS - what should KhanaChahiyo do?
A74: F1 | B74: On a new sheet called WhatIf: management wants Rs 35,000 revenue next month. If the Average Order Value stays where it is now, use Goal Seek to find how many total orders that needs.
A75: F2 | B75: Build a one-variable Data Table showing projected monthly revenue at 5 different delivery-fee levels: Rs 50, 65, 80, 100, 120. Would raising fees alone get KhanaChahiyo to target? What might customers do in response?
A76: F3 | B76: Build 3 scenarios with Scenario Manager — Weak Month, Normal Month, Strong Month — by changing Total Orders and Average Order Value together. Which scenario lines up closest with your Part E forecast?
B78: PART G: BRING IT TOGETHER
A79: G1 | B79: On Dashboard, add a dropdown to select one City. Your KPI cards or a summary table should update automatically when you change it.
A80: G2 | B80: Write 5-6 lines to KhanaChahiyo's management: what's happening, why, what's likely next, and what you recommend. Use real numbers from your own work.
B82: That's the full project. Work sheet by sheet, save often, and don't panic if a lookup throws an error, that's usually the point of that question.

Sheet Orders_Work
A1: OrderID | B1: OrderDate | C1: Customer Name | D1: Customer Phone | E1: CustomerSignupDate | F1: Customer Type | G1: City | H1: Restaurant Partner | I1: ItemCategory | J1: ItemName | K1: Quantity | L1: RiderID | M1: PaymentMethod | N1: PromoCode | O1: OrderStatus | P1: Status Review | Q1: CustomerRating | R1: DeliveryTimeTaken_Min | S1: FeedbackText | T1: Order Summary | U1: City Upper | V1: Payment Lower | W1: Unit Price | X1: Order Amount | Y1: Delivery Fee | Z1: Discount Amount | AA1: Final Amount | AB1: Rider City | AC1: Value Tier | AD1: Promo Check
A2: ORD-1001 | B2: 45871 | C2: Bikash Rai | D2: 9887-801759 | E2: 45827 | F2: =IF(B2-E2<=2,"New","Returning") -> Returning | G2: Lalitpur | H2: Yeti Newari Bhoj | I2: Newari Khana | J2: Chatamari | K2: 1 | L2: R-108 | M2: Khalti | O2: Delivered | P2: =IF(O2=""," NEED REVIEW","") | Q2: 4 | R2: 36 | T2: =_xlfn.CONCAT(Table5[[#This Row],[OrderID]]," | ",Table5[[#This Row],[City]]," | ",Table5[[#This Row],[ItemName]]) -> ORD-1001 | Lalitpur | Chatamari | U2: =UPPER(Table5[[#This Row],[City]]) -> LALITPUR | V2: =LOWER(Table5[[#This Row],[PaymentMethod]]) -> khalti | W2: {=_xlfn.XLOOKUP(TRIM(Table5[[#This Row],[ItemName]]), TRIM(Menu_Price_List_tbl[ItemName]),Menu_Price_List_tbl[UnitPrice_NPR])} -> 210 | X2: =W2*K2 -> 210 | Y2: =_xlfn.XLOOKUP(Table5[[#This Row],[City]],City_Delivery_Fee_tbl[City],City_Delivery_Fee_tbl[BaseDeliveryFee_NPR]) -> 50 | Z2: =IF(ISBLANK(Table5[[#This Row],[PromoCode]]), 0, _xlfn.LET( _xlpm.type, _xlfn.XLOOKUP(Table5[[#This Row],[PromoCode]], Promo_Codes!$A$2:$A$9, Promo_Codes!$C$2:$C$9, "Flat"), _xlpm.val, _xlfn.XLOOKUP(Table5[[#This Row],[PromoCode]], Promo_Codes!$A$2:$A$9, Promo_Codes!$D$2:$D$9, 0), IF(_xlpm.type="Percentage", Table5[[#This Row],[Order Amount]]*(_xlpm.val/100), _xlpm.val) ) ) -> 0 | AA2: =Table5[[#This Row],[Order Amount]]+Table5[[#This Row],[Delivery Fee]]-Table5[[#This Row],[Discount Amount]] -> 260 | AB2: =_xlfn.XLOOKUP(Table5[[#This Row],[RiderID]], Rider_Directory!$F$2:$F$26, Rider_Directory!$B$2:$B$26) -> Lalitpur | AC2: {=_xlfn.IFS(Table5[[#This Row],[Final Amount]]<500, "Small", Table5[[#This Row],[Final Amount]]<=1000, "Medium", Table5[[#This Row],[Final Amount]]>1000, "Large")} -> Small | AD2: =_xlfn.LET(_xlpm.expiry,_xlfn.XLOOKUP(Table5[[#This Row],[PromoCode]],Promo_Codes!$A$2:$A$9,Promo_Codes!$F$2:$F$9,DATE(2099,1,1)),IF(Table5[[#This Row],[OrderDate]]>_xlpm.expiry,"Expired Code Used","Valid")) -> Valid
A3: ORD-1002 | B3: 45871 | C3: Prakash Gurung | D3: 9809-541858 | E3: 45871 | F3: =IF(B3-E3<=2,"New","Returning") -> New | G3: Chitwan | H3: Fast Bites | I3: Fast Food | J3: French Fries | K3: 1 | L3: R-123 | M3: eSewa | O3: Cancelled | P3: =IF(O3=""," NEED REVIEW","") | R3: 41 | T3: =_xlfn.CONCAT(Table5[[#This Row],[OrderID]]," | ",Table5[[#This Row],[City]]," | ",Table5[[#This Row],[ItemName]]) -> ORD-1002 | Chitwan | French Fries | U3: =UPPER(Table5[[#This Row],[City]]) -> CHITWAN | V3: =LOWER(Table5[[#This Row],[PaymentMethod]]) -> esewa | W3: {=_xlfn.XLOOKUP(TRIM(Table5[[#This Row],[ItemName]]), TRIM(Menu_Price_List_tbl[ItemName]),Menu_Price_List_tbl[UnitPrice_NPR])} -> 160 | X3: =W3*K3 -> 160 | Y3: =_xlfn.XLOOKUP(Table5[[#This Row],[City]],City_Delivery_Fee_tbl[City],City_Delivery_Fee_tbl[BaseDeliveryFee_NPR]) -> 80 | Z3: =IF(ISBLANK(Table5[[#This Row],[PromoCode]]), 0, _xlfn.LET( _xlpm.type, _xlfn.XLOOKUP(Table5[[#This Row],[PromoCode]], Promo_Codes!$A$2:$A$9, Promo_Codes!$C$2:$C$9, "Flat"), _xlpm.val, _xlfn.XLOOKUP(Table5[[#This Row],[PromoCode]], Promo_Codes!$A$2:$A$9, Promo_Codes!$D$2:$D$9, 0), IF(_xlpm.type="Percentage", Table5[[#This Row],[Order Amount]]*(_xlpm.val/100), _xlpm.val) ) ) -> 0 | AA3: =Table5[[#This Row],[Order Amount]]+Table5[[#This Row],[Delivery Fee]]-Table5[[#This Row],[Discount Amount]] -> 240 | AB3: =_xlfn.XLOOKUP(Table5[[#This Row],[RiderID]], Rider_Directory!$F$2:$F$26, Rider_Directory!$B$2:$B$26) -> Chitwan | AC3: {=_xlfn.IFS(Table5[[#This Row],[Final Amount]]<500, "Small", Table5[[#This Row],[Final Amount]]<=1000, "Medium", Table5[[#This Row],[Final Amount]]>1000, "Large")} -> Small | AD3: =_xlfn.LET(_xlpm.expiry,_xlfn.XLOOKUP(Table5[[#This Row],[PromoCode]],Promo_Codes!$A$2:$A$9,Promo_Codes!$F$2:$F$9,DATE(2099,1,1)),IF(Table5[[#This Row],[OrderDate]]>_xlpm.expiry,"Expired Code Used","Valid")) -> Valid
A4: ORD-1003 | B4: 45872 | C4: Sagar Tamang | D4: 9820-297299 | E4: 45871 | F4: =IF(B4-E4<=2,"New","Returning") -> New | G4: Lalitpur | H4: Yeti Newari Bhoj | I4: Newari Khana | J4: Sukuti Sandheko | K4: 3 | L4: R-107 | M4: Khalti | O4: Delivered | P4: =IF(O4=""," NEED REVIEW","") | Q4: 4 | R4: 36 | T4: =_xlfn.CONCAT(Table5[[#This Row],[OrderID]]," | ",Table5[[#This Row],[City]]," | ",Table5[[#This Row],[ItemName]]) -> ORD-1003 | Lalitpur | Sukuti Sandheko | U4: =UPPER(Table5[[#This Row],[City]]) -> LALITPUR | V4: =LOWER(Table5[[#This Row],[PaymentMethod]]) -> khalti | W4: {=_xlfn.XLOOKUP(TRIM(Table5[[#This Row],[ItemName]]), TRIM(Menu_Price_List_tbl[ItemName]),Menu_Price_List_tbl[UnitPrice_NPR])} -> 350 | X4: =W4*K4 -> 1050 | Y4: =_xlfn.XLOOKUP(Table5[[#This Row],[City]],City_Delivery_Fee_tbl[City],City_Delivery_Fee_tbl[BaseDeliveryFee_NPR]) -> 50 | Z4: =IF(ISBLANK(Table5[[#This Row],[PromoCode]]), 0, _xlfn.LET( _xlpm.type, _xlfn.XLOOKUP(Table5[[#This Row],[PromoCode]], Promo_Codes!$A$2:$A$9, Promo_Codes!$C$2:$C$9, "Flat"), _xlpm.val, _xlfn.XLOOKUP(Table5[[#This Row],[PromoCode]], Promo_Codes!$A$2:$A$9, Promo_Codes!$D$2:$D$9, 0), IF(_xlpm.type="Percentage", Table5[[#This Row],[Order Amount]]*(_xlpm.val/100), _xlpm.val) ) ) -> 0 | AA4: =Table5[[#This Row],[Order Amount]]+Table5[[#This Row],[Delivery Fee]]-Table5[[#This Row],[Discount Amount]] -> 1100 | AB4: =_xlfn.XLOOKUP(Table5[[#This Row],[RiderID]], Rider_Directory!$F$2:$F$26, Rider_Directory!$B$2:$B$26) -> Lalitpur | AC4: {=_xlfn.IFS(Table5[[#This Row],[Final Amount]]<500, "Small", Table5[[#This Row],[Final Amount]]<=1000, "Medium", Table5[[#This Row],[Final Amount]]>1000, "Large")} -> Large | AD4: =_xlfn.LET(_xlpm.expiry,_xlfn.XLOOKUP(Table5[[#This Row],[PromoCode]],Promo_Codes!$A$2:$A$9,Promo_Codes!$F$2:$F$9,DATE(2099,1,1)),IF(Table5[[#This Row],[OrderDate]]>_xlpm.expiry,"Expired Code Used","Valid")) -> Valid
A5: ORD-1004 | B5: 45872 | C5: Suresh Magar | D5: 9822-791805 | E5: 45871 | F5: =IF(B5-E5<=2,"New","Returning") -> New | G5: Kathmandu | H5: Sekuwa Point | I5: Sekuwa | J5: Buff Sekuwa | K5: 2 | L5: R-104 | M5: eSewa | N5: MOMO20 | O5: Delivered | P5: =IF(O5=""," NEED REVIEW","") | Q5: 4 | R5: 27 | S5: Fast delivery today | T5: =_xlfn.CONCAT(Table5[[#This Row],[OrderID]]," | ",Table5[[#This Row],[City]]," | ",Table5[[#This Row],[ItemName]]) -> ORD-1004 | Kathmandu | Buff Sekuwa | U5: =UPPER(Table5[[#This Row],[City]]) -> KATHMANDU | V5: =LOWER(Table5[[#This Row],[PaymentMethod]]) -> esewa | W5: {=_xlfn.XLOOKUP(TRIM(Table5[[#This Row],[ItemName]]), TRIM(Menu_Price_List_tbl[ItemName]),Menu_Price_List_tbl[UnitPrice_NPR])} -> 380 | X5: =W5*K5 -> 760 | Y5: =_xlfn.XLOOKUP(Table5[[#This Row],[City]],City_Delivery_Fee_tbl[City],City_Delivery_Fee_tbl[BaseDeliveryFee_NPR]) -> 50 | Z5: =IF(ISBLANK(Table5[[#This Row],[PromoCode]]), 0, _xlfn.LET( _xlpm.type, _xlfn.XLOOKUP(Table5[[#This Row],[PromoCode]], Promo_Codes!$A$2:$A$9, Promo_Codes!$C$2:$C$9, "Flat"), _xlpm.val, _xlfn.XLOOKUP(Table5[[#This Row],[PromoCode]], Promo_Codes!$A$2:$A$9, Promo_Codes!$D$2:$D$9, 0), IF(_xlpm.type="Percentage", Table5[[#This Row],[Order Amount]]*(_xlpm.val/100), _xlpm.val) ) ) -> 152 | AA5: =Table5[[#This Row],[Order Amount]]+Table5[[#This Row],[Delivery Fee]]-Table5[[#This Row],[Discount Amount]] -> 658 | AB5: =_xlfn.XLOOKUP(Table5[[#This Row],[RiderID]], Rider_Directory!$F$2:$F$26, Rider_Directory!$B$2:$B$26) -> Kathmandu | AC5: {=_xlfn.IFS(Table5[[#This Row],[Final Amount]]<500, "Small", Table5[[#This Row],[Final Amount]]<=1000, "Medium", Table5[[#This Row],[Final Amount]]>1000, "Large")} -> Medium | AD5: =_xlfn.LET(_xlpm.expiry,_xlfn.XLOOKUP(Table5[[#This Row],[PromoCode]],Promo_Codes!$A$2:$A$9,Promo_Codes!$F$2:$F$9,DATE(2099,1,1)),IF(Table5[[#This Row],[OrderDate]]>_xlpm.expiry,"Expired Code Used","Valid")) -> Valid
A6: ORD-1005 | B6: 45875 | C6: Suresh Shrestha | D6: 9868-773132 | E6: 45873 | F6: =IF(B6-E6<=2,"New","Returning") -> New | G6: Kathmandu | H6: Yeti Newari Bhoj | I6: Newari Khana | J6: Bara | K6: 1 | L6: R-106 | M6: IME Pay | O6: Delivered | P6: =IF(O6=""," NEED REVIEW","") | Q6: 4 | R6: 25 | T6: =_xlfn.CONCAT(Table5[[#This Row],[OrderID]]," | ",Table5[[#This Row],[City]]," | ",Table5[[#This Row],[ItemName]]) -> ORD-1005 | Kathmandu | Bara | U6: =UPPER(Table5[[#This Row],[City]]) -> KATHMANDU | V6: =LOWER(Table5[[#This Row],[PaymentMethod]]) -> ime pay | W6: {=_xlfn.XLOOKUP(TRIM(Table5[[#This Row],[ItemName]]), TRIM(Menu_Price_List_tbl[ItemName]),Menu_Price_List_tbl[UnitPrice_NPR])} -> 160 | X6: =W6*K6 -> 160 | Y6: =_xlfn.XLOOKUP(Table5[[#This Row],[City]],City_Delivery_Fee_tbl[City],City_Delivery_Fee_tbl[BaseDeliveryFee_NPR]) -> 50 | Z6: =IF(ISBLANK(Table5[[#This Row],[PromoCode]]), 0, _xlfn.LET( _xlpm.type, _xlfn.XLOOKUP(Table5[[#This Row],[PromoCode]], Promo_Codes!$A$2:$A$9, Promo_Codes!$C$2:$C$9, "Flat"), _xlpm.val, _xlfn.XLOOKUP(Table5[[#This Row],[PromoCode]], Promo_Codes!$A$2:$A$9, Promo_Codes!$D$2:$D$9, 0), IF(_xlpm.type="Percentage", Table5[[#This Row],[Order Amount]]*(_xlpm.val/100), _xlpm.val) ) ) -> 0 | AA6: =Table5[[#This Row],[Order Amount]]+Table5[[#This Row],[Delivery Fee]]-Table5[[#This Row],[Discount Amount]] -> 210 | AB6: =_xlfn.XLOOKUP(Table5[[#This Row],[RiderID]], Rider_Directory!$F$2:$F$26, Rider_Directory!$B$2:$B$26) -> Kathmandu | AC6: {=_xlfn.IFS(Table5[[#This Row],[Final Amount]]<500, "Small", Table5[[#This Row],[Final Amount]]<=1000, "Medium", Table5[[#This Row],[Final Amount]]>1000, "Large")} -> Small | AD6: =_xlfn.LET(_xlpm.expiry,_xlfn.XLOOKUP(Table5[[#This Row],[PromoCode]],Promo_Codes!$A$2:$A$9,Promo_Codes!$F$2:$F$9,DATE(2099,1,1)),IF(Table5[[#This Row],[OrderDate]]>_xlpm.expiry,"Expired Code Used","Valid")) -> Valid
A7: ORD-1006 | B7: 45875 | C7: Sita Bhattarai | D7: 9851-313735 | E7: 45873 | F7: =IF(B7-E7<=2,"New","Returning") -> New | G7: Lalitpur | H7: Chiya Adda | I7: Beverages | J7: Milk Tea | K7: 2 | L7: R-108 | M7: Cash on Delivery | O7: Delivered | P7: =IF(O7=""," NEED REVIEW","") | Q7: 4 | R7: 22 | S7: Fast delivery today | T7: =_xlfn.CONCAT(Table5[[#This Row],[OrderID]]," | ",Table5[[#This Row],[City]]," | ",Table5[[#This Row],[ItemName]]) -> ORD-1006 | Lalitpur | Milk Tea | U7: =UPPER(Table5[[#This Row],[City]]) -> LALITPUR | V7: =LOWER(Table5[[#This Row],[PaymentMethod]]) -> cash on delivery | W7: {=_xlfn.XLOOKUP(TRIM(Table5[[#This Row],[ItemName]]), TRIM(Menu_Price_List_tbl[ItemName]),Menu_Price_List_tbl[UnitPrice_NPR])} -> 60 | X7: =W7*K7 -> 120 | Y7: =_xlfn.XLOOKUP(Table5[[#This Row],[City]],City_Delivery_Fee_tbl[City],City_Delivery_Fee_tbl[BaseDeliveryFee_NPR]) -> 50 | Z7: =IF(ISBLANK(Table5[[#This Row],[PromoCode]]), 0, _xlfn.LET( _xlpm.type, _xlfn.XLOOKUP(Table5[[#This Row],[PromoCode]], Promo_Codes!$A$2:$A$9, Promo_Codes!$C$2:$C$9, "Flat"), _xlpm.val, _xlfn.XLOOKUP(Table5[[#This Row],[PromoCode]], Promo_Codes!$A$2:$A$9, Promo_Codes!$D$2:$D$9, 0), IF(_xlpm.type="Percentage", Table5[[#This Row],[Order Amount]]*(_xlpm.val/100), _xlpm.val) ) ) -> 0 | AA7: =Table5[[#This Row],[Order Amount]]+Table5[[#This Row],[Delivery Fee]]-Table5[[#This Row],[Discount Amount]] -> 170 | AB7: =_xlfn.XLOOKUP(Table5[[#This Row],[RiderID]], Rider_Directory!$F$2:$F$26, Rider_Directory!$B$2:$B$26) -> Lalitpur | AC7: {=_xlfn.IFS(Table5[[#This Row],[Final Amount]]<500, "Small", Table5[[#This Row],[Final Amount]]<=1000, "Medium", Table5[[#This Row],[Final Amount]]>1000, "Large")} -> Small | AD7: =_xlfn.LET(_xlpm.expiry,_xlfn.XLOOKUP(Table5[[#This Row],[PromoCode]],Promo_Codes!$A$2:$A$9,Promo_Codes!$F$2:$F$9,DATE(2099,1,1)),IF(Table5[[#This Row],[OrderDate]]>_xlpm.expiry,"Expired Code Used","Valid")) -> Valid
A8: ORD-1007 | B8: 45876 | C8: Rohit Limbu | D8: 9850-201462 | E8: 45874 | F8: =IF(B8-E8<=2,"New","Returning") -> New | G8: Lalitpur | H8: Sweet Home Bakery | I8: Bakery | J8: Sel Roti (4 pcs) | K8: 1 | L8: R-109 | M8: Cash on Delivery | N8: MOMO20 | O8: Delivered | P8: =IF(O8=""," NEED REVIEW","") | Q8: 5 | R8: 34 | T8: =_xlfn.CONCAT(Table5[[#This Row],[OrderID]]," | ",Table5[[#This Row],[City]]," | ",Table5[[#This Row],[ItemName]]) -> ORD-1007 | Lalitpur | Sel Roti (4 pcs) | U8: =UPPER(Table5[[#This Row],[City]]) -> LALITPUR | V8: =LOWER(Table5[[#This Row],[PaymentMethod]]) -> cash on delivery | W8: {=_xlfn.XLOOKUP(TRIM(Table5[[#This Row],[ItemName]]), TRIM(Menu_Price_List_tbl[ItemName]),Menu_Price_List_tbl[UnitPrice_NPR])} -> 140 | X8: =W8*K8 -> 140 | Y8: =_xlfn.XLOOKUP(Table5[[#This Row],[City]],City_Delivery_Fee_tbl[City],City_Delivery_Fee_tbl[BaseDeliveryFee_NPR]) -> 50 | Z8: =IF(ISBLANK(Table5[[#This Row],[PromoCode]]), 0, _xlfn.LET( _xlpm.type, _xlfn.XLOOKUP(Table5[[#This Row],[PromoCode]], Promo_Codes!$A$2:$A$9, Promo_Codes!$C$2:$C$9, "Flat"), _xlpm.val, _xlfn.XLOOKUP(Table5[[#This Row],[PromoCode]], Promo_Codes!$A$2:$A$9, Promo_Codes!$D$2:$D$9, 0), IF(_xlpm.type="Percentage", Table5[[#This Row],[Order Amount]]*(_xlpm.val/100), _xlpm.val) ) ) -> 28 | AA8: =Table5[[#This Row],[Order Amount]]+Table5[[#This Row],[Delivery Fee]]-Table5[[#This Row],[Discount Amount]] -> 162 | AB8: =_xlfn.XLOOKUP(Table5[[#This Row],[RiderID]], Rider_Directory!$F$2:$F$26, Rider_Directory!$B$2:$B$26) -> Lalitpur | AC8: {=_xlfn.IFS(Table5[[#This Row],[Final Amount]]<500, "Small", Table5[[#This Row],[Final Amount]]<=1000, "Medium", Table5[[#This Row],[Final Amount]]>1000, "Large")} -> Small | AD8: =_xlfn.LET(_xlpm.expiry,_xlfn.XLOOKUP(Table5[[#This Row],[PromoCode]],Promo_Codes!$A$2:$A$9,Promo_Codes!$F$2:$F$9,DATE(2099,1,1)),IF(Table5[[#This Row],[OrderDate]]>_xlpm.expiry,"Expired Code Used","Valid")) -> Valid
A9: ORD-1008 | B9: 45878 | C9: Ramesh Lama | D9: 9853-705656 | E9: 45877 | F9: =IF(B9-E9<=2,"New","Returning") -> New | G9: Lalitpur | H9: Chiya Adda | I9: Beverages | J9: Lemon Soda | K9: 1 | L9: R-107 | M9: IME Pay | O9: Delivered | P9: =IF(O9=""," NEED REVIEW","") | Q9: 4 | R9: 31 | T9: =_xlfn.CONCAT(Table5[[#This Row],[OrderID]]," | ",Table5[[#This Row],[City]]," | ",Table5[[#This Row],[ItemName]]) -> ORD-1008 | Lalitpur | Lemon Soda | U9: =UPPER(Table5[[#This Row],[City]]) -> LALITPUR | V9: =LOWER(Table5[[#This Row],[PaymentMethod]]) -> ime pay | W9: {=_xlfn.XLOOKUP(TRIM(Table5[[#This Row],[ItemName]]), TRIM(Menu_Price_List_tbl[ItemName]),Menu_Price_List_tbl[UnitPrice_NPR])} -> 100 | X9: =W9*K9 -> 100 | Y9: =_xlfn.XLOOKUP(Table5[[#This Row],[City]],City_Delivery_Fee_tbl[City],City_Delivery_Fee_tbl[BaseDeliveryFee_NPR]) -> 50 | Z9: =IF(ISBLANK(Table5[[#This Row],[PromoCode]]), 0, _xlfn.LET( _xlpm.type, _xlfn.XLOOKUP(Table5[[#This Row],[PromoCode]], Promo_Codes!$A$2:$A$9, Promo_Codes!$C$2:$C$9, "Flat"), _xlpm.val, _xlfn.XLOOKUP(Table5[[#This Row],[PromoCode]], Promo_Codes!$A$2:$A$9, Promo_Codes!$D$2:$D$9, 0), IF(_xlpm.type="Percentage", Table5[[#This Row],[Order Amount]]*(_xlpm.val/100), _xlpm.val) ) ) -> 0 | AA9: =Table5[[#This Row],[Order Amount]]+Table5[[#This Row],[Delivery Fee]]-Table5[[#This Row],[Discount Amount]] -> 150 | AB9: =_xlfn.XLOOKUP(Table5[[#This Row],[RiderID]], Rider_Directory!$F$2:$F$26, Rider_Directory!$B$2:$B$26) -> Lalitpur | AC9: {=_xlfn.IFS(Table5[[#This Row],[Final Amount]]<500, "Small", Table5[[#This Row],[Final Amount]]<=1000, "Medium", Table5[[#This Row],[Final Amount]]>1000, "Large")} -> Small | AD9: =_xlfn.LET(_xlpm.expiry,_xlfn.XLOOKUP(Table5[[#This Row],[PromoCode]],Promo_Codes!$A$2:$A$9,Promo_Codes!$F$2:$F$9,DATE(2099,1,1)),IF(Table5[[#This Row],[OrderDate]]>_xlpm.expiry,"Expired Code Used","Valid")) -> Valid
A10: ORD-1009 | B10: 45879 | C10: Nisha Bista | D10: 9874-121547 | E10: 45879 | F10: =IF(B10-E10<=2,"New","Returning") -> New | G10: Biratnagar | H10: Bhattarai Momo Center | I10: Momo | J10: Buff Momo (Steamed) | K10: 2 | L10: R-118 | M10: eSewa | O10: Delivered | P10: =IF(O10=""," NEED REVIEW","") | Q10: 3 | R10: 45 | S10: quantity was less than expected | T10: =_xlfn.CONCAT(Table5[[#This Row],[OrderID]]," | ",Table5[[#This Row],[City]]," | ",Table5[[#This Row],[ItemName]]) -> ORD-1009 | Biratnagar | Buff Momo (Steamed) | U10: =UPPER(Table5[[#This Row],[City]]) -> BIRATNAGAR | V10: =LOWER(Table5[[#This Row],[PaymentMethod]]) -> esewa | W10: {=_xlfn.XLOOKUP(TRIM(Table5[[#This Row],[ItemName]]), TRIM(Menu_Price_List_tbl[ItemName]),Menu_Price_List_tbl[UnitPrice_NPR])} -> 170 | X10: =W10*K10 -> 340 | Y10: =_xlfn.XLOOKUP(Table5[[#This Row],[City]],City_Delivery_Fee_tbl[City],City_Delivery_Fee_tbl[BaseDeliveryFee_NPR]) -> 90 | Z10: =IF(ISBLANK(Table5[[#This Row],[PromoCode]]), 0, _xlfn.LET( _xlpm.type, _xlfn.XLOOKUP(Table5[[#This Row],[PromoCode]], Promo_Codes!$A$2:$A$9, Promo_Codes!$C$2:$C$9, "Flat"), _xlpm.val, _xlfn.XLOOKUP(Table5[[#This Row],[PromoCode]], Promo_Codes!$A$2:$A$9, Promo_Codes!$D$2:$D$9, 0), IF(_xlpm.type="Percentage", Table5[[#This Row],[Order Amount]]*(_xlpm.val/100), _xlpm.val) ) ) -> 0 | AA10: =Table5[[#This Row],[Order Amount]]+Table5[[#This Row],[Delivery Fee]]-Table5[[#This Row],[Discount Amount]] -> 430 | AB10: =_xlfn.XLOOKUP(Table5[[#This Row],[RiderID]], Rider_Directory!$F$2:$F$26, Rider_Directory!$B$2:$B$26) -> Biratnagar | AC10: {=_xlfn.IFS(Table5[[#This Row],[Final Amount]]<500, "Small", Table5[[#This Row],[Final Amount]]<=1000, "Medium", Table5[[#This Row],[Final Amount]]>1000, "Large")} -> Small | AD10: =_xlfn.LET(_xlpm.expiry,_xlfn.XLOOKUP(Table5[[#This Row],[PromoCode]],Promo_Codes!$A$2:$A$9,Promo_Codes!$F$2:$F$9,DATE(2099,1,1)),IF(Table5[[#This Row],[OrderDate]]>_xlpm.expiry,"Expired Code Used","Valid")) -> Valid
A11: ORD-1010 | B11: 45879 | C11: Suresh Bista | D11: 9837-504310 | E11: 45878 | F11: =IF(B11-E11<=2,"New","Returning") -> New | G11: Butwal | H11: Newa Kitchen | I11: Newari Khana | J11: Yomari | K11: 1 | L11: R-120 | M11: eSewa | N11: MOMO20 | O11: Delivered | P11: =IF(O11=""," NEED REVIEW","") | Q11: 3 | R11: 50 | S11: food was cold when it arrived | T11: =_xlfn.CONCAT(Table5[[#This Row],[OrderID]]," | ",Table5[[#This Row],[City]]," | ",Table5[[#This Row],[ItemName]]) -> ORD-1010 | Butwal | Yomari | U11: =UPPER(Table5[[#This Row],[City]]) -> BUTWAL | V11: =LOWER(Table5[[#This Row],[PaymentMethod]]) -> esewa | W11: {=_xlfn.XLOOKUP(TRIM(Table5[[#This Row],[ItemName]]), TRIM(Menu_Price_List_tbl[ItemName]),Menu_Price_List_tbl[UnitPrice_NPR])} -> 180 | X11: =W11*K11 -> 180 | Y11: =_xlfn.XLOOKUP(Table5[[#This Row],[City]],City_Delivery_Fee_tbl[City],City_Delivery_Fee_tbl[BaseDeliveryFee_NPR]) -> 85 | Z11: =IF(ISBLANK(Table5[[#This Row],[PromoCode]]), 0, _xlfn.LET( _xlpm.type, _xlfn.XLOOKUP(Table5[[#This Row],[PromoCode]], Promo_Codes!$A$2:$A$9, Promo_Codes!$C$2:$C$9, "Flat"), _xlpm.val, _xlfn.XLOOKUP(Table5[[#This Row],[PromoCode]], Promo_Codes!$A$2:$A$9, Promo_Codes!$D$2:$D$9, 0), IF(_xlpm.type="Percentage", Table5[[#This Row],[Order Amount]]*(_xlpm.val/100), _xlpm.val) ) ) -> 36 | AA11: =Table5[[#This Row],[Order Amount]]+Table5[[#This Row],[Delivery Fee]]-Table5[[#This Row],[Discount Amount]] -> 229 | AB11: =_xlfn.XLOOKUP(Table5[[#This Row],[RiderID]], Rider_Directory!$F$2:$F$26, Rider_Directory!$B$2:$B$26) -> Butwal | AC11: {=_xlfn.IFS(Table5[[#This Row],[Final Amount]]<500, "Small", Table5[[#This Row],[Final Amount]]<=1000, "Medium", Table5[[#This Row],[Final Amount]]>1000, "Large")} -> Small | AD11: =_xlfn.LET(_xlpm.expiry,_xlfn.XLOOKUP(Table5[[#This Row],[PromoCode]],Promo_Codes!$A$2:$A$9,Promo_Codes!$F$2:$F$9,DATE(2099,1,1)),IF(Table5[[#This Row],[OrderDate]]>_xlpm.expiry,"Expired Code Used","Valid")) -> Valid
A12: ORD-1011 | B12: 45880 | C12: Sabina Magar | D12: 9876-018955 | E12: 45880 | F12: =IF(B12-E12<=2,"New","Returning") -> New | G12: Dharan | H12: Newa Kitchen | I12: Newari Khana | J12: Choila (Buff) | K12: 3 | L12: R-124 | M12: eSewa | N12: MONSOON30 | O12: Delivered | P12: =IF(O12=""," NEED REVIEW","") | Q12: 4 | R12: 53 | S12: best momo in town | T12: =_xlfn.CONCAT(Table5[[#This Row],[OrderID]]," | ",Table5[[#This Row],[City]]," | ",Table5[[#This Row],[ItemName]]) -> ORD-1011 | Dharan | Choila (Buff) | U12: =UPPER(Table5[[#This Row],[City]]) -> DHARAN | V12: =LOWER(Table5[[#This Row],[PaymentMethod]]) -> esewa | W12: {=_xlfn.XLOOKUP(TRIM(Table5[[#This Row],[ItemName]]), TRIM(Menu_Price_List_tbl[ItemName]),Menu_Price_List_tbl[UnitPrice_NPR])} -> 320 | X12: =W12*K12 -> 960 | Y12: =_xlfn.XLOOKUP(Table5[[#This Row],[City]],City_Delivery_Fee_tbl[City],City_Delivery_Fee_tbl[BaseDeliveryFee_NPR]) -> 95 | Z12: =IF(ISBLANK(Table5[[#This Row],[PromoCode]]), 0, _xlfn.LET( _xlpm.type, _xlfn.XLOOKUP(Table5[[#This Row],[PromoCode]], Promo_Codes!$A$2:$A$9, Promo_Codes!$C$2:$C$9, "Flat"), _xlpm.val, _xlfn.XLOOKUP(Table5[[#This Row],[PromoCode]], Promo_Codes!$A$2:$A$9, Promo_Codes!$D$2:$D$9, 0), IF(_xlpm.type="Percentage", Table5[[#This Row],[Order Amount]]*(_xlpm.val/100), _xlpm.val) ) ) -> 30 | AA12: =Table5[[#This Row],[Order Amount]]+Table5[[#This Row],[Delivery Fee]]-Table5[[#This Row],[Discount Amount]] -> 1025 | AB12: =_xlfn.XLOOKUP(Table5[[#This Row],[RiderID]], Rider_Directory!$F$2:$F$26, Rider_Directory!$B$2:$B$26) -> Dharan | AC12: {=_xlfn.IFS(Table5[[#This Row],[Final Amount]]<500, "Small", Table5[[#This Row],[Final Amount]]<=1000, "Medium", Table5[[#This Row],[Final Amount]]>1000, "Large")} -> Large | AD12: =_xlfn.LET(_xlpm.expiry,_xlfn.XLOOKUP(Table5[[#This Row],[PromoCode]],Promo_Codes!$A$2:$A$9,Promo_Codes!$F$2:$F$9,DATE(2099,1,1)),IF(Table5[[#This Row],[OrderDate]]>_xlpm.expiry,"Expired Code Used","Valid")) -> Valid
A13: ORD-1012 | B13: 45880 | C13: Ramesh Shrestha | D13: 9800-251678 | E13: 45880 | F13: =IF(B13-E13<=2,"New","Returning") -> New | G13: Kathmandu | H13: Sweet Home Bakery | I13: Bakery | J13: Cheese Cake Slice | K13: 1 | L13: R-105 | M13: Khalti | O13: Delivered | P13: =IF(O13=""," NEED REVIEW","") | Q13: 5 | R13: 27 | S13: quality was great as always | T13: =_xlfn.CONCAT(Table5[[#This Row],[OrderID]]," | ",Table5[[#This Row],[City]]," | ",Table5[[#This Row],[ItemName]]) -> ORD-1012 | Kathmandu | Cheese Cake Slice | U13: =UPPER(Table5[[#This Row],[City]]) -> KATHMANDU | V13: =LOWER(Table5[[#This Row],[PaymentMethod]]) -> khalti | W13: {=_xlfn.XLOOKUP(TRIM(Table5[[#This Row],[ItemName]]), TRIM(Menu_Price_List_tbl[ItemName]),Menu_Price_List_tbl[UnitPrice_NPR])} -> 250 | X13: =W13*K13 -> 250 | Y13: =_xlfn.XLOOKUP(Table5[[#This Row],[City]],City_Delivery_Fee_tbl[City],City_Delivery_Fee_tbl[BaseDeliveryFee_NPR]) -> 50 | Z13: =IF(ISBLANK(Table5[[#This Row],[PromoCode]]), 0, _xlfn.LET( _xlpm.type, _xlfn.XLOOKUP(Table5[[#This Row],[PromoCode]], Promo_Codes!$A$2:$A$9, Promo_Codes!$C$2:$C$9, "Flat"), _xlpm.val, _xlfn.XLOOKUP(Table5[[#This Row],[PromoCode]], Promo_Codes!$A$2:$A$9, Promo_Codes!$D$2:$D$9, 0), IF(_xlpm.type="Percentage", Table5[[#This Row],[Order Amount]]*(_xlpm.val/100), _xlpm.val) ) ) -> 0 | AA13: =Table5[[#This Row],[Order Amount]]+Table5[[#This Row],[Delivery Fee]]-Table5[[#This Row],[Discount Amount]] -> 300 | AB13: =_xlfn.XLOOKUP(Table5[[#This Row],[RiderID]], Rider_Directory!$F$2:$F$26, Rider_Directory!$B$2:$B$26) -> Kathmandu | AC13: {=_xlfn.IFS(Table5[[#This Row],[Final Amount]]<500, "Small", Table5[[#This Row],[Final Amount]]<=1000, "Medium", Table5[[#This Row],[Final Amount]]>1000, "Large")} -> Small | AD13: =_xlfn.LET(_xlpm.expiry,_xlfn.XLOOKUP(Table5[[#This Row],[PromoCode]],Promo_Codes!$A$2:$A$9,Promo_Codes!$F$2:$F$9,DATE(2099,1,1)),IF(Table5[[#This Row],[OrderDate]]>_xlpm.expiry,"Expired Code Used","Valid")) -> Valid
A14: ORD-1013 | B14: 45881 | C14: Sunita Magar | D14: 9842-731672 | E14: 45784 | F14: =IF(B14-E14<=2,"New","Returning") -> Returning | G14: Butwal | H14: Newa Kitchen | I14: Newari Khana | J14: Aloo Achar | K14: 3 | L14: R-119 | M14: eSewa | O14: Delivered | P14: =IF(O14=""," NEED REVIEW","") | Q14: 2 | R14: 43 | T14: =_xlfn.CONCAT(Table5[[#This Row],[OrderID]]," | ",Table5[[#This Row],[City]]," | ",Table5[[#This Row],[ItemName]]) -> ORD-1013 | Butwal | Aloo Achar | U14: =UPPER(Table5[[#This Row],[City]]) -> BUTWAL | V14: =LOWER(Table5[[#This Row],[PaymentMethod]]) -> esewa | W14: {=_xlfn.XLOOKUP(TRIM(Table5[[#This Row],[ItemName]]), TRIM(Menu_Price_List_tbl[ItemName]),Menu_Price_List_tbl[UnitPrice_NPR])} -> 120 | X14: =W14*K14 -> 360 | Y14: =_xlfn.XLOOKUP(Table5[[#This Row],[City]],City_Delivery_Fee_tbl[City],City_Delivery_Fee_tbl[BaseDeliveryFee_NPR]) -> 85 | Z14: =IF(ISBLANK(Table5[[#This Row],[PromoCode]]), 0, _xlfn.LET( _xlpm.type, _xlfn.XLOOKUP(Table5[[#This Row],[PromoCode]], Promo_Codes!$A$2:$A$9, Promo_Codes!$C$2:$C$9, "Flat"), _xlpm.val, _xlfn.XLOOKUP(Table5[[#This Row],[PromoCode]], Promo_Codes!$A$2:$A$9, Promo_Codes!$D$2:$D$9, 0), IF(_xlpm.type="Percentage", Table5[[#This Row],[Order Amount]]*(_xlpm.val/100), _xlpm.val) ) ) -> 0 | AA14: =Table5[[#This Row],[Order Amount]]+Table5[[#This Row],[Delivery Fee]]-Table5[[#This Row],[Discount Amount]] -> 445 | AB14: =_xlfn.XLOOKUP(Table5[[#This Row],[RiderID]], Rider_Directory!$F$2:$F$26, Rider_Directory!$B$2:$B$26) -> Butwal | AC14: {=_xlfn.IFS(Table5[[#This Row],[Final Amount]]<500, "Small", Table5[[#This Row],[Final Amount]]<=1000, "Medium", Table5[[#This Row],[Final Amount]]>1000, "Large")} -> Small | AD14: =_xlfn.LET(_xlpm.expiry,_xlfn.XLOOKUP(Table5[[#This Row],[PromoCode]],Promo_Codes!$A$2:$A$9,Promo_Codes!$F$2:$F$9,DATE(2099,1,1)),IF(Table5[[#This Row],[OrderDate]]>_xlpm.expiry,"Expired Code Used","Valid")) -> Valid
A15: ORD-1014 | B15: 45881 | C15: Bishal Bista | D15: 9899-075116 | E15: 45880 | F15: =IF(B15-E15<=2,"New","Returning") -> New | G15: Lalitpur | H15: Newa Kitchen | I15: Newari Khana | J15: Bara | K15: 1 | L15: R-108 | M15: IME Pay | N15: FIRSTORDER | O15: Returned | P15: =IF(O15=""," NEED REVIEW","") | R15: 21 | T15: =_xlfn.CONCAT(Table5[[#This Row],[OrderID]]," | ",Table5[[#This Row],[City]]," | ",Table5[[#This Row],[ItemName]]) -> ORD-1014 | Lalitpur | Bara | U15: =UPPER(Table5[[#This Row],[City]]) -> LALITPUR | V15: =LOWER(Table5[[#This Row],[PaymentMethod]]) -> ime pay | W15: {=_xlfn.XLOOKUP(TRIM(Table5[[#This Row],[ItemName]]), TRIM(Menu_Price_List_tbl[ItemName]),Menu_Price_List_tbl[UnitPrice_NPR])} -> 160 | X15: =W15*K15 -> 160 | Y15: =_xlfn.XLOOKUP(Table5[[#This Row],[City]],City_Delivery_Fee_tbl[City],City_Delivery_Fee_tbl[BaseDeliveryFee_NPR]) -> 50 | Z15: =IF(ISBLANK(Table5[[#This Row],[PromoCode]]), 0, _xlfn.LET( _xlpm.type, _xlfn.XLOOKUP(Table5[[#This Row],[PromoCode]], Promo_Codes!$A$2:$A$9, Promo_Codes!$C$2:$C$9, "Flat"), _xlpm.val, _xlfn.XLOOKUP(Table5[[#This Row],[PromoCode]], Promo_Codes!$A$2:$A$9, Promo_Codes!$D$2:$D$9, 0), IF(_xlpm.type="Percentage", Table5[[#This Row],[Order Amount]]*(_xlpm.val/100), _xlpm.val) ) ) -> 100 | AA15: =Table5[[#This Row],[Order Amount]]+Table5[[#This Row],[Delivery Fee]]-Table5[[#This Row],[Discount Amount]] -> 110 | AB15: =_xlfn.XLOOKUP(Table5[[#This Row],[RiderID]], Rider_Directory!$F$2:$F$26, Rider_Directory!$B$2:$B$26) -> Lalitpur | AC15: {=_xlfn.IFS(Table5[[#This Row],[Final Amount]]<500, "Small", Table5[[#This Row],[Final Amount]]<=1000, "Medium", Table5[[#This Row],[Final Amount]]>1000, "Large")} -> Small | AD15: =_xlfn.LET(_xlpm.expiry,_xlfn.XLOOKUP(Table5[[#This Row],[PromoCode]],Promo_Codes!$A$2:$A$9,Promo_Codes!$F$2:$F$9,DATE(2099,1,1)),IF(Table5[[#This Row],[OrderDate]]>_xlpm.expiry,"Expired Code Used","Valid")) -> Valid
A16: ORD-1015 | B16: 45882 | C16: Manisha Bista | D16: 9886-843353 | E16: 45881 | F16: =IF(B16-E16<=2,"New","Returning") -> New | G16: Dharan | H16: Quick Snacks Corner | I16: Fast Food | J16: Veg Fried Rice | K16: 1 | L16: R-125 | M16: eSewa | N16: MONSOON30 | O16: Delivered | P16: =IF(O16=""," NEED REVIEW","") | Q16: 4 | R16: 48 | T16: =_xlfn.CONCAT(Table5[[#This Row],[OrderID]]," | ",Table5[[#This Row],[City]]," | ",Table5[[#This Row],[ItemName]]) -> ORD-1015 | Dharan | Veg Fried Rice | U16: =UPPER(Table5[[#This Row],[City]]) -> DHARAN | V16: =LOWER(Table5[[#This Row],[PaymentMethod]]) -> esewa | W16: {=_xlfn.XLOOKUP(TRIM(Table5[[#This Row],[ItemName]]), TRIM(Menu_Price_List_tbl[ItemName]),Menu_Price_List_tbl[UnitPrice_NPR])} -> 220 | X16: =W16*K16 -> 220 | Y16: =_xlfn.XLOOKUP(Table5[[#This Row],[City]],City_Delivery_Fee_tbl[City],City_Delivery_Fee_tbl[BaseDeliveryFee_NPR]) -> 95 | Z16: =IF(ISBLANK(Table5[[#This Row],[PromoCode]]), 0, _xlfn.LET( _xlpm.type, _xlfn.XLOOKUP(Table5[[#This Row],[PromoCode]], Promo_Codes!$A$2:$A$9, Promo_Codes!$C$2:$C$9, "Flat"), _xlpm.val, _xlfn.XLOOKUP(Table5[[#This Row],[PromoCode]], Promo_Codes!$A$2:$A$9, Promo_Codes!$D$2:$D$9, 0), IF(_xlpm.type="Percentage", Table5[[#This Row],[Order Amount]]*(_xlpm.val/100), _xlpm.val) ) ) -> 30 | AA16: =Table5[[#This Row],[Order Amount]]+Table5[[#This Row],[Delivery Fee]]-Table5[[#This Row],[Discount Amount]] -> 285 | AB16: =_xlfn.XLOOKUP(Table5[[#This Row],[RiderID]], Rider_Directory!$F$2:$F$26, Rider_Directory!$B$2:$B$26) -> Dharan | AC16: {=_xlfn.IFS(Table5[[#This Row],[Final Amount]]<500, "Small", Table5[[#This Row],[Final Amount]]<=1000, "Medium", Table5[[#This Row],[Final Amount]]>1000, "Large")} -> Small | AD16: =_xlfn.LET(_xlpm.expiry,_xlfn.XLOOKUP(Table5[[#This Row],[PromoCode]],Promo_Codes!$A$2:$A$9,Promo_Codes!$F$2:$F$9,DATE(2099,1,1)),IF(Table5[[#This Row],[OrderDate]]>_xlpm.expiry,"Expired Code Used","Valid")) -> Valid
A17: ORD-1016 | B17: 45882 | C17: Deepak Basnet | D17: 9844-634786 | E17: 45814 | F17: =IF(B17-E17<=2,"New","Returning") -> Returning | G17: Butwal | H17: Fast Bites | I17: Fast Food | J17: CHICKEN CHOWMEIN | K17: 2 | L17: R-120 | M17: Khalti | O17: Delivered | P17: =IF(O17=""," NEED REVIEW","") | Q17: 3 | R17: 58 | T17: =_xlfn.CONCAT(Table5[[#This Row],[OrderID]]," | ",Table5[[#This Row],[City]]," | ",Table5[[#This Row],[ItemName]]) -> ORD-1016 | Butwal | CHICKEN CHOWMEIN | U17: =UPPER(Table5[[#This Row],[City]]) -> BUTWAL | V17: =LOWER(Table5[[#This Row],[PaymentMethod]]) -> khalti | W17: {=_xlfn.XLOOKUP(TRIM(Table5[[#This Row],[ItemName]]), TRIM(Menu_Price_List_tbl[ItemName]),Menu_Price_List_tbl[UnitPrice_NPR])} -> 250 | X17: =W17*K17 -> 500 | Y17: =_xlfn.XLOOKUP(Table5[[#This Row],[City]],City_Delivery_Fee_tbl[City],City_Delivery_Fee_tbl[BaseDeliveryFee_NPR]) -> 85 | Z17: =IF(ISBLANK(Table5[[#This Row],[PromoCode]]), 0, _xlfn.LET( _xlpm.type, _xlfn.XLOOKUP(Table5[[#This Row],[PromoCode]], Promo_Codes!$A$2:$A$9, Promo_Codes!$C$2:$C$9, "Flat"), _xlpm.val, _xlfn.XLOOKUP(Table5[[#This Row],[PromoCode]], Promo_Codes!$A$2:$A$9, Promo_Codes!$D$2:$D$9, 0), IF(_xlpm.type="Percentage", Table5[[#This Row],[Order Amount]]*(_xlpm.val/100), _xlpm.val) ) ) -> 0 | AA17: =Table5[[#This Row],[Order Amount]]+Table5[[#This Row],[Delivery Fee]]-Table5[[#This Row],[Discount Amount]] -> 585 | AB17: =_xlfn.XLOOKUP(Table5[[#This Row],[RiderID]], Rider_Directory!$F$2:$F$26, Rider_Directory!$B$2:$B$26) -> Butwal | AC17: {=_xlfn.IFS(Table5[[#This Row],[Final Amount]]<500, "Small", Table5[[#This Row],[Final Amount]]<=1000, "Medium", Table5[[#This Row],[Final Amount]]>1000, "Large")} -> Medium | AD17: =_xlfn.LET(_xlpm.expiry,_xlfn.XLOOKUP(Table5[[#This Row],[PromoCode]],Promo_Codes!$A$2:$A$9,Promo_Codes!$F$2:$F$9,DATE(2099,1,1)),IF(Table5[[#This Row],[OrderDate]]>_xlpm.expiry,"Expired Code Used","Valid")) -> Valid
A18: ORD-1017 | B18: 45883 | C18: Kabita Adhikari | D18: 9838-831701 | E18: 45881 | F18: =IF(B18-E18<=2,"New","Returning") -> New | G18: Kathmandu | H18: Cafe Cup | I18: Beverages | J18: Milk Tea | K18: 2 | L18: R-105 | M18: eSewa | O18: Cancelled | P18: =IF(O18=""," NEED REVIEW","") | R18: 34 | T18: =_xlfn.CONCAT(Table5[[#This Row],[OrderID]]," | ",Table5[[#This Row],[City]]," | ",Table5[[#This Row],[ItemName]]) -> ORD-1017 | Kathmandu | Milk Tea | U18: =UPPER(Table5[[#This Row],[City]]) -> KATHMANDU | V18: =LOWER(Table5[[#This Row],[PaymentMethod]]) -> esewa | W18: {=_xlfn.XLOOKUP(TRIM(Table5[[#This Row],[ItemName]]), TRIM(Menu_Price_List_tbl[ItemName]),Menu_Price_List_tbl[UnitPrice_NPR])} -> 60 | X18: =W18*K18 -> 120 | Y18: =_xlfn.XLOOKUP(Table5[[#This Row],[City]],City_Delivery_Fee_tbl[City],City_Delivery_Fee_tbl[BaseDeliveryFee_NPR]) -> 50 | Z18: =IF(ISBLANK(Table5[[#This Row],[PromoCode]]), 0, _xlfn.LET( _xlpm.type, _xlfn.XLOOKUP(Table5[[#This Row],[PromoCode]], Promo_Codes!$A$2:$A$9, Promo_Codes!$C$2:$C$9, "Flat"), _xlpm.val, _xlfn.XLOOKUP(Table5[[#This Row],[PromoCode]], Promo_Codes!$A$2:$A$9, Promo_Codes!$D$2:$D$9, 0), IF(_xlpm.type="Percentage", Table5[[#This Row],[Order Amount]]*(_xlpm.val/100), _xlpm.val) ) ) -> 0 | AA18: =Table5[[#This Row],[Order Amount]]+Table5[[#This Row],[Delivery Fee]]-Table5[[#This Row],[Discount Amount]] -> 170 | AB18: =_xlfn.XLOOKUP(Table5[[#This Row],[RiderID]], Rider_Directory!$F$2:$F$26, Rider_Directory!$B$2:$B$26) -> Kathmandu | AC18: {=_xlfn.IFS(Table5[[#This Row],[Final Amount]]<500, "Small", Table5[[#This Row],[Final Amount]]<=1000, "Medium", Table5[[#This Row],[Final Amount]]>1000, "Large")} -> Small | AD18: =_xlfn.LET(_xlpm.expiry,_xlfn.XLOOKUP(Table5[[#This Row],[PromoCode]],Promo_Codes!$A$2:$A$9,Promo_Codes!$F$2:$F$9,DATE(2099,1,1)),IF(Table5[[#This Row],[OrderDate]]>_xlpm.expiry,"Expired Code Used","Valid")) -> Valid
A19: ORD-1018 | B19: 45884 | C19: Nisha Thapa | D19: 9858-649208 | E19: 45787 | F19: =IF(B19-E19<=2,"New","Returning") -> Returning | G19: Kathmandu | H19: Bhatti Sekuwa Corner | I19: Sekuwa | J19: Buff Sekuwa | K19: 1 | L19: R-106 | M19: Khalti | O19: Delivered | P19: =IF(O19=""," NEED REVIEW","") | Q19: 5 | R19: 26 | T19: =_xlfn.CONCAT(Table5[[#This Row],[OrderID]]," | ",Table5[[#This Row],[City]]," | ",Table5[[#This Row],[ItemName]]) -> ORD-1018 | Kathmandu | Buff Sekuwa | U19: =UPPER(Table5[[#This Row],[City]]) -> KATHMANDU | V19: =LOWER(Table5[[#This Row],[PaymentMethod]]) -> khalti | W19: {=_xlfn.XLOOKUP(TRIM(Table5[[#This Row],[ItemName]]), TRIM(Menu_Price_List_tbl[ItemName]),Menu_Price_List_tbl[UnitPrice_NPR])} -> 380 | X19: =W19*K19 -> 380 | Y19: =_xlfn.XLOOKUP(Table5[[#This Row],[City]],City_Delivery_Fee_tbl[City],City_Delivery_Fee_tbl[BaseDeliveryFee_NPR]) -> 50 | Z19: =IF(ISBLANK(Table5[[#This Row],[PromoCode]]), 0, _xlfn.LET( _xlpm.type, _xlfn.XLOOKUP(Table5[[#This Row],[PromoCode]], Promo_Codes!$A$2:$A$9, Promo_Codes!$C$2:$C$9, "Flat"), _xlpm.val, _xlfn.XLOOKUP(Table5[[#This Row],[PromoCode]], Promo_Codes!$A$2:$A$9, Promo_Codes!$D$2:$D$9, 0), IF(_xlpm.type="Percentage", Table5[[#This Row],[Order Amount]]*(_xlpm.val/100), _xlpm.val) ) ) -> 0 | AA19: =Table5[[#This Row],[Order Amount]]+Table5[[#This Row],[Delivery Fee]]-Table5[[#This Row],[Discount Amount]] -> 430 | AB19: =_xlfn.XLOOKUP(Table5[[#This Row],[RiderID]], Rider_Directory!$F$2:$F$26, Rider_Directory!$B$2:$B$26) -> Kathmandu | AC19: {=_xlfn.IFS(Table5[[#This Row],[Final Amount]]<500, "Small", Table5[[#This Row],[Final Amount]]<=1000, "Medium", Table5[[#This Row],[Final Amount]]>1000, "Large")} -> Small | AD19: =_xlfn.LET(_xlpm.expiry,_xlfn.XLOOKUP(Table5[[#This Row],[PromoCode]],Promo_Codes!$A$2:$A$9,Promo_Codes!$F$2:$F$9,DATE(2099,1,1)),IF(Table5[[#This Row],[OrderDate]]>_xlpm.expiry,"Expired Code Used","Valid")) -> Valid
A20: ORD-1019 | B20: 45885 | C20: Ramesh Tamang | D20: 9868-656355 | E20: 45885 | F20: =IF(B20-E20<=2,"New","Returning") -> New | G20: Kathmandu | H20: Yeti Newari Bhoj | I20: Newari Khana | J20: Sukuti Sandheko | K20: 3 | L20: R-101 | M20: eSewa | O20: Delivered | P20: =IF(O20=""," NEED REVIEW","") | Q20: 4 | R20: 32 | T20: =_xlfn.CONCAT(Table5[[#This Row],[OrderID]]," | ",Table5[[#This Row],[City]]," | ",Table5[[#This Row],[ItemName]]) -> ORD-1019 | Kathmandu | Sukuti Sandheko | U20: =UPPER(Table5[[#This Row],[City]]) -> KATHMANDU | V20: =LOWER(Table5[[#This Row],[PaymentMethod]]) -> esewa | W20: {=_xlfn.XLOOKUP(TRIM(Table5[[#This Row],[ItemName]]), TRIM(Menu_Price_List_tbl[ItemName]),Menu_Price_List_tbl[UnitPrice_NPR])} -> 350 | X20: =W20*K20 -> 1050 | Y20: =_xlfn.XLOOKUP(Table5[[#This Row],[City]],City_Delivery_Fee_tbl[City],City_Delivery_Fee_tbl[BaseDeliveryFee_NPR]) -> 50 | Z20: =IF(ISBLANK(Table5[[#This Row],[PromoCode]]), 0, _xlfn.LET( _xlpm.type, _xlfn.XLOOKUP(Table5[[#This Row],[PromoCode]], Promo_Codes!$A$2:$A$9, Promo_Codes!$C$2:$C$9, "Flat"), _xlpm.val, _xlfn.XLOOKUP(Table5[[#This Row],[PromoCode]], Promo_Codes!$A$2:$A$9, Promo_Codes!$D$2:$D$9, 0), IF(_xlpm.type="Percentage", Table5[[#This Row],[Order Amount]]*(_xlpm.val/100), _xlpm.val) ) ) -> 0 | AA20: =Table5[[#This Row],[Order Amount]]+Table5[[#This Row],[Delivery Fee]]-Table5[[#This Row],[Discount Amount]] -> 1100 | AB20: =_xlfn.XLOOKUP(Table5[[#This Row],[RiderID]], Rider_Directory!$F$2:$F$26, Rider_Directory!$B$2:$B$26) -> Kathmandu | AC20: {=_xlfn.IFS(Table5[[#This Row],[Final Amount]]<500, "Small", Table5[[#This Row],[Final Amount]]<=1000, "Medium", Table5[[#This Row],[Final Amount]]>1000, "Large")} -> Large | AD20: =_xlfn.LET(_xlpm.expiry,_xlfn.XLOOKUP(Table5[[#This Row],[PromoCode]],Promo_Codes!$A$2:$A$9,Promo_Codes!$F$2:$F$9,DATE(2099,1,1)),IF(Table5[[#This Row],[OrderDate]]>_xlpm.expiry,"Expired Code Used","Valid")) -> Valid
A21: ORD-1020 | B21: 45886 | C21: Kiran Maharjan | D21: 9817-180023 | E21: 45886 | F21: =IF(B21-E21<=2,"New","Returning") -> New | G21: Chitwan | H21: Fast Bites | I21: Fast Food | J21: Chicken Burger | K21: 3 | L21: R-123 | M21: eSewa | O21: Returned | P21: =IF(O21=""," NEED REVIEW","") | R21: 56 | S21: fine I guess | T21: =_xlfn.CONCAT(Table5[[#This Row],[OrderID]]," | ",Table5[[#This Row],[City]]," | ",Table5[[#This Row],[ItemName]]) -> ORD-1020 | Chitwan | Chicken Burger | U21: =UPPER(Table5[[#This Row],[City]]) -> CHITWAN | V21: =LOWER(Table5[[#This Row],[PaymentMethod]]) -> esewa | W21: {=_xlfn.XLOOKUP(TRIM(Table5[[#This Row],[ItemName]]), TRIM(Menu_Price_List_tbl[ItemName]),Menu_Price_List_tbl[UnitPrice_NPR])} -> 280 | X21: =W21*K21 -> 840 | Y21: =_xlfn.XLOOKUP(Table5[[#This Row],[City]],City_Delivery_Fee_tbl[City],City_Delivery_Fee_tbl[BaseDeliveryFee_NPR]) -> 80 | Z21: =IF(ISBLANK(Table5[[#This Row],[PromoCode]]), 0, _xlfn.LET( _xlpm.type, _xlfn.XLOOKUP(Table5[[#This Row],[PromoCode]], Promo_Codes!$A$2:$A$9, Promo_Codes!$C$2:$C$9, "Flat"), _xlpm.val, _xlfn.XLOOKUP(Table5[[#This Row],[PromoCode]], Promo_Codes!$A$2:$A$9, Promo_Codes!$D$2:$D$9, 0), IF(_xlpm.type="Percentage", Table5[[#This Row],[Order Amount]]*(_xlpm.val/100), _xlpm.val) ) ) -> 0 | AA21: =Table5[[#This Row],[Order Amount]]+Table5[[#This Row],[Delivery Fee]]-Table5[[#This Row],[Discount Amount]] -> 920 | AB21: =_xlfn.XLOOKUP(Table5[[#This Row],[RiderID]], Rider_Directory!$F$2:$F$26, Rider_Directory!$B$2:$B$26) -> Chitwan | AC21: {=_xlfn.IFS(Table5[[#This Row],[Final Amount]]<500, "Small", Table5[[#This Row],[Final Amount]]<=1000, "Medium", Table5[[#This Row],[Final Amount]]>1000, "Large")} -> Medium | AD21: =_xlfn.LET(_xlpm.expiry,_xlfn.XLOOKUP(Table5[[#This Row],[PromoCode]],Promo_Codes!$A$2:$A$9,Promo_Codes!$F$2:$F$9,DATE(2099,1,1)),IF(Table5[[#This Row],[OrderDate]]>_xlpm.expiry,"Expired Code Used","Valid")) -> Valid
A22: ORD-1021 | B22: 45886 | C22: Rohit Limbu | D22: 9850-201462 | E22: 45874 | F22: =IF(B22-E22<=2,"New","Returning") -> Returning | G22: Bhaktapur | H22: Chiya Adda | I22: Beverages | J22: Black Coffee | K22: 1 | L22: R-111 | M22: Khalti | O22: Delivered | P22: =IF(O22=""," NEED REVIEW","") | Q22: 4 | R22: 24 | T22: =_xlfn.CONCAT(Table5[[#This Row],[OrderID]]," | ",Table5[[#This Row],[City]]," | ",Table5[[#This Row],[ItemName]]) -> ORD-1021 | Bhaktapur | Black Coffee | U22: =UPPER(Table5[[#This Row],[City]]) -> BHAKTAPUR | V22: =LOWER(Table5[[#This Row],[PaymentMethod]]) -> khalti | W22: {=_xlfn.XLOOKUP(TRIM(Table5[[#This Row],[ItemName]]), TRIM(Menu_Price_List_tbl[ItemName]),Menu_Price_List_tbl[UnitPrice_NPR])} -> 90 | X22: =W22*K22 -> 90 | Y22: =_xlfn.XLOOKUP(Table5[[#This Row],[City]],City_Delivery_Fee_tbl[City],City_Delivery_Fee_tbl[BaseDeliveryFee_NPR]) -> 55 | Z22: =IF(ISBLANK(Table5[[#This Row],[PromoCode]]), 0, _xlfn.LET( _xlpm.type, _xlfn.XLOOKUP(Table5[[#This Row],[PromoCode]], Promo_Codes!$A$2:$A$9, Promo_Codes!$C$2:$C$9, "Flat"), _xlpm.val, _xlfn.XLOOKUP(Table5[[#This Row],[PromoCode]], Promo_Codes!$A$2:$A$9, Promo_Codes!$D$2:$D$9, 0), IF(_xlpm.type="Percentage", Table5[[#This Row],[Order Amount]]*(_xlpm.val/100), _xlpm.val) ) ) -> 0 | AA22: =Table5[[#This Row],[Order Amount]]+Table5[[#This Row],[Delivery Fee]]-Table5[[#This Row],[Discount Amount]] -> 145 | AB22: =_xlfn.XLOOKUP(Table5[[#This Row],[RiderID]], Rider_Directory!$F$2:$F$26, Rider_Directory!$B$2:$B$26) -> Bhaktapur | AC22: {=_xlfn.IFS(Table5[[#This Row],[Final Amount]]<500, "Small", Table5[[#This Row],[Final Amount]]<=1000, "Medium", Table5[[#This Row],[Final Amount]]>1000, "Large")} -> Small | AD22: =_xlfn.LET(_xlpm.expiry,_xlfn.XLOOKUP(Table5[[#This Row],[PromoCode]],Promo_Codes!$A$2:$A$9,Promo_Codes!$F$2:$F$9,DATE(2099,1,1)),IF(Table5[[#This Row],[OrderDate]]>_xlpm.expiry,"Expired Code Used","Valid")) -> Valid
A23: ORD-1022 | B23: 45887 | C23: Kiran Bhattarai | D23: 9851-732904 | E23: 45886 | F23: =IF(B23-E23<=2,"New","Returning") -> New | G23: Kathmandu | H23: Thakali Ghar | I23: Thakali Set | J23: Mutton Thakali Set | K23: 3 | L23: R-105 | M23: eSewa | O23: Returned | P23: =IF(O23=""," NEED REVIEW","") | R23: 23 | S23: fine I guess | T23: =_xlfn.CONCAT(Table5[[#This Row],[OrderID]]," | ",Table5[[#This Row],[City]]," | ",Table5[[#This Row],[ItemName]]) -> ORD-1022 | Kathmandu | Mutton Thakali Set | U23: =UPPER(Table5[[#This Row],[City]]) -> KATHMANDU | V23: =LOWER(Table5[[#This Row],[PaymentMethod]]) -> esewa | W23: {=_xlfn.XLOOKUP(TRIM(Table5[[#This Row],[ItemName]]), TRIM(Menu_Price_List_tbl[ItemName]),Menu_Price_List_tbl[UnitPrice_NPR])} -> 650 | X23: =W23*K23 -> 1950 | Y23: =_xlfn.XLOOKUP(Table5[[#This Row],[City]],City_Delivery_Fee_tbl[City],City_Delivery_Fee_tbl[BaseDeliveryFee_NPR]) -> 50 | Z23: =IF(ISBLANK(Table5[[#This Row],[PromoCode]]), 0, _xlfn.LET( _xlpm.type, _xlfn.XLOOKUP(Table5[[#This Row],[PromoCode]], Promo_Codes!$A$2:$A$9, Promo_Codes!$C$2:$C$9, "Flat"), _xlpm.val, _xlfn.XLOOKUP(Table5[[#This Row],[PromoCode]], Promo_Codes!$A$2:$A$9, Promo_Codes!$D$2:$D$9, 0), IF(_xlpm.type="Percentage", Table5[[#This Row],[Order Amount]]*(_xlpm.val/100), _xlpm.val) ) ) -> 0 | AA23: =Table5[[#This Row],[Order Amount]]+Table5[[#This Row],[Delivery Fee]]-Table5[[#This Row],[Discount Amount]] -> 2000 | AB23: =_xlfn.XLOOKUP(Table5[[#This Row],[RiderID]], Rider_Directory!$F$2:$F$26, Rider_Directory!$B$2:$B$26) -> Kathmandu | AC23: {=_xlfn.IFS(Table5[[#This Row],[Final Amount]]<500, "Small", Table5[[#This Row],[Final Amount]]<=1000, "Medium", Table5[[#This Row],[Final Amount]]>1000, "Large")} -> Large | AD23: =_xlfn.LET(_xlpm.expiry,_xlfn.XLOOKUP(Table5[[#This Row],[PromoCode]],Promo_Codes!$A$2:$A$9,Promo_Codes!$F$2:$F$9,DATE(2099,1,1)),IF(Table5[[#This Row],[OrderDate]]>_xlpm.expiry,"Expired Code Used","Valid")) -> Valid
A24: ORD-1023 | B24: 45888 | C24: Ramesh Bista | D24: 9860-926030 | E24: 45888 | F24: =IF(B24-E24<=2,"New","Returning") -> New | G24: Lalitpur | H24: Quick Snacks Corner | I24: Fast Food | J24: veg fried rice | K24: 3 | L24: R-108 | M24: Khalti | O24: Delivered | P24: =IF(O24=""," NEED REVIEW","") | Q24: 5 | R24: 37 | T24: =_xlfn.CONCAT(Table5[[#This Row],[OrderID]]," | ",Table5[[#This Row],[City]]," | ",Table5[[#This Row],[ItemName]]) -> ORD-1023 | Lalitpur | veg fried rice | U24: =UPPER(Table5[[#This Row],[City]]) -> LALITPUR | V24: =LOWER(Table5[[#This Row],[PaymentMethod]]) -> khalti | W24: {=_xlfn.XLOOKUP(TRIM(Table5[[#This Row],[ItemName]]), TRIM(Menu_Price_List_tbl[ItemName]),Menu_Price_List_tbl[UnitPrice_NPR])} -> 220 | X24: =W24*K24 -> 660 | Y24: =_xlfn.XLOOKUP(Table5[[#This Row],[City]],City_Delivery_Fee_tbl[City],City_Delivery_Fee_tbl[BaseDeliveryFee_NPR]) -> 50 | Z24: =IF(ISBLANK(Table5[[#This Row],[PromoCode]]), 0, _xlfn.LET( _xlpm.type, _xlfn.XLOOKUP(Table5[[#This Row],[PromoCode]], Promo_Codes!$A$2:$A$9, Promo_Codes!$C$2:$C$9, "Flat"), _xlpm.val, _xlfn.XLOOKUP(Table5[[#This Row],[PromoCode]], Promo_Codes!$A$2:$A$9, Promo_Codes!$D$2:$D$9, 0), IF(_xlpm.type="Percentage", Table5[[#This Row],[Order Amount]]*(_xlpm.val/100), _xlpm.val) ) ) -> 0 | AA24: =Table5[[#This Row],[Order Amount]]+Table5[[#This Row],[Delivery Fee]]-Table5[[#This Row],[Discount Amount]] -> 710 | AB24: =_xlfn.XLOOKUP(Table5[[#This Row],[RiderID]], Rider_Directory!$F$2:$F$26, Rider_Directory!$B$2:$B$26) -> Lalitpur | AC24: {=_xlfn.IFS(Table5[[#This Row],[Final Amount]]<500, "Small", Table5[[#This Row],[Final Amount]]<=1000, "Medium", Table5[[#This Row],[Final Amount]]>1000, "Large")} -> Medium | AD24: =_xlfn.LET(_xlpm.expiry,_xlfn.XLOOKUP(Table5[[#This Row],[PromoCode]],Promo_Codes!$A$2:$A$9,Promo_Codes!$F$2:$F$9,DATE(2099,1,1)),IF(Table5[[#This Row],[OrderDate]]>_xlpm.expiry,"Expired Code Used","Valid")) -> Valid
A25: ORD-1024 | B25: 45889 | C25: Gopal Karki | D25: 9869-919220 | E25: 45888 | F25: =IF(B25-E25<=2,"New","Returning") -> New | G25: Kathmandu | H25: Quick Snacks Corner | I25: Fast Food | J25: chicken burger | K25: 2 | L25: R-105 | M25: IME Pay | O25: Returned | P25: =IF(O25=""," NEED REVIEW","") | R25: 31 | T25: =_xlfn.CONCAT(Table5[[#This Row],[OrderID]]," | ",Table5[[#This Row],[City]]," | ",Table5[[#This Row],[ItemName]]) -> ORD-1024 | Kathmandu | chicken burger | U25: =UPPER(Table5[[#This Row],[City]]) -> KATHMANDU | V25: =LOWER(Table5[[#This Row],[PaymentMethod]]) -> ime pay | W25: {=_xlfn.XLOOKUP(TRIM(Table5[[#This Row],[ItemName]]), TRIM(Menu_Price_List_tbl[ItemName]),Menu_Price_List_tbl[UnitPrice_NPR])} -> 280 | X25: =W25*K25 -> 560 | Y25: =_xlfn.XLOOKUP(Table5[[#This Row],[City]],City_Delivery_Fee_tbl[City],City_Delivery_Fee_tbl[BaseDeliveryFee_NPR]) -> 50 | Z25: =IF(ISBLANK(Table5[[#This Row],[PromoCode]]), 0, _xlfn.LET( _xlpm.type, _xlfn.XLOOKUP(Table5[[#This Row],[PromoCode]], Promo_Codes!$A$2:$A$9, Promo_Codes!$C$2:$C$9, "Flat"), _xlpm.val, _xlfn.XLOOKUP(Table5[[#This Row],[PromoCode]], Promo_Codes!$A$2:$A$9, Promo_Codes!$D$2:$D$9, 0), IF(_xlpm.type="Percentage", Table5[[#This Row],[Order Amount]]*(_xlpm.val/100), _xlpm.val) ) ) -> 0 | AA25: =Table5[[#This Row],[Order Amount]]+Table5[[#This Row],[Delivery Fee]]-Table5[[#This Row],[Discount Amount]] -> 610 | AB25: =_xlfn.XLOOKUP(Table5[[#This Row],[RiderID]], Rider_Directory!$F$2:$F$26, Rider_Directory!$B$2:$B$26) -> Kathmandu | AC25: {=_xlfn.IFS(Table5[[#This Row],[Final Amount]]<500, "Small", Table5[[#This Row],[Final Amount]]<=1000, "Medium", Table5[[#This Row],[Final Amount]]>1000, "Large")} -> Medium | AD25: =_xlfn.LET(_xlpm.expiry,_xlfn.XLOOKUP(Table5[[#This Row],[PromoCode]],Promo_Codes!$A$2:$A$9,Promo_Codes!$F$2:$F$9,DATE(2099,1,1)),IF(Table5[[#This Row],[OrderDate]]>_xlpm.expiry,"Expired Code Used","Valid")) -> Valid
A26: ORD-1025 | B26: 45890 | C26: Rina Adhikari | D26: 9867-272042 | E26: 45743 | F26: =IF(B26-E26<=2,"New","Returning") -> Returning | G26: Biratnagar | H26: Cafe Cup | I26: Beverages | J26: MANGO JUICE | K26: 1 | L26: R-117 | M26: Khalti | O26: Delivered | P26: =IF(O26=""," NEED REVIEW","") | Q26: 5 | R26: 34 | S26: quality was great as always | T26: =_xlfn.CONCAT(Table5[[#This Row],[OrderID]]," | ",Table5[[#This Row],[City]]," | ",Table5[[#This Row],[ItemName]]) -> ORD-1025 | Biratnagar | MANGO JUICE | U26: =UPPER(Table5[[#This Row],[City]]) -> BIRATNAGAR | V26: =LOWER(Table5[[#This Row],[PaymentMethod]]) -> khalti | W26: {=_xlfn.XLOOKUP(TRIM(Table5[[#This Row],[ItemName]]), TRIM(Menu_Price_List_tbl[ItemName]),Menu_Price_List_tbl[UnitPrice_NPR])} -> 120 | X26: =W26*K26 -> 120 | Y26: =_xlfn.XLOOKUP(Table5[[#This Row],[City]],City_Delivery_Fee_tbl[City],City_Delivery_Fee_tbl[BaseDeliveryFee_NPR]) -> 90 | Z26: =IF(ISBLANK(Table5[[#This Row],[PromoCode]]), 0, _xlfn.LET( _xlpm.type, _xlfn.XLOOKUP(Table5[[#This Row],[PromoCode]], Promo_Codes!$A$2:$A$9, Promo_Codes!$C$2:$C$9, "Flat"), _xlpm.val, _xlfn.XLOOKUP(Table5[[#This Row],[PromoCode]], Promo_Codes!$A$2:$A$9, Promo_Codes!$D$2:$D$9, 0), IF(_xlpm.type="Percentage", Table5[[#This Row],[Order Amount]]*(_xlpm.val/100), _xlpm.val) ) ) -> 0 | AA26: =Table5[[#This Row],[Order Amount]]+Table5[[#This Row],[Delivery Fee]]-Table5[[#This Row],[Discount Amount]] -> 210 | AB26: =_xlfn.XLOOKUP(Table5[[#This Row],[RiderID]], Rider_Directory!$F$2:$F$26, Rider_Directory!$B$2:$B$26) -> Biratnagar | AC26: {=_xlfn.IFS(Table5[[#This Row],[Final Amount]]<500, "Small", Table5[[#This Row],[Final Amount]]<=1000, "Medium", Table5[[#This Row],[Final Amount]]>1000, "Large")} -> Small | AD26: =_xlfn.LET(_xlpm.expiry,_xlfn.XLOOKUP(Table5[[#This Row],[PromoCode]],Promo_Codes!$A$2:$A$9,Promo_Codes!$F$2:$F$9,DATE(2099,1,1)),IF(Table5[[#This Row],[OrderDate]]>_xlpm.expiry,"Expired Code Used","Valid")) -> Valid
A27: ORD-1026 | B27: 45890 | C27: Pradeep Maharjan | D27: 9848-372616 | E27: 45889 | F27: =IF(B27-E27<=2,"New","Returning") -> New | G27: Pokhara | H27: Fast Bites | I27: Fast Food | J27: Chicken Chowmein | K27: 1 | L27: R-112 | M27: IME Pay | O27: Delivered | P27: =IF(O27=""," NEED REVIEW","") | Q27: 5 | R27: 23 | S27: packaging was nice | T27: =_xlfn.CONCAT(Table5[[#This Row],[OrderID]]," | ",Table5[[#This Row],[City]]," | ",Table5[[#This Row],[ItemName]]) -> ORD-1026 | Pokhara | Chicken Chowmein | U27: =UPPER(Table5[[#This Row],[City]]) -> POKHARA | V27: =LOWER(Table5[[#This Row],[PaymentMethod]]) -> ime pay | W27: {=_xlfn.XLOOKUP(TRIM(Table5[[#This Row],[ItemName]]), TRIM(Menu_Price_List_tbl[ItemName]),Menu_Price_List_tbl[UnitPrice_NPR])} -> 250 | X27: =W27*K27 -> 250 | Y27: =_xlfn.XLOOKUP(Table5[[#This Row],[City]],City_Delivery_Fee_tbl[City],City_Delivery_Fee_tbl[BaseDeliveryFee_NPR]) -> 70 | Z27: =IF(ISBLANK(Table5[[#This Row],[PromoCode]]), 0, _xlfn.LET( _xlpm.type, _xlfn.XLOOKUP(Table5[[#This Row],[PromoCode]], Promo_Codes!$A$2:$A$9, Promo_Codes!$C$2:$C$9, "Flat"), _xlpm.val, _xlfn.XLOOKUP(Table5[[#This Row],[PromoCode]], Promo_Codes!$A$2:$A$9, Promo_Codes!$D$2:$D$9, 0), IF(_xlpm.type="Percentage", Table5[[#This Row],[Order Amount]]*(_xlpm.val/100), _xlpm.val) ) ) -> 0 | AA27: =Table5[[#This Row],[Order Amount]]+Table5[[#This Row],[Delivery Fee]]-Table5[[#This Row],[Discount Amount]] -> 320 | AB27: =_xlfn.XLOOKUP(Table5[[#This Row],[RiderID]], Rider_Directory!$F$2:$F$26, Rider_Directory!$B$2:$B$26) -> Pokhara | AC27: {=_xlfn.IFS(Table5[[#This Row],[Final Amount]]<500, "Small", Table5[[#This Row],[Final Amount]]<=1000, "Medium", Table5[[#This Row],[Final Amount]]>1000, "Large")} -> Small | AD27: =_xlfn.LET(_xlpm.expiry,_xlfn.XLOOKUP(Table5[[#This Row],[PromoCode]],Promo_Codes!$A$2:$A$9,Promo_Codes!$F$2:$F$9,DATE(2099,1,1)),IF(Table5[[#This Row],[OrderDate]]>_xlpm.expiry,"Expired Code Used","Valid")) -> Valid
A28: ORD-1027 | B28: 45891 | C28: Sagar Poudel | D28: 9896-937293 | E28: 45891 | F28: =IF(B28-E28<=2,"New","Returning") -> New | G28: Kathmandu | H28: Quick Snacks Corner | I28: Fast Food | J28: Chicken Chowmein | K28: 3 | L28: R-102 | M28: Khalti | N28: MONSOON30 | O28: Delivered | P28: =IF(O28=""," NEED REVIEW","") | R28: 32 | T28: =_xlfn.CONCAT(Table5[[#This Row],[OrderID]]," | ",Table5[[#This Row],[City]]," | ",Table5[[#This Row],[ItemName]]) -> ORD-1027 | Kathmandu | Chicken Chowmein | U28: =UPPER(Table5[[#This Row],[City]]) -> KATHMANDU | V28: =LOWER(Table5[[#This Row],[PaymentMethod]]) -> khalti | W28: {=_xlfn.XLOOKUP(TRIM(Table5[[#This Row],[ItemName]]), TRIM(Menu_Price_List_tbl[ItemName]),Menu_Price_List_tbl[UnitPrice_NPR])} -> 250 | X28: =W28*K28 -> 750 | Y28: =_xlfn.XLOOKUP(Table5[[#This Row],[City]],City_Delivery_Fee_tbl[City],City_Delivery_Fee_tbl[BaseDeliveryFee_NPR]) -> 50 | Z28: =IF(ISBLANK(Table5[[#This Row],[PromoCode]]), 0, _xlfn.LET( _xlpm.type, _xlfn.XLOOKUP(Table5[[#This Row],[PromoCode]], Promo_Codes!$A$2:$A$9, Promo_Codes!$C$2:$C$9, "Flat"), _xlpm.val, _xlfn.XLOOKUP(Table5[[#This Row],[PromoCode]], Promo_Codes!$A$2:$A$9, Promo_Codes!$D$2:$D$9, 0), IF(_xlpm.type="Percentage", Table5[[#This Row],[Order Amount]]*(_xlpm.val/100), _xlpm.val) ) ) -> 30 | AA28: =Table5[[#This Row],[Order Amount]]+Table5[[#This Row],[Delivery Fee]]-Table5[[#This Row],[Discount Amount]] -> 770 | AB28: =_xlfn.XLOOKUP(Table5[[#This Row],[RiderID]], Rider_Directory!$F$2:$F$26, Rider_Directory!$B$2:$B$26) -> Kathmandu | AC28: {=_xlfn.IFS(Table5[[#This Row],[Final Amount]]<500, "Small", Table5[[#This Row],[Final Amount]]<=1000, "Medium", Table5[[#This Row],[Final Amount]]>1000, "Large")} -> Medium | AD28: =_xlfn.LET(_xlpm.expiry,_xlfn.XLOOKUP(Table5[[#This Row],[PromoCode]],Promo_Codes!$A$2:$A$9,Promo_Codes!$F$2:$F$9,DATE(2099,1,1)),IF(Table5[[#This Row],[OrderDate]]>_xlpm.expiry,"Expired Code Used","Valid")) -> Valid
A29: ORD-1028 | B29: 45892 | C29: Kabita Limbu | D29: 9891-564041 | E29: 45891 | F29: =IF(B29-E29<=2,"New","Returning") -> New | G29: Kathmandu | H29: Newa Kitchen | I29: Newari Khana | J29: Choila (Buff) | K29: 1 | L29: R-104 | M29: Cash on Delivery | O29: Delivered | P29: =IF(O29=""," NEED REVIEW","") | Q29: 4 | R29: 27 | S29: Fast delivery today | T29: =_xlfn.CONCAT(Table5[[#This Row],[OrderID]]," | ",Table5[[#This Row],[City]]," | ",Table5[[#This Row],[ItemName]]) -> ORD-1028 | Kathmandu | Choila (Buff) | U29: =UPPER(Table5[[#This Row],[City]]) -> KATHMANDU | V29: =LOWER(Table5[[#This Row],[PaymentMethod]]) -> cash on delivery | W29: {=_xlfn.XLOOKUP(TRIM(Table5[[#This Row],[ItemName]]), TRIM(Menu_Price_List_tbl[ItemName]),Menu_Price_List_tbl[UnitPrice_NPR])} -> 320 | X29: =W29*K29 -> 320 | Y29: =_xlfn.XLOOKUP(Table5[[#This Row],[City]],City_Delivery_Fee_tbl[City],City_Delivery_Fee_tbl[BaseDeliveryFee_NPR]) -> 50 | Z29: =IF(ISBLANK(Table5[[#This Row],[PromoCode]]), 0, _xlfn.LET( _xlpm.type, _xlfn.XLOOKUP(Table5[[#This Row],[PromoCode]], Promo_Codes!$A$2:$A$9, Promo_Codes!$C$2:$C$9, "Flat"), _xlpm.val, _xlfn.XLOOKUP(Table5[[#This Row],[PromoCode]], Promo_Codes!$A$2:$A$9, Promo_Codes!$D$2:$D$9, 0), IF(_xlpm.type="Percentage", Table5[[#This Row],[Order Amount]]*(_xlpm.val/100), _xlpm.val) ) ) -> 0 | AA29: =Table5[[#This Row],[Order Amount]]+Table5[[#This Row],[Delivery Fee]]-Table5[[#This Row],[Discount Amount]] -> 370 | AB29: =_xlfn.XLOOKUP(Table5[[#This Row],[RiderID]], Rider_Directory!$F$2:$F$26, Rider_Directory!$B$2:$B$26) -> Kathmandu | AC29: {=_xlfn.IFS(Table5[[#This Row],[Final Amount]]<500, "Small", Table5[[#This Row],[Final Amount]]<=1000, "Medium", Table5[[#This Row],[Final Amount]]>1000, "Large")} -> Small | AD29: =_xlfn.LET(_xlpm.expiry,_xlfn.XLOOKUP(Table5[[#This Row],[PromoCode]],Promo_Codes!$A$2:$A$9,Promo_Codes!$F$2:$F$9,DATE(2099,1,1)),IF(Table5[[#This Row],[OrderDate]]>_xlpm.expiry,"Expired Code Used","Valid")) -> Valid
A30: ORD-1029 | B30: 45893 | C30: Sujan Acharya | D30: 9855-459045 | E30: 45701 | F30: =IF(B30-E30<=2,"New","Returning") -> Returning | G30: Lalitpur | H30: Yeti Newari Bhoj | I30: Newari Khana | J30: Choila (Buff) | K30: 1 | L30: R-108 | M30: Khalti | O30: Delivered | P30: =IF(O30=""," NEED REVIEW","") | Q30: 3 | R30: 21 | T30: =_xlfn.CONCAT(Table5[[#This Row],[OrderID]]," | ",Table5[[#This Row],[City]]," | ",Table5[[#This Row],[ItemName]]) -> ORD-1029 | Lalitpur | Choila (Buff) | U30: =UPPER(Table5[[#This Row],[City]]) -> LALITPUR | V30: =LOWER(Table5[[#This Row],[PaymentMethod]]) -> khalti | W30: {=_xlfn.XLOOKUP(TRIM(Table5[[#This Row],[ItemName]]), TRIM(Menu_Price_List_tbl[ItemName]),Menu_Price_List_tbl[UnitPrice_NPR])} -> 320 | X30: =W30*K30 -> 320 | Y30: =_xlfn.XLOOKUP(Table5[[#This Row],[City]],City_Delivery_Fee_tbl[City],City_Delivery_Fee_tbl[BaseDeliveryFee_NPR]) -> 50 | Z30: =IF(ISBLANK(Table5[[#This Row],[PromoCode]]), 0, _xlfn.LET( _xlpm.type, _xlfn.XLOOKUP(Table5[[#This Row],[PromoCode]], Promo_Codes!$A$2:$A$9, Promo_Codes!$C$2:$C$9, "Flat"), _xlpm.val, _xlfn.XLOOKUP(Table5[[#This Row],[PromoCode]], Promo_Codes!$A$2:$A$9, Promo_Codes!$D$2:$D$9, 0), IF(_xlpm.type="Percentage", Table5[[#This Row],[Order Amount]]*(_xlpm.val/100), _xlpm.val) ) ) -> 0 | AA30: =Table5[[#This Row],[Order Amount]]+Table5[[#This Row],[Delivery Fee]]-Table5[[#This Row],[Discount Amount]] -> 370 | AB30: =_xlfn.XLOOKUP(Table5[[#This Row],[RiderID]], Rider_Directory!$F$2:$F$26, Rider_Directory!$B$2:$B$26) -> Lalitpur | AC30: {=_xlfn.IFS(Table5[[#This Row],[Final Amount]]<500, "Small", Table5[[#This Row],[Final Amount]]<=1000, "Medium", Table5[[#This Row],[Final Amount]]>1000, "Large")} -> Small | AD30: =_xlfn.LET(_xlpm.expiry,_xlfn.XLOOKUP(Table5[[#This Row],[PromoCode]],Promo_Codes!$A$2:$A$9,Promo_Codes!$F$2:$F$9,DATE(2099,1,1)),IF(Table5[[#This Row],[OrderDate]]>_xlpm.expiry,"Expired Code Used","Valid")) -> Valid
A31: ORD-1030 | B31: 45894 | C31: Manisha Gurung | D31: 9891-390996 | E31: 45892 | F31: =IF(B31-E31<=2,"New","Returning") -> New | G31: Lalitpur | H31: Himalayan Thakali Kitchen | I31: Thakali Set | J31: Veg Thakali Set | K31: 1 | L31: R-109 | M31: eSewa | N31: WEEKEND10 | O31: Delivered | P31: =IF(O31=""," NEED REVIEW","") | Q31: 5 | R31: 25 | S31: best momo in town | T31: =_xlfn.CONCAT(Table5[[#This Row],[OrderID]]," | ",Table5[[#This Row],[City]]," | ",Table5[[#This Row],[ItemName]]) -> ORD-1030 | Lalitpur | Veg Thakali Set | U31: =UPPER(Table5[[#This Row],[City]]) -> LALITPUR | V31: =LOWER(Table5[[#This Row],[PaymentMethod]]) -> esewa | W31: {=_xlfn.XLOOKUP(TRIM(Table5[[#This Row],[ItemName]]), TRIM(Menu_Price_List_tbl[ItemName]),Menu_Price_List_tbl[UnitPrice_NPR])} -> 380 | X31: =W31*K31 -> 380 | Y31: =_xlfn.XLOOKUP(Table5[[#This Row],[City]],City_Delivery_Fee_tbl[City],City_Delivery_Fee_tbl[BaseDeliveryFee_NPR]) -> 50 | Z31: =IF(ISBLANK(Table5[[#This Row],[PromoCode]]), 0, _xlfn.LET( _xlpm.type, _xlfn.XLOOKUP(Table5[[#This Row],[PromoCode]], Promo_Codes!$A$2:$A$9, Promo_Codes!$C$2:$C$9, "Flat"), _xlpm.val, _xlfn.XLOOKUP(Table5[[#This Row],[PromoCode]], Promo_Codes!$A$2:$A$9, Promo_Codes!$D$2:$D$9, 0), IF(_xlpm.type="Percentage", Table5[[#This Row],[Order Amount]]*(_xlpm.val/100), _xlpm.val) ) ) -> 38 | AA31: =Table5[[#This Row],[Order Amount]]+Table5[[#This Row],[Delivery Fee]]-Table5[[#This Row],[Discount Amount]] -> 392 | AB31: =_xlfn.XLOOKUP(Table5[[#This Row],[RiderID]], Rider_Directory!$F$2:$F$26, Rider_Directory!$B$2:$B$26) -> Lalitpur | AC31: {=_xlfn.IFS(Table5[[#This Row],[Final Amount]]<500, "Small", Table5[[#This Row],[Final Amount]]<=1000, "Medium", Table5[[#This Row],[Final Amount]]>1000, "Large")} -> Small | AD31: =_xlfn.LET(_xlpm.expiry,_xlfn.XLOOKUP(Table5[[#This Row],[PromoCode]],Promo_Codes!$A$2:$A$9,Promo_Codes!$F$2:$F$9,DATE(2099,1,1)),IF(Table5[[#This Row],[OrderDate]]>_xlpm.expiry,"Expired Code Used","Valid")) -> Valid
A32: ORD-1031 | B32: 45897 | C32: Manisha Rai | D32: 9814-913167 | E32: 45895 | F32: =IF(B32-E32<=2,"New","Returning") -> New | G32: Chitwan | H32: Quick Snacks Corner | I32: Fast Food | J32: FRENCH FRIES | K32: 1 | L32: R-123 | M32: Khalti | O32: Delivered | P32: =IF(O32=""," NEED REVIEW","") | Q32: 5 | R32: 28 | T32: =_xlfn.CONCAT(Table5[[#This Row],[OrderID]]," | ",Table5[[#This Row],[City]]," | ",Table5[[#This Row],[ItemName]]) -> ORD-1031 | Chitwan | FRENCH FRIES | U32: =UPPER(Table5[[#This Row],[City]]) -> CHITWAN | V32: =LOWER(Table5[[#This Row],[PaymentMethod]]) -> khalti | W32: {=_xlfn.XLOOKUP(TRIM(Table5[[#This Row],[ItemName]]), TRIM(Menu_Price_List_tbl[ItemName]),Menu_Price_List_tbl[UnitPrice_NPR])} -> 160 | X32: =W32*K32 -> 160 | Y32: =_xlfn.XLOOKUP(Table5[[#This Row],[City]],City_Delivery_Fee_tbl[City],City_Delivery_Fee_tbl[BaseDeliveryFee_NPR]) -> 80 | Z32: =IF(ISBLANK(Table5[[#This Row],[PromoCode]]), 0, _xlfn.LET( _xlpm.type, _xlfn.XLOOKUP(Table5[[#This Row],[PromoCode]], Promo_Codes!$A$2:$A$9, Promo_Codes!$C$2:$C$9, "Flat"), _xlpm.val, _xlfn.XLOOKUP(Table5[[#This Row],[PromoCode]], Promo_Codes!$A$2:$A$9, Promo_Codes!$D$2:$D$9, 0), IF(_xlpm.type="Percentage", Table5[[#This Row],[Order Amount]]*(_xlpm.val/100), _xlpm.val) ) ) -> 0 | AA32: =Table5[[#This Row],[Order Amount]]+Table5[[#This Row],[Delivery Fee]]-Table5[[#This Row],[Discount Amount]] -> 240 | AB32: =_xlfn.XLOOKUP(Table5[[#This Row],[RiderID]], Rider_Directory!$F$2:$F$26, Rider_Directory!$B$2:$B$26) -> Chitwan | AC32: {=_xlfn.IFS(Table5[[#This Row],[Final Amount]]<500, "Small", Table5[[#This Row],[Final Amount]]<=1000, "Medium", Table5[[#This Row],[Final Amount]]>1000, "Large")} -> Small | AD32: =_xlfn.LET(_xlpm.expiry,_xlfn.XLOOKUP(Table5[[#This Row],[PromoCode]],Promo_Codes!$A$2:$A$9,Promo_Codes!$F$2:$F$9,DATE(2099,1,1)),IF(Table5[[#This Row],[OrderDate]]>_xlpm.expiry,"Expired Code Used","Valid")) -> Valid
A33: ORD-1032 | B33: 45897 | C33: Anish Tamang | D33: 9821-387837 | E33: 45897 | F33: =IF(B33-E33<=2,"New","Returning") -> New | G33: Kathmandu | H33: Quick Snacks Corner | I33: Fast Food | J33: Chicken Pizza | K33: 1 | L33: R-105 | M33: Cash on Delivery | O33: Delivered | P33: =IF(O33=""," NEED REVIEW","") | Q33: 4 | R33: 520 | T33: =_xlfn.CONCAT(Table5[[#This Row],[OrderID]]," | ",Table5[[#This Row],[City]]," | ",Table5[[#This Row],[ItemName]]) -> ORD-1032 | Kathmandu | Chicken Pizza | U33: =UPPER(Table5[[#This Row],[City]]) -> KATHMANDU | V33: =LOWER(Table5[[#This Row],[PaymentMethod]]) -> cash on delivery | W33: {=_xlfn.XLOOKUP(TRIM(Table5[[#This Row],[ItemName]]), TRIM(Menu_Price_List_tbl[ItemName]),Menu_Price_List_tbl[UnitPrice_NPR])} -> 650 | X33: =W33*K33 -> 650 | Y33: =_xlfn.XLOOKUP(Table5[[#This Row],[City]],City_Delivery_Fee_tbl[City],City_Delivery_Fee_tbl[BaseDeliveryFee_NPR]) -> 50 | Z33: =IF(ISBLANK(Table5[[#This Row],[PromoCode]]), 0, _xlfn.LET( _xlpm.type, _xlfn.XLOOKUP(Table5[[#This Row],[PromoCode]], Promo_Codes!$A$2:$A$9, Promo_Codes!$C$2:$C$9, "Flat"), _xlpm.val, _xlfn.XLOOKUP(Table5[[#This Row],[PromoCode]], Promo_Codes!$A$2:$A$9, Promo_Codes!$D$2:$D$9, 0), IF(_xlpm.type="Percentage", Table5[[#This Row],[Order Amount]]*(_xlpm.val/100), _xlpm.val) ) ) -> 0 | AA33: =Table5[[#This Row],[Order Amount]]+Table5[[#This Row],[Delivery Fee]]-Table5[[#This Row],[Discount Amount]] -> 700 | AB33: =_xlfn.XLOOKUP(Table5[[#This Row],[RiderID]], Rider_Directory!$F$2:$F$26, Rider_Directory!$B$2:$B$26) -> Kathmandu | AC33: {=_xlfn.IFS(Table5[[#This Row],[Final Amount]]<500, "Small", Table5[[#This Row],[Final Amount]]<=1000, "Medium", Table5[[#This Row],[Final Amount]]>1000, "Large")} -> Medium | AD33: =_xlfn.LET(_xlpm.expiry,_xlfn.XLOOKUP(Table5[[#This Row],[PromoCode]],Promo_Codes!$A$2:$A$9,Promo_Codes!$F$2:$F$9,DATE(2099,1,1)),IF(Table5[[#This Row],[OrderDate]]>_xlpm.expiry,"Expired Code Used","Valid")) -> Valid
A34: ORD-1033 | B34: 45898 | C34: Ramesh Shrestha | D34: 9800-251678 | E34: 45880 | F34: =IF(B34-E34<=2,"New","Returning") -> Returning | G34: Pokhara | H34: Sweet Home Bakery | I34: Bakery | J34: Barfi (5 pcs) | K34: 2 | L34: R-113 | M34: eSewa | O34: Delivered | P34: =IF(O34=""," NEED REVIEW","") | R34: 43 | T34: =_xlfn.CONCAT(Table5[[#This Row],[OrderID]]," | ",Table5[[#This Row],[City]]," | ",Table5[[#This Row],[ItemName]]) -> ORD-1033 | Pokhara | Barfi (5 pcs) | U34: =UPPER(Table5[[#This Row],[City]]) -> POKHARA | V34: =LOWER(Table5[[#This Row],[PaymentMethod]]) -> esewa | W34: {=_xlfn.XLOOKUP(TRIM(Table5[[#This Row],[ItemName]]), TRIM(Menu_Price_List_tbl[ItemName]),Menu_Price_List_tbl[UnitPrice_NPR])} -> 220 | X34: =W34*K34 -> 440 | Y34: =_xlfn.XLOOKUP(Table5[[#This Row],[City]],City_Delivery_Fee_tbl[City],City_Delivery_Fee_tbl[BaseDeliveryFee_NPR]) -> 70 | Z34: =IF(ISBLANK(Table5[[#This Row],[PromoCode]]), 0, _xlfn.LET( _xlpm.type, _xlfn.XLOOKUP(Table5[[#This Row],[PromoCode]], Promo_Codes!$A$2:$A$9, Promo_Codes!$C$2:$C$9, "Flat"), _xlpm.val, _xlfn.XLOOKUP(Table5[[#This Row],[PromoCode]], Promo_Codes!$A$2:$A$9, Promo_Codes!$D$2:$D$9, 0), IF(_xlpm.type="Percentage", Table5[[#This Row],[Order Amount]]*(_xlpm.val/100), _xlpm.val) ) ) -> 0 | AA34: =Table5[[#This Row],[Order Amount]]+Table5[[#This Row],[Delivery Fee]]-Table5[[#This Row],[Discount Amount]] -> 510 | AB34: =_xlfn.XLOOKUP(Table5[[#This Row],[RiderID]], Rider_Directory!$F$2:$F$26, Rider_Directory!$B$2:$B$26) -> Pokhara | AC34: {=_xlfn.IFS(Table5[[#This Row],[Final Amount]]<500, "Small", Table5[[#This Row],[Final Amount]]<=1000, "Medium", Table5[[#This Row],[Final Amount]]>1000, "Large")} -> Medium | AD34: =_xlfn.LET(_xlpm.expiry,_xlfn.XLOOKUP(Table5[[#This Row],[PromoCode]],Promo_Codes!$A$2:$A$9,Promo_Codes!$F$2:$F$9,DATE(2099,1,1)),IF(Table5[[#This Row],[OrderDate]]>_xlpm.expiry,"Expired Code Used","Valid")) -> Valid
A35: ORD-1033 | B35: 45898 | C35: Ramesh Shrestha | D35: 9800-251678 | E35: 45880 | F35: =IF(B35-E35<=2,"New","Returning") -> Returning | G35: Pokhara | H35: Sweet Home Bakery | I35: Bakery | J35: Barfi (5 pcs) | K35: 3 | L35: R-113 | M35: eSewa | O35: Delivered | P35: =IF(O35=""," NEED REVIEW","") | Q35: 5 | R35: 43 | T35: =_xlfn.CONCAT(Table5[[#This Row],[OrderID]]," | ",Table5[[#This Row],[City]]," | ",Table5[[#This Row],[ItemName]]) -> ORD-1033 | Pokhara | Barfi (5 pcs) | U35: =UPPER(Table5[[#This Row],[City]]) -> POKHARA | V35: =LOWER(Table5[[#This Row],[PaymentMethod]]) -> esewa | W35: {=_xlfn.XLOOKUP(TRIM(Table5[[#This Row],[ItemName]]), TRIM(Menu_Price_List_tbl[ItemName]),Menu_Price_List_tbl[UnitPrice_NPR])} -> 220 | X35: =W35*K35 -> 660 | Y35: =_xlfn.XLOOKUP(Table5[[#This Row],[City]],City_Delivery_Fee_tbl[City],City_Delivery_Fee_tbl[BaseDeliveryFee_NPR]) -> 70 | Z35: =IF(ISBLANK(Table5[[#This Row],[PromoCode]]), 0, _xlfn.LET( _xlpm.type, _xlfn.XLOOKUP(Table5[[#This Row],[PromoCode]], Promo_Codes!$A$2:$A$9, Promo_Codes!$C$2:$C$9, "Flat"), _xlpm.val, _xlfn.XLOOKUP(Table5[[#This Row],[PromoCode]], Promo_Codes!$A$2:$A$9, Promo_Codes!$D$2:$D$9, 0), IF(_xlpm.type="Percentage", Table5[[#This Row],[Order Amount]]*(_xlpm.val/100), _xlpm.val) ) ) -> 0 | AA35: =Table5[[#This Row],[Order Amount]]+Table5[[#This Row],[Delivery Fee]]-Table5[[#This Row],[Discount Amount]] -> 730 | AB35: =_xlfn.XLOOKUP(Table5[[#This Row],[RiderID]], Rider_Directory!$F$2:$F$26, Rider_Directory!$B$2:$B$26) -> Pokhara | AC35: {=_xlfn.IFS(Table5[[#This Row],[Final Amount]]<500, "Small", Table5[[#This Row],[Final Amount]]<=1000, "Medium", Table5[[#This Row],[Final Amount]]>1000, "Large")} -> Medium | AD35: =_xlfn.LET(_xlpm.expiry,_xlfn.XLOOKUP(Table5[[#This Row],[PromoCode]],Promo_Codes!$A$2:$A$9,Promo_Codes!$F$2:$F$9,DATE(2099,1,1)),IF(Table5[[#This Row],[OrderDate]]>_xlpm.expiry,"Expired Code Used","Valid")) -> Valid
A36: ORD-1034 | B36: 45898 | C36: Sushmita Karki | D36: 9801-661318 | E36: 45898 | F36: =IF(B36-E36<=2,"New","Returning") -> New | G36: Kathmandu | H36: Yeti Newari Bhoj | I36: Newari Khana | J36: Yomari | K36: 1 | L36: R-104 | M36: Khalti | O36: Delivered | P36: =IF(O36=""," NEED REVIEW","") | Q36: 5 | R36: 15 | T36: =_xlfn.CONCAT(Table5[[#This Row],[OrderID]]," | ",Table5[[#This Row],[City]]," | ",Table5[[#This Row],[ItemName]]) -> ORD-1034 | Kathmandu | Yomari | U36: =UPPER(Table5[[#This Row],[City]]) -> KATHMANDU | V36: =LOWER(Table5[[#This Row],[PaymentMethod]]) -> khalti | W36: {=_xlfn.XLOOKUP(TRIM(Table5[[#This Row],[ItemName]]), TRIM(Menu_Price_List_tbl[ItemName]),Menu_Price_List_tbl[UnitPrice_NPR])} -> 180 | X36: =W36*K36 -> 180 | Y36: =_xlfn.XLOOKUP(Table5[[#This Row],[City]],City_Delivery_Fee_tbl[City],City_Delivery_Fee_tbl[BaseDeliveryFee_NPR]) -> 50 | Z36: =IF(ISBLANK(Table5[[#This Row],[PromoCode]]), 0, _xlfn.LET( _xlpm.type, _xlfn.XLOOKUP(Table5[[#This Row],[PromoCode]], Promo_Codes!$A$2:$A$9, Promo_Codes!$C$2:$C$9, "Flat"), _xlpm.val, _xlfn.XLOOKUP(Table5[[#This Row],[PromoCode]], Promo_Codes!$A$2:$A$9, Promo_Codes!$D$2:$D$9, 0), IF(_xlpm.type="Percentage", Table5[[#This Row],[Order Amount]]*(_xlpm.val/100), _xlpm.val) ) ) -> 0 | AA36: =Table5[[#This Row],[Order Amount]]+Table5[[#This Row],[Delivery Fee]]-Table5[[#This Row],[Discount Amount]] -> 230 | AB36: =_xlfn.XLOOKUP(Table5[[#This Row],[RiderID]], Rider_Directory!$F$2:$F$26, Rider_Directory!$B$2:$B$26) -> Kathmandu | AC36: {=_xlfn.IFS(Table5[[#This Row],[Final Amount]]<500, "Small", Table5[[#This Row],[Final Amount]]<=1000, "Medium", Table5[[#This Row],[Final Amount]]>1000, "Large")} -> Small | AD36: =_xlfn.LET(_xlpm.expiry,_xlfn.XLOOKUP(Table5[[#This Row],[PromoCode]],Promo_Codes!$A$2:$A$9,Promo_Codes!$F$2:$F$9,DATE(2099,1,1)),IF(Table5[[#This Row],[OrderDate]]>_xlpm.expiry,"Expired Code Used","Valid")) -> Valid
A37: ORD-1035 | B37: 45900 | C37: Rina Magar | D37: 9845-957117 | E37: 45820 | F37: =IF(B37-E37<=2,"New","Returning") -> Returning | G37: Chitwan | H37: Wok Point | I37: Chinese | J37: Veg Chopsuey | K37: 1 | L37: R-123 | M37: Khalti | O37: Delivered | P37: =IF(O37=""," NEED REVIEW","") | Q37: 4 | R37: 46 | T37: =_xlfn.CONCAT(Table5[[#This Row],[OrderID]]," | ",Table5[[#This Row],[City]]," | ",Table5[[#This Row],[ItemName]]) -> ORD-1035 | Chitwan | Veg Chopsuey | U37: =UPPER(Table5[[#This Row],[City]]) -> CHITWAN | V37: =LOWER(Table5[[#This Row],[PaymentMethod]]) -> khalti | W37: {=_xlfn.XLOOKUP(TRIM(Table5[[#This Row],[ItemName]]), TRIM(Menu_Price_List_tbl[ItemName]),Menu_Price_List_tbl[UnitPrice_NPR])} -> 260 | X37: =W37*K37 -> 260 | Y37: =_xlfn.XLOOKUP(Table5[[#This Row],[City]],City_Delivery_Fee_tbl[City],City_Delivery_Fee_tbl[BaseDeliveryFee_NPR]) -> 80 | Z37: =IF(ISBLANK(Table5[[#This Row],[PromoCode]]), 0, _xlfn.LET( _xlpm.type, _xlfn.XLOOKUP(Table5[[#This Row],[PromoCode]], Promo_Codes!$A$2:$A$9, Promo_Codes!$C$2:$C$9, "Flat"), _xlpm.val, _xlfn.XLOOKUP(Table5[[#This Row],[PromoCode]], Promo_Codes!$A$2:$A$9, Promo_Codes!$D$2:$D$9, 0), IF(_xlpm.type="Percentage", Table5[[#This Row],[Order Amount]]*(_xlpm.val/100), _xlpm.val) ) ) -> 0 | AA37: =Table5[[#This Row],[Order Amount]]+Table5[[#This Row],[Delivery Fee]]-Table5[[#This Row],[Discount Amount]] -> 340 | AB37: =_xlfn.XLOOKUP(Table5[[#This Row],[RiderID]], Rider_Directory!$F$2:$F$26, Rider_Directory!$B$2:$B$26) -> Chitwan | AC37: {=_xlfn.IFS(Table5[[#This Row],[Final Amount]]<500, "Small", Table5[[#This Row],[Final Amount]]<=1000, "Medium", Table5[[#This Row],[Final Amount]]>1000, "Large")} -> Small | AD37: =_xlfn.LET(_xlpm.expiry,_xlfn.XLOOKUP(Table5[[#This Row],[PromoCode]],Promo_Codes!$A$2:$A$9,Promo_Codes!$F$2:$F$9,DATE(2099,1,1)),IF(Table5[[#This Row],[OrderDate]]>_xlpm.expiry,"Expired Code Used","Valid")) -> Valid
A38: ORD-1036 | B38: 45901 | C38: Bandana Bhattarai | D38: 9800-474395 | E38: 45901 | F38: =IF(B38-E38<=2,"New","Returning") -> New | G38: Butwal | H38: Fast Bites | I38: Fast Food | J38: French Fries | K38: 2 | L38: R-120 | M38: eSewa | O38: Delivered | P38: =IF(O38=""," NEED REVIEW","") | Q38: 2 | R38: 30 | T38: =_xlfn.CONCAT(Table5[[#This Row],[OrderID]]," | ",Table5[[#This Row],[City]]," | ",Table5[[#This Row],[ItemName]]) -> ORD-1036 | Butwal | French Fries | U38: =UPPER(Table5[[#This Row],[City]]) -> BUTWAL | V38: =LOWER(Table5[[#This Row],[PaymentMethod]]) -> esewa | W38: {=_xlfn.XLOOKUP(TRIM(Table5[[#This Row],[ItemName]]), TRIM(Menu_Price_List_tbl[ItemName]),Menu_Price_List_tbl[UnitPrice_NPR])} -> 160 | X38: =W38*K38 -> 320 | Y38: =_xlfn.XLOOKUP(Table5[[#This Row],[City]],City_Delivery_Fee_tbl[City],City_Delivery_Fee_tbl[BaseDeliveryFee_NPR]) -> 85 | Z38: =IF(ISBLANK(Table5[[#This Row],[PromoCode]]), 0, _xlfn.LET( _xlpm.type, _xlfn.XLOOKUP(Table5[[#This Row],[PromoCode]], Promo_Codes!$A$2:$A$9, Promo_Codes!$C$2:$C$9, "Flat"), _xlpm.val, _xlfn.XLOOKUP(Table5[[#This Row],[PromoCode]], Promo_Codes!$A$2:$A$9, Promo_Codes!$D$2:$D$9, 0), IF(_xlpm.type="Percentage", Table5[[#This Row],[Order Amount]]*(_xlpm.val/100), _xlpm.val) ) ) -> 0 | AA38: =Table5[[#This Row],[Order Amount]]+Table5[[#This Row],[Delivery Fee]]-Table5[[#This Row],[Discount Amount]] -> 405 | AB38: =_xlfn.XLOOKUP(Table5[[#This Row],[RiderID]], Rider_Directory!$F$2:$F$26, Rider_Directory!$B$2:$B$26) -> Butwal | AC38: {=_xlfn.IFS(Table5[[#This Row],[Final Amount]]<500, "Small", Table5[[#This Row],[Final Amount]]<=1000, "Medium", Table5[[#This Row],[Final Amount]]>1000, "Large")} -> Small | AD38: =_xlfn.LET(_xlpm.expiry,_xlfn.XLOOKUP(Table5[[#This Row],[PromoCode]],Promo_Codes!$A$2:$A$9,Promo_Codes!$F$2:$F$9,DATE(2099,1,1)),IF(Table5[[#This Row],[OrderDate]]>_xlpm.expiry,"Expired Code Used","Valid")) -> Valid
A39: ORD-1037 | B39: 45901 | C39: Sagar Khadka | D39: 9832-870465 | E39: 45722 | F39: =IF(B39-E39<=2,"New","Returning") -> Returning | G39: Kathmandu | H39: Fast Bites | I39: Fast Food | J39: French Fries | K39: 1 | L39: R-106 | M39: IME Pay | O39: Cancelled | P39: =IF(O39=""," NEED REVIEW","") | R39: 8 | S39: average, nothing special | T39: =_xlfn.CONCAT(Table5[[#This Row],[OrderID]]," | ",Table5[[#This Row],[City]]," | ",Table5[[#This Row],[ItemName]]) -> ORD-1037 | Kathmandu | French Fries | U39: =UPPER(Table5[[#This Row],[City]]) -> KATHMANDU | V39: =LOWER(Table5[[#This Row],[PaymentMethod]]) -> ime pay | W39: {=_xlfn.XLOOKUP(TRIM(Table5[[#This Row],[ItemName]]), TRIM(Menu_Price_List_tbl[ItemName]),Menu_Price_List_tbl[UnitPrice_NPR])} -> 160 | X39: =W39*K39 -> 160 | Y39: =_xlfn.XLOOKUP(Table5[[#This Row],[City]],City_Delivery_Fee_tbl[City],City_Delivery_Fee_tbl[BaseDeliveryFee_NPR]) -> 50 | Z39: =IF(ISBLANK(Table5[[#This Row],[PromoCode]]), 0, _xlfn.LET( _xlpm.type, _xlfn.XLOOKUP(Table5[[#This Row],[PromoCode]], Promo_Codes!$A$2:$A$9, Promo_Codes!$C$2:$C$9, "Flat"), _xlpm.val, _xlfn.XLOOKUP(Table5[[#This Row],[PromoCode]], Promo_Codes!$A$2:$A$9, Promo_Codes!$D$2:$D$9, 0), IF(_xlpm.type="Percentage", Table5[[#This Row],[Order Amount]]*(_xlpm.val/100), _xlpm.val) ) ) -> 0 | AA39: =Table5[[#This Row],[Order Amount]]+Table5[[#This Row],[Delivery Fee]]-Table5[[#This Row],[Discount Amount]] -> 210 | AB39: =_xlfn.XLOOKUP(Table5[[#This Row],[RiderID]], Rider_Directory!$F$2:$F$26, Rider_Directory!$B$2:$B$26) -> Kathmandu | AC39: {=_xlfn.IFS(Table5[[#This Row],[Final Amount]]<500, "Small", Table5[[#This Row],[Final Amount]]<=1000, "Medium", Table5[[#This Row],[Final Amount]]>1000, "Large")} -> Small | AD39: =_xlfn.LET(_xlpm.expiry,_xlfn.XLOOKUP(Table5[[#This Row],[PromoCode]],Promo_Codes!$A$2:$A$9,Promo_Codes!$F$2:$F$9,DATE(2099,1,1)),IF(Table5[[#This Row],[OrderDate]]>_xlpm.expiry,"Expired Code Used","Valid")) -> Valid
A40: ORD-1038 | B40: 45901 | C40: Rohit Basnet | D40: 9870-822765 | E40: 45721 | F40: =IF(B40-E40<=2,"New","Returning") -> Returning | G40: Kathmandu | H40: Quick Snacks Corner | I40: Fast Food | J40: French Fries | K40: 2 | L40: R-106 | M40: eSewa | O40: Delivered | P40: =IF(O40=""," NEED REVIEW","") | Q40: 4 | R40: 41 | T40: =_xlfn.CONCAT(Table5[[#This Row],[OrderID]]," | ",Table5[[#This Row],[City]]," | ",Table5[[#This Row],[ItemName]]) -> ORD-1038 | Kathmandu | French Fries | U40: =UPPER(Table5[[#This Row],[City]]) -> KATHMANDU | V40: =LOWER(Table5[[#This Row],[PaymentMethod]]) -> esewa | W40: {=_xlfn.XLOOKUP(TRIM(Table5[[#This Row],[ItemName]]), TRIM(Menu_Price_List_tbl[ItemName]),Menu_Price_List_tbl[UnitPrice_NPR])} -> 160 | X40: =W40*K40 -> 320 | Y40: =_xlfn.XLOOKUP(Table5[[#This Row],[City]],City_Delivery_Fee_tbl[City],City_Delivery_Fee_tbl[BaseDeliveryFee_NPR]) -> 50 | Z40: =IF(ISBLANK(Table5[[#This Row],[PromoCode]]), 0, _xlfn.LET( _xlpm.type, _xlfn.XLOOKUP(Table5[[#This Row],[PromoCode]], Promo_Codes!$A$2:$A$9, Promo_Codes!$C$2:$C$9, "Flat"), _xlpm.val, _xlfn.XLOOKUP(Table5[[#This Row],[PromoCode]], Promo_Codes!$A$2:$A$9, Promo_Codes!$D$2:$D$9, 0), IF(_xlpm.type="Percentage", Table5[[#This Row],[Order Amount]]*(_xlpm.val/100), _xlpm.val) ) ) -> 0 | AA40: =Table5[[#This Row],[Order Amount]]+Table5[[#This Row],[Delivery Fee]]-Table5[[#This Row],[Discount Amount]] -> 370 | AB40: =_xlfn.XLOOKUP(Table5[[#This Row],[RiderID]], Rider_Directory!$F$2:$F$26, Rider_Directory!$B$2:$B$26) -> Kathmandu | AC40: {=_xlfn.IFS(Table5[[#This Row],[Final Amount]]<500, "Small", Table5[[#This Row],[Final Amount]]<=1000, "Medium", Table5[[#This Row],[Final Amount]]>1000, "Large")} -> Small | AD40: =_xlfn.LET(_xlpm.expiry,_xlfn.XLOOKUP(Table5[[#This Row],[PromoCode]],Promo_Codes!$A$2:$A$9,Promo_Codes!$F$2:$F$9,DATE(2099,1,1)),IF(Table5[[#This Row],[OrderDate]]>_xlpm.expiry,"Expired Code Used","Valid")) -> Valid
A41: ORD-1039 | B41: 45901 | C41: Rohit Lama | D41: 9833-043483 | E41: 45680 | F41: =IF(B41-E41<=2,"New","Returning") -> Returning | G41: Pokhara | H41: Chiya Adda | I41: Beverages | J41: Lemon Soda | K41: 2 | L41: R-115 | M41: Cash on Delivery | N41: WEEKEND10 | O41: Returned | P41: =IF(O41=""," NEED REVIEW","") | R41: 55 | S41: okay experience | T41: =_xlfn.CONCAT(Table5[[#This Row],[OrderID]]," | ",Table5[[#This Row],[City]]," | ",Table5[[#This Row],[ItemName]]) -> ORD-1039 | Pokhara | Lemon Soda | U41: =UPPER(Table5[[#This Row],[City]]) -> POKHARA | V41: =LOWER(Table5[[#This Row],[PaymentMethod]]) -> cash on delivery | W41: {=_xlfn.XLOOKUP(TRIM(Table5[[#This Row],[ItemName]]), TRIM(Menu_Price_List_tbl[ItemName]),Menu_Price_List_tbl[UnitPrice_NPR])} -> 100 | X41: =W41*K41 -> 200 | Y41: =_xlfn.XLOOKUP(Table5[[#This Row],[City]],City_Delivery_Fee_tbl[City],City_Delivery_Fee_tbl[BaseDeliveryFee_NPR]) -> 70 | Z41: =IF(ISBLANK(Table5[[#This Row],[PromoCode]]), 0, _xlfn.LET( _xlpm.type, _xlfn.XLOOKUP(Table5[[#This Row],[PromoCode]], Promo_Codes!$A$2:$A$9, Promo_Codes!$C$2:$C$9, "Flat"), _xlpm.val, _xlfn.XLOOKUP(Table5[[#This Row],[PromoCode]], Promo_Codes!$A$2:$A$9, Promo_Codes!$D$2:$D$9, 0), IF(_xlpm.type="Percentage", Table5[[#This Row],[Order Amount]]*(_xlpm.val/100), _xlpm.val) ) ) -> 20 | AA41: =Table5[[#This Row],[Order Amount]]+Table5[[#This Row],[Delivery Fee]]-Table5[[#This Row],[Discount Amount]] -> 250 | AB41: =_xlfn.XLOOKUP(Table5[[#This Row],[RiderID]], Rider_Directory!$F$2:$F$26, Rider_Directory!$B$2:$B$26) -> Pokhara | AC41: {=_xlfn.IFS(Table5[[#This Row],[Final Amount]]<500, "Small", Table5[[#This Row],[Final Amount]]<=1000, "Medium", Table5[[#This Row],[Final Amount]]>1000, "Large")} -> Small | AD41: =_xlfn.LET(_xlpm.expiry,_xlfn.XLOOKUP(Table5[[#This Row],[PromoCode]],Promo_Codes!$A$2:$A$9,Promo_Codes!$F$2:$F$9,DATE(2099,1,1)),IF(Table5[[#This Row],[OrderDate]]>_xlpm.expiry,"Expired Code Used","Valid")) -> Valid
A42: ORD-1040 | B42: 45904 | C42: Manisha Rai | D42: 9814-913167 | E42: 45895 | F42: =IF(B42-E42<=2,"New","Returning") -> Returning | G42: Chitwan | H42: Sweet Home Bakery | I42: Bakery | J42: Barfi (5 pcs) | K42: 4 | L42: R-121 | M42: Khalti | O42: Delivered | P42: =IF(O42=""," NEED REVIEW","") | Q42: 5 | R42: 50 | T42: =_xlfn.CONCAT(Table5[[#This Row],[OrderID]]," | ",Table5[[#This Row],[City]]," | ",Table5[[#This Row],[ItemName]]) -> ORD-1040 | Chitwan | Barfi (5 pcs) | U42: =UPPER(Table5[[#This Row],[City]]) -> CHITWAN | V42: =LOWER(Table5[[#This Row],[PaymentMethod]]) -> khalti | W42: {=_xlfn.XLOOKUP(TRIM(Table5[[#This Row],[ItemName]]), TRIM(Menu_Price_List_tbl[ItemName]),Menu_Price_List_tbl[UnitPrice_NPR])} -> 220 | X42: =W42*K42 -> 880 | Y42: =_xlfn.XLOOKUP(Table5[[#This Row],[City]],City_Delivery_Fee_tbl[City],City_Delivery_Fee_tbl[BaseDeliveryFee_NPR]) -> 80 | Z42: =IF(ISBLANK(Table5[[#This Row],[PromoCode]]), 0, _xlfn.LET( _xlpm.type, _xlfn.XLOOKUP(Table5[[#This Row],[PromoCode]], Promo_Codes!$A$2:$A$9, Promo_Codes!$C$2:$C$9, "Flat"), _xlpm.val, _xlfn.XLOOKUP(Table5[[#This Row],[PromoCode]], Promo_Codes!$A$2:$A$9, Promo_Codes!$D$2:$D$9, 0), IF(_xlpm.type="Percentage", Table5[[#This Row],[Order Amount]]*(_xlpm.val/100), _xlpm.val) ) ) -> 0 | AA42: =Table5[[#This Row],[Order Amount]]+Table5[[#This Row],[Delivery Fee]]-Table5[[#This Row],[Discount Amount]] -> 960 | AB42: =_xlfn.XLOOKUP(Table5[[#This Row],[RiderID]], Rider_Directory!$F$2:$F$26, Rider_Directory!$B$2:$B$26) -> Chitwan | AC42: {=_xlfn.IFS(Table5[[#This Row],[Final Amount]]<500, "Small", Table5[[#This Row],[Final Amount]]<=1000, "Medium", Table5[[#This Row],[Final Amount]]>1000, "Large")} -> Medium | AD42: =_xlfn.LET(_xlpm.expiry,_xlfn.XLOOKUP(Table5[[#This Row],[PromoCode]],Promo_Codes!$A$2:$A$9,Promo_Codes!$F$2:$F$9,DATE(2099,1,1)),IF(Table5[[#This Row],[OrderDate]]>_xlpm.expiry,"Expired Code Used","Valid")) -> Valid
A43: ORD-1041 | B43: 45904 | C43: Bandana Basnet | D43: 9823-159425 | E43: 45904 | F43: =IF(B43-E43<=2,"New","Returning") -> New | G43: Kathmandu | H43: Chiya Adda | I43: Beverages | J43: Lemon Soda | K43: 2 | L43: R-106 | M43: Khalti | O43: Delivered | P43: =IF(O43=""," NEED REVIEW","") | Q43: 5 | R43: 26 | T43: =_xlfn.CONCAT(Table5[[#This Row],[OrderID]]," | ",Table5[[#This Row],[City]]," | ",Table5[[#This Row],[ItemName]]) -> ORD-1041 | Kathmandu | Lemon Soda | U43: =UPPER(Table5[[#This Row],[City]]) -> KATHMANDU | V43: =LOWER(Table5[[#This Row],[PaymentMethod]]) -> khalti | W43: {=_xlfn.XLOOKUP(TRIM(Table5[[#This Row],[ItemName]]), TRIM(Menu_Price_List_tbl[ItemName]),Menu_Price_List_tbl[UnitPrice_NPR])} -> 100 | X43: =W43*K43 -> 200 | Y43: =_xlfn.XLOOKUP(Table5[[#This Row],[City]],City_Delivery_Fee_tbl[City],City_Delivery_Fee_tbl[BaseDeliveryFee_NPR]) -> 50 | Z43: =IF(ISBLANK(Table5[[#This Row],[PromoCode]]), 0, _xlfn.LET( _xlpm.type, _xlfn.XLOOKUP(Table5[[#This Row],[PromoCode]], Promo_Codes!$A$2:$A$9, Promo_Codes!$C$2:$C$9, "Flat"), _xlpm.val, _xlfn.XLOOKUP(Table5[[#This Row],[PromoCode]], Promo_Codes!$A$2:$A$9, Promo_Codes!$D$2:$D$9, 0), IF(_xlpm.type="Percentage", Table5[[#This Row],[Order Amount]]*(_xlpm.val/100), _xlpm.val) ) ) -> 0 | AA43: =Table5[[#This Row],[Order Amount]]+Table5[[#This Row],[Delivery Fee]]-Table5[[#This Row],[Discount Amount]] -> 250 | AB43: =_xlfn.XLOOKUP(Table5[[#This Row],[RiderID]], Rider_Directory!$F$2:$F$26, Rider_Directory!$B$2:$B$26) -> Kathmandu | AC43: {=_xlfn.IFS(Table5[[#This Row],[Final Amount]]<500, "Small", Table5[[#This Row],[Final Amount]]<=1000, "Medium", Table5[[#This Row],[Final Amount]]>1000, "Large")} -> Small | AD43: =_xlfn.LET(_xlpm.expiry,_xlfn.XLOOKUP(Table5[[#This Row],[PromoCode]],Promo_Codes!$A$2:$A$9,Promo_Codes!$F$2:$F$9,DATE(2099,1,1)),IF(Table5[[#This Row],[OrderDate]]>_xlpm.expiry,"Expired Code Used","Valid")) -> Valid
A44: ORD-1042 | B44: 45906 | C44: Rajan Shakya | D44: 9826-199582 | E44: 45904 | F44: =IF(B44-E44<=2,"New","Returning") -> New | G44: Dharan | H44: Himalayan Bakers | I44: Bakery | J44: SEL ROTI (4 PCS) | K44: 1 | L44: R-124 | M44: Cash on Delivery | O44: Cancelled | P44: =IF(O44=""," NEED REVIEW","") | R44: 63 | T44: =_xlfn.CONCAT(Table5[[#This Row],[OrderID]]," | ",Table5[[#This Row],[City]]," | ",Table5[[#This Row],[ItemName]]) -> ORD-1042 | Dharan | SEL ROTI (4 PCS) | U44: =UPPER(Table5[[#This Row],[City]]) -> DHARAN | V44: =LOWER(Table5[[#This Row],[PaymentMethod]]) -> cash on delivery | W44: {=_xlfn.XLOOKUP(TRIM(Table5[[#This Row],[ItemName]]), TRIM(Menu_Price_List_tbl[ItemName]),Menu_Price_List_tbl[UnitPrice_NPR])} -> 140 | X44: =W44*K44 -> 140 | Y44: =_xlfn.XLOOKUP(Table5[[#This Row],[City]],City_Delivery_Fee_tbl[City],City_Delivery_Fee_tbl[BaseDeliveryFee_NPR]) -> 95 | Z44: =IF(ISBLANK(Table5[[#This Row],[PromoCode]]), 0, _xlfn.LET( _xlpm.type, _xlfn.XLOOKUP(Table5[[#This Row],[PromoCode]], Promo_Codes!$A$2:$A$9, Promo_Codes!$C$2:$C$9, "Flat"), _xlpm.val, _xlfn.XLOOKUP(Table5[[#This Row],[PromoCode]], Promo_Codes!$A$2:$A$9, Promo_Codes!$D$2:$D$9, 0), IF(_xlpm.type="Percentage", Table5[[#This Row],[Order Amount]]*(_xlpm.val/100), _xlpm.val) ) ) -> 0 | AA44: =Table5[[#This Row],[Order Amount]]+Table5[[#This Row],[Delivery Fee]]-Table5[[#This Row],[Discount Amount]] -> 235 | AB44: =_xlfn.XLOOKUP(Table5[[#This Row],[RiderID]], Rider_Directory!$F$2:$F$26, Rider_Directory!$B$2:$B$26) -> Dharan | AC44: {=_xlfn.IFS(Table5[[#This Row],[Final Amount]]<500, "Small", Table5[[#This Row],[Final Amount]]<=1000, "Medium", Table5[[#This Row],[Final Amount]]>1000, "Large")} -> Small | AD44: =_xlfn.LET(_xlpm.expiry,_xlfn.XLOOKUP(Table5[[#This Row],[PromoCode]],Promo_Codes!$A$2:$A$9,Promo_Codes!$F$2:$F$9,DATE(2099,1,1)),IF(Table5[[#This Row],[OrderDate]]>_xlpm.expiry,"Expired Code Used","Valid")) -> Valid
A45: ORD-1043 | B45: 45909 | C45: Rajan Poudel | D45: 9808-246281 | E45: 45909 | F45: =IF(B45-E45<=2,"New","Returning") -> New | G45: Dharan | H45: Thakali Ghar | I45: Thakali Set | J45: Chicken Thakali Set | K45: 1 | L45: R-124 | M45: eSewa | O45: Delivered | P45: =IF(O45=""," NEED REVIEW","") | Q45: 4 | R45: 55 | S45: best momo in town | T45: =_xlfn.CONCAT(Table5[[#This Row],[OrderID]]," | ",Table5[[#This Row],[City]]," | ",Table5[[#This Row],[ItemName]]) -> ORD-1043 | Dharan | Chicken Thakali Set | U45: =UPPER(Table5[[#This Row],[City]]) -> DHARAN | V45: =LOWER(Table5[[#This Row],[PaymentMethod]]) -> esewa | W45: {=_xlfn.XLOOKUP(TRIM(Table5[[#This Row],[ItemName]]), TRIM(Menu_Price_List_tbl[ItemName]),Menu_Price_List_tbl[UnitPrice_NPR])} -> 480 | X45: =W45*K45 -> 480 | Y45: =_xlfn.XLOOKUP(Table5[[#This Row],[City]],City_Delivery_Fee_tbl[City],City_Delivery_Fee_tbl[BaseDeliveryFee_NPR]) -> 95 | Z45: =IF(ISBLANK(Table5[[#This Row],[PromoCode]]), 0, _xlfn.LET( _xlpm.type, _xlfn.XLOOKUP(Table5[[#This Row],[PromoCode]], Promo_Codes!$A$2:$A$9, Promo_Codes!$C$2:$C$9, "Flat"), _xlpm.val, _xlfn.XLOOKUP(Table5[[#This Row],[PromoCode]], Promo_Codes!$A$2:$A$9, Promo_Codes!$D$2:$D$9, 0), IF(_xlpm.type="Percentage", Table5[[#This Row],[Order Amount]]*(_xlpm.val/100), _xlpm.val) ) ) -> 0 | AA45: =Table5[[#This Row],[Order Amount]]+Table5[[#This Row],[Delivery Fee]]-Table5[[#This Row],[Discount Amount]] -> 575 | AB45: =_xlfn.XLOOKUP(Table5[[#This Row],[RiderID]], Rider_Directory!$F$2:$F$26, Rider_Directory!$B$2:$B$26) -> Dharan | AC45: {=_xlfn.IFS(Table5[[#This Row],[Final Amount]]<500, "Small", Table5[[#This Row],[Final Amount]]<=1000, "Medium", Table5[[#This Row],[Final Amount]]>1000, "Large")} -> Medium | AD45: =_xlfn.LET(_xlpm.expiry,_xlfn.XLOOKUP(Table5[[#This Row],[PromoCode]],Promo_Codes!$A$2:$A$9,Promo_Codes!$F$2:$F$9,DATE(2099,1,1)),IF(Table5[[#This Row],[OrderDate]]>_xlpm.expiry,"Expired Code Used","Valid")) -> Valid
A46: ORD-1044 | B46: 45910 | C46: Sita Tamang | D46: 9831-430154 | E46: 45908 | F46: =IF(B46-E46<=2,"New","Returning") -> New | G46: Butwal | H46: Chiya Adda | I46: Beverages | J46: Lassi | K46: 1 | L46: R-119 | M46: ConnectIPS | N46: WEEKEND10 | O46: Delivered | P46: =IF(O46=""," NEED REVIEW","") | Q46: 3 | R46: 25 | T46: =_xlfn.CONCAT(Table5[[#This Row],[OrderID]]," | ",Table5[[#This Row],[City]]," | ",Table5[[#This Row],[ItemName]]) -> ORD-1044 | Butwal | Lassi | U46: =UPPER(Table5[[#This Row],[City]]) -> BUTWAL | V46: =LOWER(Table5[[#This Row],[PaymentMethod]]) -> connectips | W46: {=_xlfn.XLOOKUP(TRIM(Table5[[#This Row],[ItemName]]), TRIM(Menu_Price_List_tbl[ItemName]),Menu_Price_List_tbl[UnitPrice_NPR])} -> 130 | X46: =W46*K46 -> 130 | Y46: =_xlfn.XLOOKUP(Table5[[#This Row],[City]],City_Delivery_Fee_tbl[City],City_Delivery_Fee_tbl[BaseDeliveryFee_NPR]) -> 85 | Z46: =IF(ISBLANK(Table5[[#This Row],[PromoCode]]), 0, _xlfn.LET( _xlpm.type, _xlfn.XLOOKUP(Table5[[#This Row],[PromoCode]], Promo_Codes!$A$2:$A$9, Promo_Codes!$C$2:$C$9, "Flat"), _xlpm.val, _xlfn.XLOOKUP(Table5[[#This Row],[PromoCode]], Promo_Codes!$A$2:$A$9, Promo_Codes!$D$2:$D$9, 0), IF(_xlpm.type="Percentage", Table5[[#This Row],[Order Amount]]*(_xlpm.val/100), _xlpm.val) ) ) -> 13 | AA46: =Table5[[#This Row],[Order Amount]]+Table5[[#This Row],[Delivery Fee]]-Table5[[#This Row],[Discount Amount]] -> 202 | AB46: =_xlfn.XLOOKUP(Table5[[#This Row],[RiderID]], Rider_Directory!$F$2:$F$26, Rider_Directory!$B$2:$B$26) -> Butwal | AC46: {=_xlfn.IFS(Table5[[#This Row],[Final Amount]]<500, "Small", Table5[[#This Row],[Final Amount]]<=1000, "Medium", Table5[[#This Row],[Final Amount]]>1000, "Large")} -> Small | AD46: =_xlfn.LET(_xlpm.expiry,_xlfn.XLOOKUP(Table5[[#This Row],[PromoCode]],Promo_Codes!$A$2:$A$9,Promo_Codes!$F$2:$F$9,DATE(2099,1,1)),IF(Table5[[#This Row],[OrderDate]]>_xlpm.expiry,"Expired Code Used","Valid")) -> Valid
A47: ORD-1045 | B47: 45910 | C47: Manisha Rai | D47: 9814-913167 | E47: 45895 | F47: =IF(B47-E47<=2,"New","Returning") -> Returning | G47: Lalitpur | H47: Sweet Home Bakery | I47: Bakery | J47: Chocolate Pastry | K47: 2 | L47: R-107 | M47: Cash on Delivery | O47: Delivered | P47: =IF(O47=""," NEED REVIEW","") | Q47: 4 | R47: 24 | T47: =_xlfn.CONCAT(Table5[[#This Row],[OrderID]]," | ",Table5[[#This Row],[City]]," | ",Table5[[#This Row],[ItemName]]) -> ORD-1045 | Lalitpur | Chocolate Pastry | U47: =UPPER(Table5[[#This Row],[City]]) -> LALITPUR | V47: =LOWER(Table5[[#This Row],[PaymentMethod]]) -> cash on delivery | W47: {=_xlfn.XLOOKUP(TRIM(Table5[[#This Row],[ItemName]]), TRIM(Menu_Price_List_tbl[ItemName]),Menu_Price_List_tbl[UnitPrice_NPR])} -> 150 | X47: =W47*K47 -> 300 | Y47: =_xlfn.XLOOKUP(Table5[[#This Row],[City]],City_Delivery_Fee_tbl[City],City_Delivery_Fee_tbl[BaseDeliveryFee_NPR]) -> 50 | Z47: =IF(ISBLANK(Table5[[#This Row],[PromoCode]]), 0, _xlfn.LET( _xlpm.type, _xlfn.XLOOKUP(Table5[[#This Row],[PromoCode]], Promo_Codes!$A$2:$A$9, Promo_Codes!$C$2:$C$9, "Flat"), _xlpm.val, _xlfn.XLOOKUP(Table5[[#This Row],[PromoCode]], Promo_Codes!$A$2:$A$9, Promo_Codes!$D$2:$D$9, 0), IF(_xlpm.type="Percentage", Table5[[#This Row],[Order Amount]]*(_xlpm.val/100), _xlpm.val) ) ) -> 0 | AA47: =Table5[[#This Row],[Order Amount]]+Table5[[#This Row],[Delivery Fee]]-Table5[[#This Row],[Discount Amount]] -> 350 | AB47: =_xlfn.XLOOKUP(Table5[[#This Row],[RiderID]], Rider_Directory!$F$2:$F$26, Rider_Directory!$B$2:$B$26) -> Lalitpur | AC47: {=_xlfn.IFS(Table5[[#This Row],[Final Amount]]<500, "Small", Table5[[#This Row],[Final Amount]]<=1000, "Medium", Table5[[#This Row],[Final Amount]]>1000, "Large")} -> Small | AD47: =_xlfn.LET(_xlpm.expiry,_xlfn.XLOOKUP(Table5[[#This Row],[PromoCode]],Promo_Codes!$A$2:$A$9,Promo_Codes!$F$2:$F$9,DATE(2099,1,1)),IF(Table5[[#This Row],[OrderDate]]>_xlpm.expiry,"Expired Code Used","Valid")) -> Valid
A48: ORD-1046 | B48: 45910 | C48: Bishal Bista | D48: 9899-075116 | E48: 45880 | F48: =IF(B48-E48<=2,"New","Returning") -> Returning | G48: Lalitpur | H48: Thakali Ghar | I48: Thakali Set | J48: Chicken Thakali Set | K48: 1 | L48: R-107 | M48: Khalti | O48: Delivered | P48: =IF(O48=""," NEED REVIEW","") | Q48: 3 | R48: 28 | S48: delivery was very late | T48: =_xlfn.CONCAT(Table5[[#This Row],[OrderID]]," | ",Table5[[#This Row],[City]]," | ",Table5[[#This Row],[ItemName]]) -> ORD-1046 | Lalitpur | Chicken Thakali Set | U48: =UPPER(Table5[[#This Row],[City]]) -> LALITPUR | V48: =LOWER(Table5[[#This Row],[PaymentMethod]]) -> khalti | W48: {=_xlfn.XLOOKUP(TRIM(Table5[[#This Row],[ItemName]]), TRIM(Menu_Price_List_tbl[ItemName]),Menu_Price_List_tbl[UnitPrice_NPR])} -> 480 | X48: =W48*K48 -> 480 | Y48: =_xlfn.XLOOKUP(Table5[[#This Row],[City]],City_Delivery_Fee_tbl[City],City_Delivery_Fee_tbl[BaseDeliveryFee_NPR]) -> 50 | Z48: =IF(ISBLANK(Table5[[#This Row],[PromoCode]]), 0, _xlfn.LET( _xlpm.type, _xlfn.XLOOKUP(Table5[[#This Row],[PromoCode]], Promo_Codes!$A$2:$A$9, Promo_Codes!$C$2:$C$9, "Flat"), _xlpm.val, _xlfn.XLOOKUP(Table5[[#This Row],[PromoCode]], Promo_Codes!$A$2:$A$9, Promo_Codes!$D$2:$D$9, 0), IF(_xlpm.type="Percentage", Table5[[#This Row],[Order Amount]]*(_xlpm.val/100), _xlpm.val) ) ) -> 0 | AA48: =Table5[[#This Row],[Order Amount]]+Table5[[#This Row],[Delivery Fee]]-Table5[[#This Row],[Discount Amount]] -> 530 | AB48: =_xlfn.XLOOKUP(Table5[[#This Row],[RiderID]], Rider_Directory!$F$2:$F$26, Rider_Directory!$B$2:$B$26) -> Lalitpur | AC48: {=_xlfn.IFS(Table5[[#This Row],[Final Amount]]<500, "Small", Table5[[#This Row],[Final Amount]]<=1000, "Medium", Table5[[#This Row],[Final Amount]]>1000, "Large")} -> Medium | AD48: =_xlfn.LET(_xlpm.expiry,_xlfn.XLOOKUP(Table5[[#This Row],[PromoCode]],Promo_Codes!$A$2:$A$9,Promo_Codes!$F$2:$F$9,DATE(2099,1,1)),IF(Table5[[#This Row],[OrderDate]]>_xlpm.expiry,"Expired Code Used","Valid")) -> Valid
A49: ORD-1047 | B49: 45911 | C49: Rita Adhikari | D49: 9883-380141 | E49: 45909 | F49: =IF(B49-E49<=2,"New","Returning") -> New | G49: Pokhara | H49: Yeti Newari Bhoj | I49: Newari Khana | J49: BARA | K49: 1 | L49: R-114 | M49: eSewa | N49: LOYAL100 | O49: Delivered | P49: =IF(O49=""," NEED REVIEW","") | Q49: 5 | R49: 38 | T49: =_xlfn.CONCAT(Table5[[#This Row],[OrderID]]," | ",Table5[[#This Row],[City]]," | ",Table5[[#This Row],[ItemName]]) -> ORD-1047 | Pokhara | BARA | U49: =UPPER(Table5[[#This Row],[City]]) -> POKHARA | V49: =LOWER(Table5[[#This Row],[PaymentMethod]]) -> esewa | W49: {=_xlfn.XLOOKUP(TRIM(Table5[[#This Row],[ItemName]]), TRIM(Menu_Price_List_tbl[ItemName]),Menu_Price_List_tbl[UnitPrice_NPR])} -> 160 | X49: =W49*K49 -> 160 | Y49: =_xlfn.XLOOKUP(Table5[[#This Row],[City]],City_Delivery_Fee_tbl[City],City_Delivery_Fee_tbl[BaseDeliveryFee_NPR]) -> 70 | Z49: =IF(ISBLANK(Table5[[#This Row],[PromoCode]]), 0, _xlfn.LET( _xlpm.type, _xlfn.XLOOKUP(Table5[[#This Row],[PromoCode]], Promo_Codes!$A$2:$A$9, Promo_Codes!$C$2:$C$9, "Flat"), _xlpm.val, _xlfn.XLOOKUP(Table5[[#This Row],[PromoCode]], Promo_Codes!$A$2:$A$9, Promo_Codes!$D$2:$D$9, 0), IF(_xlpm.type="Percentage", Table5[[#This Row],[Order Amount]]*(_xlpm.val/100), _xlpm.val) ) ) -> 100 | AA49: =Table5[[#This Row],[Order Amount]]+Table5[[#This Row],[Delivery Fee]]-Table5[[#This Row],[Discount Amount]] -> 130 | AB49: =_xlfn.XLOOKUP(Table5[[#This Row],[RiderID]], Rider_Directory!$F$2:$F$26, Rider_Directory!$B$2:$B$26) -> Pokhara | AC49: {=_xlfn.IFS(Table5[[#This Row],[Final Amount]]<500, "Small", Table5[[#This Row],[Final Amount]]<=1000, "Medium", Table5[[#This Row],[Final Amount]]>1000, "Large")} -> Small | AD49: =_xlfn.LET(_xlpm.expiry,_xlfn.XLOOKUP(Table5[[#This Row],[PromoCode]],Promo_Codes!$A$2:$A$9,Promo_Codes!$F$2:$F$9,DATE(2099,1,1)),IF(Table5[[#This Row],[OrderDate]]>_xlpm.expiry,"Expired Code Used","Valid")) -> Valid
A50: ORD-1048 | B50: 45911 | C50: Pradeep Maharjan | D50: 9848-372616 | E50: 45889 | F50: =IF(B50-E50<=2,"New","Returning") -> Returning | G50: Chitwan | H50: Kathmandu Momo House | I50: Momo | J50: Veg Momo (Fried) | K50: 2 | L50: R-122 | M50: IME Pay | O50: Delivered | P50: =IF(O50=""," NEED REVIEW","") | Q50: 5 | R50: 51 | T50: =_xlfn.CONCAT(Table5[[#This Row],[OrderID]]," | ",Table5[[#This Row],[City]]," | ",Table5[[#This Row],[ItemName]]) -> ORD-1048 | Chitwan | Veg Momo (Fried) | U50: =UPPER(Table5[[#This Row],[City]]) -> CHITWAN | V50: =LOWER(Table5[[#This Row],[PaymentMethod]]) -> ime pay | W50: {=_xlfn.XLOOKUP(TRIM(Table5[[#This Row],[ItemName]]), TRIM(Menu_Price_List_tbl[ItemName]),Menu_Price_List_tbl[UnitPrice_NPR])} -> 160 | X50: =W50*K50 -> 320 | Y50: =_xlfn.XLOOKUP(Table5[[#This Row],[City]],City_Delivery_Fee_tbl[City],City_Delivery_Fee_tbl[BaseDeliveryFee_NPR]) -> 80 | Z50: =IF(ISBLANK(Table5[[#This Row],[PromoCode]]), 0, _xlfn.LET( _xlpm.type, _xlfn.XLOOKUP(Table5[[#This Row],[PromoCode]], Promo_Codes!$A$2:$A$9, Promo_Codes!$C$2:$C$9, "Flat"), _xlpm.val, _xlfn.XLOOKUP(Table5[[#This Row],[PromoCode]], Promo_Codes!$A$2:$A$9, Promo_Codes!$D$2:$D$9, 0), IF(_xlpm.type="Percentage", Table5[[#This Row],[Order Amount]]*(_xlpm.val/100), _xlpm.val) ) ) -> 0 | AA50: =Table5[[#This Row],[Order Amount]]+Table5[[#This Row],[Delivery Fee]]-Table5[[#This Row],[Discount Amount]] -> 400 | AB50: =_xlfn.XLOOKUP(Table5[[#This Row],[RiderID]], Rider_Directory!$F$2:$F$26, Rider_Directory!$B$2:$B$26) -> Chitwan | AC50: {=_xlfn.IFS(Table5[[#This Row],[Final Amount]]<500, "Small", Table5[[#This Row],[Final Amount]]<=1000, "Medium", Table5[[#This Row],[Final Amount]]>1000, "Large")} -> Small | AD50: =_xlfn.LET(_xlpm.expiry,_xlfn.XLOOKUP(Table5[[#This Row],[PromoCode]],Promo_Codes!$A$2:$A$9,Promo_Codes!$F$2:$F$9,DATE(2099,1,1)),IF(Table5[[#This Row],[OrderDate]]>_xlpm.expiry,"Expired Code Used","Valid")) -> Valid
A51: ORD-1049 | B51: 45911 | C51: Sabina Magar | D51: 9876-018955 | E51: 45880 | F51: =IF(B51-E51<=2,"New","Returning") -> Returning | G51: Butwal | H51: Fast Bites | I51: Fast Food | J51: Chicken Pizza | K51: 2 | L51: R-120 | M51: Khalti | O51: Delivered | P51: =IF(O51=""," NEED REVIEW","") | Q51: 3 | R51: 44 | S51: not happy, order took too long | T51: =_xlfn.CONCAT(Table5[[#This Row],[OrderID]]," | ",Table5[[#This Row],[City]]," | ",Table5[[#This Row],[ItemName]]) -> ORD-1049 | Butwal | Chicken Pizza | U51: =UPPER(Table5[[#This Row],[City]]) -> BUTWAL | V51: =LOWER(Table5[[#This Row],[PaymentMethod]]) -> khalti | W51: {=_xlfn.XLOOKUP(TRIM(Table5[[#This Row],[ItemName]]), TRIM(Menu_Price_List_tbl[ItemName]),Menu_Price_List_tbl[UnitPrice_NPR])} -> 650 | X51: =W51*K51 -> 1300 | Y51: =_xlfn.XLOOKUP(Table5[[#This Row],[City]],City_Delivery_Fee_tbl[City],City_Delivery_Fee_tbl[BaseDeliveryFee_NPR]) -> 85 | Z51: =IF(ISBLANK(Table5[[#This Row],[PromoCode]]), 0, _xlfn.LET( _xlpm.type, _xlfn.XLOOKUP(Table5[[#This Row],[PromoCode]], Promo_Codes!$A$2:$A$9, Promo_Codes!$C$2:$C$9, "Flat"), _xlpm.val, _xlfn.XLOOKUP(Table5[[#This Row],[PromoCode]], Promo_Codes!$A$2:$A$9, Promo_Codes!$D$2:$D$9, 0), IF(_xlpm.type="Percentage", Table5[[#This Row],[Order Amount]]*(_xlpm.val/100), _xlpm.val) ) ) -> 0 | AA51: =Table5[[#This Row],[Order Amount]]+Table5[[#This Row],[Delivery Fee]]-Table5[[#This Row],[Discount Amount]] -> 1385 | AB51: =_xlfn.XLOOKUP(Table5[[#This Row],[RiderID]], Rider_Directory!$F$2:$F$26, Rider_Directory!$B$2:$B$26) -> Butwal | AC51: {=_xlfn.IFS(Table5[[#This Row],[Final Amount]]<500, "Small", Table5[[#This Row],[Final Amount]]<=1000, "Medium", Table5[[#This Row],[Final Amount]]>1000, "Large")} -> Large | AD51: =_xlfn.LET(_xlpm.expiry,_xlfn.XLOOKUP(Table5[[#This Row],[PromoCode]],Promo_Codes!$A$2:$A$9,Promo_Codes!$F$2:$F$9,DATE(2099,1,1)),IF(Table5[[#This Row],[OrderDate]]>_xlpm.expiry,"Expired Code Used","Valid")) -> Valid
A52: ORD-1050 | B52: 45911 | C52: Milan Thapa | D52: 9809-773797 | E52: 45909 | F52: =IF(B52-E52<=2,"New","Returning") -> New | G52: Kathmandu | H52: Wok Point | I52: Chinese | J52: Chicken Fried Rice | K52: 1 | L52: R-101 | M52: eSewa | O52: Delivered | P52: =IF(O52=""," NEED REVIEW","") | Q52: 3 | R52: 30 | S52: delivery was very late | T52: =_xlfn.CONCAT(Table5[[#This Row],[OrderID]]," | ",Table5[[#This Row],[City]]," | ",Table5[[#This Row],[ItemName]]) -> ORD-1050 | Kathmandu | Chicken Fried Rice | U52: =UPPER(Table5[[#This Row],[City]]) -> KATHMANDU | V52: =LOWER(Table5[[#This Row],[PaymentMethod]]) -> esewa | W52: {=_xlfn.XLOOKUP(TRIM(Table5[[#This Row],[ItemName]]), TRIM(Menu_Price_List_tbl[ItemName]),Menu_Price_List_tbl[UnitPrice_NPR])} -> 260 | X52: =W52*K52 -> 260 | Y52: =_xlfn.XLOOKUP(Table5[[#This Row],[City]],City_Delivery_Fee_tbl[City],City_Delivery_Fee_tbl[BaseDeliveryFee_NPR]) -> 50 | Z52: =IF(ISBLANK(Table5[[#This Row],[PromoCode]]), 0, _xlfn.LET( _xlpm.type, _xlfn.XLOOKUP(Table5[[#This Row],[PromoCode]], Promo_Codes!$A$2:$A$9, Promo_Codes!$C$2:$C$9, "Flat"), _xlpm.val, _xlfn.XLOOKUP(Table5[[#This Row],[PromoCode]], Promo_Codes!$A$2:$A$9, Promo_Codes!$D$2:$D$9, 0), IF(_xlpm.type="Percentage", Table5[[#This Row],[Order Amount]]*(_xlpm.val/100), _xlpm.val) ) ) -> 0 | AA52: =Table5[[#This Row],[Order Amount]]+Table5[[#This Row],[Delivery Fee]]-Table5[[#This Row],[Discount Amount]] -> 310 | AB52: =_xlfn.XLOOKUP(Table5[[#This Row],[RiderID]], Rider_Directory!$F$2:$F$26, Rider_Directory!$B$2:$B$26) -> Kathmandu | AC52: {=_xlfn.IFS(Table5[[#This Row],[Final Amount]]<500, "Small", Table5[[#This Row],[Final Amount]]<=1000, "Medium", Table5[[#This Row],[Final Amount]]>1000, "Large")} -> Small | AD52: =_xlfn.LET(_xlpm.expiry,_xlfn.XLOOKUP(Table5[[#This Row],[PromoCode]],Promo_Codes!$A$2:$A$9,Promo_Codes!$F$2:$F$9,DATE(2099,1,1)),IF(Table5[[#This Row],[OrderDate]]>_xlpm.expiry,"Expired Code Used","Valid")) -> Valid
A53: ORD-1051 | B53: 45911 | C53: Pradeep Tamang | D53: 9833-249351 | E53: 45909 | F53: =IF(B53-E53<=2,"New","Returning") -> New | G53: Lalitpur | H53: Momo Hut | I53: Momo | J53: Chicken Momo (Fried) | K53: 3 | L53: R-107 | M53: ConnectIPS | O53: Delivered | P53: =IF(O53=""," NEED REVIEW","") | Q53: 4 | R53: 43 | S53: Fast delivery today | T53: =_xlfn.CONCAT(Table5[[#This Row],[OrderID]]," | ",Table5[[#This Row],[City]]," | ",Table5[[#This Row],[ItemName]]) -> ORD-1051 | Lalitpur | Chicken Momo (Fried) | U53: =UPPER(Table5[[#This Row],[City]]) -> LALITPUR | V53: =LOWER(Table5[[#This Row],[PaymentMethod]]) -> connectips | W53: {=_xlfn.XLOOKUP(TRIM(Table5[[#This Row],[ItemName]]), TRIM(Menu_Price_List_tbl[ItemName]),Menu_Price_List_tbl[UnitPrice_NPR])} -> 210 | X53: =W53*K53 -> 630 | Y53: =_xlfn.XLOOKUP(Table5[[#This Row],[City]],City_Delivery_Fee_tbl[City],City_Delivery_Fee_tbl[BaseDeliveryFee_NPR]) -> 50 | Z53: =IF(ISBLANK(Table5[[#This Row],[PromoCode]]), 0, _xlfn.LET( _xlpm.type, _xlfn.XLOOKUP(Table5[[#This Row],[PromoCode]], Promo_Codes!$A$2:$A$9, Promo_Codes!$C$2:$C$9, "Flat"), _xlpm.val, _xlfn.XLOOKUP(Table5[[#This Row],[PromoCode]], Promo_Codes!$A$2:$A$9, Promo_Codes!$D$2:$D$9, 0), IF(_xlpm.type="Percentage", Table5[[#This Row],[Order Amount]]*(_xlpm.val/100), _xlpm.val) ) ) -> 0 | AA53: =Table5[[#This Row],[Order Amount]]+Table5[[#This Row],[Delivery Fee]]-Table5[[#This Row],[Discount Amount]] -> 680 | AB53: =_xlfn.XLOOKUP(Table5[[#This Row],[RiderID]], Rider_Directory!$F$2:$F$26, Rider_Directory!$B$2:$B$26) -> Lalitpur | AC53: {=_xlfn.IFS(Table5[[#This Row],[Final Amount]]<500, "Small", Table5[[#This Row],[Final Amount]]<=1000, "Medium", Table5[[#This Row],[Final Amount]]>1000, "Large")} -> Medium | AD53: =_xlfn.LET(_xlpm.expiry,_xlfn.XLOOKUP(Table5[[#This Row],[PromoCode]],Promo_Codes!$A$2:$A$9,Promo_Codes!$F$2:$F$9,DATE(2099,1,1)),IF(Table5[[#This Row],[OrderDate]]>_xlpm.expiry,"Expired Code Used","Valid")) -> Valid
A54: ORD-1052 | B54: 45912 | C54: Nirmala Dahal | D54: 9836-439008 | E54: 45910 | F54: =IF(B54-E54<=2,"New","Returning") -> New | G54: Butwal | H54: Sekuwa Point | I54: Sekuwa | J54: Buff Sekuwa | K54: 1 | L54: R-120 | M54: eSewa | N54: FIRSTORDER | O54: Delivered | P54: =IF(O54=""," NEED REVIEW","") | Q54: 2 | R54: 28 | T54: =_xlfn.CONCAT(Table5[[#This Row],[OrderID]]," | ",Table5[[#This Row],[City]]," | ",Table5[[#This Row],[ItemName]]) -> ORD-1052 | Butwal | Buff Sekuwa | U54: =UPPER(Table5[[#This Row],[City]]) -> BUTWAL | V54: =LOWER(Table5[[#This Row],[PaymentMethod]]) -> esewa | W54: {=_xlfn.XLOOKUP(TRIM(Table5[[#This Row],[ItemName]]), TRIM(Menu_Price_List_tbl[ItemName]),Menu_Price_List_tbl[UnitPrice_NPR])} -> 380 | X54: =W54*K54 -> 380 | Y54: =_xlfn.XLOOKUP(Table5[[#This Row],[City]],City_Delivery_Fee_tbl[City],City_Delivery_Fee_tbl[BaseDeliveryFee_NPR]) -> 85 | Z54: =IF(ISBLANK(Table5[[#This Row],[PromoCode]]), 0, _xlfn.LET( _xlpm.type, _xlfn.XLOOKUP(Table5[[#This Row],[PromoCode]], Promo_Codes!$A$2:$A$9, Promo_Codes!$C$2:$C$9, "Flat"), _xlpm.val, _xlfn.XLOOKUP(Table5[[#This Row],[PromoCode]], Promo_Codes!$A$2:$A$9, Promo_Codes!$D$2:$D$9, 0), IF(_xlpm.type="Percentage", Table5[[#This Row],[Order Amount]]*(_xlpm.val/100), _xlpm.val) ) ) -> 100 | AA54: =Table5[[#This Row],[Order Amount]]+Table5[[#This Row],[Delivery Fee]]-Table5[[#This Row],[Discount Amount]] -> 365 | AB54: =_xlfn.XLOOKUP(Table5[[#This Row],[RiderID]], Rider_Directory!$F$2:$F$26, Rider_Directory!$B$2:$B$26) -> Butwal | AC54: {=_xlfn.IFS(Table5[[#This Row],[Final Amount]]<500, "Small", Table5[[#This Row],[Final Amount]]<=1000, "Medium", Table5[[#This Row],[Final Amount]]>1000, "Large")} -> Small | AD54: =_xlfn.LET(_xlpm.expiry,_xlfn.XLOOKUP(Table5[[#This Row],[PromoCode]],Promo_Codes!$A$2:$A$9,Promo_Codes!$F$2:$F$9,DATE(2099,1,1)),IF(Table5[[#This Row],[OrderDate]]>_xlpm.expiry,"Expired Code Used","Valid")) -> Valid
A55: ORD-1053 | B55: 45913 | C55: Ashok Bhattarai | D55: 9887-355706 | E55: 45913 | F55: =IF(B55-E55<=2,"New","Returning") -> New | G55: Lalitpur | H55: Fast Bites | I55: Fast Food | J55: Chicken Pizza | K55: 1 | L55: R-108 | M55: Khalti | O55: Delivered | P55: =IF(O55=""," NEED REVIEW","") | Q55: 4 | R55: 30 | S55: best momo in town | T55: =_xlfn.CONCAT(Table5[[#This Row],[OrderID]]," | ",Table5[[#This Row],[City]]," | ",Table5[[#This Row],[ItemName]]) -> ORD-1053 | Lalitpur | Chicken Pizza | U55: =UPPER(Table5[[#This Row],[City]]) -> LALITPUR | V55: =LOWER(Table5[[#This Row],[PaymentMethod]]) -> khalti | W55: {=_xlfn.XLOOKUP(TRIM(Table5[[#This Row],[ItemName]]), TRIM(Menu_Price_List_tbl[ItemName]),Menu_Price_List_tbl[UnitPrice_NPR])} -> 650 | X55: =W55*K55 -> 650 | Y55: =_xlfn.XLOOKUP(Table5[[#This Row],[City]],City_Delivery_Fee_tbl[City],City_Delivery_Fee_tbl[BaseDeliveryFee_NPR]) -> 50 | Z55: =IF(ISBLANK(Table5[[#This Row],[PromoCode]]), 0, _xlfn.LET( _xlpm.type, _xlfn.XLOOKUP(Table5[[#This Row],[PromoCode]], Promo_Codes!$A$2:$A$9, Promo_Codes!$C$2:$C$9, "Flat"), _xlpm.val, _xlfn.XLOOKUP(Table5[[#This Row],[PromoCode]], Promo_Codes!$A$2:$A$9, Promo_Codes!$D$2:$D$9, 0), IF(_xlpm.type="Percentage", Table5[[#This Row],[Order Amount]]*(_xlpm.val/100), _xlpm.val) ) ) -> 0 | AA55: =Table5[[#This Row],[Order Amount]]+Table5[[#This Row],[Delivery Fee]]-Table5[[#This Row],[Discount Amount]] -> 700 | AB55: =_xlfn.XLOOKUP(Table5[[#This Row],[RiderID]], Rider_Directory!$F$2:$F$26, Rider_Directory!$B$2:$B$26) -> Lalitpur | AC55: {=_xlfn.IFS(Table5[[#This Row],[Final Amount]]<500, "Small", Table5[[#This Row],[Final Amount]]<=1000, "Medium", Table5[[#This Row],[Final Amount]]>1000, "Large")} -> Medium | AD55: =_xlfn.LET(_xlpm.expiry,_xlfn.XLOOKUP(Table5[[#This Row],[PromoCode]],Promo_Codes!$A$2:$A$9,Promo_Codes!$F$2:$F$9,DATE(2099,1,1)),IF(Table5[[#This Row],[OrderDate]]>_xlpm.expiry,"Expired Code Used","Valid")) -> Valid
A56: ORD-1054 | B56: 45913 | C56: Rajan Basnet | D56: 9897-465075 | E56: 45911 | F56: =IF(B56-E56<=2,"New","Returning") -> New | G56: Pokhara | H56: Cafe Cup | I56: Beverages | J56: LEMON SODA | K56: 2 | L56: R-112 | M56: Cash on Delivery | O56: Returned | P56: =IF(O56=""," NEED REVIEW","") | R56: 25 | S56: fine I guess | T56: =_xlfn.CONCAT(Table5[[#This Row],[OrderID]]," | ",Table5[[#This Row],[City]]," | ",Table5[[#This Row],[ItemName]]) -> ORD-1054 | Pokhara | LEMON SODA | U56: =UPPER(Table5[[#This Row],[City]]) -> POKHARA | V56: =LOWER(Table5[[#This Row],[PaymentMethod]]) -> cash on delivery | W56: {=_xlfn.XLOOKUP(TRIM(Table5[[#This Row],[ItemName]]), TRIM(Menu_Price_List_tbl[ItemName]),Menu_Price_List_tbl[UnitPrice_NPR])} -> 100 | X56: =W56*K56 -> 200 | Y56: =_xlfn.XLOOKUP(Table5[[#This Row],[City]],City_Delivery_Fee_tbl[City],City_Delivery_Fee_tbl[BaseDeliveryFee_NPR]) -> 70 | Z56: =IF(ISBLANK(Table5[[#This Row],[PromoCode]]), 0, _xlfn.LET( _xlpm.type, _xlfn.XLOOKUP(Table5[[#This Row],[PromoCode]], Promo_Codes!$A$2:$A$9, Promo_Codes!$C$2:$C$9, "Flat"), _xlpm.val, _xlfn.XLOOKUP(Table5[[#This Row],[PromoCode]], Promo_Codes!$A$2:$A$9, Promo_Codes!$D$2:$D$9, 0), IF(_xlpm.type="Percentage", Table5[[#This Row],[Order Amount]]*(_xlpm.val/100), _xlpm.val) ) ) -> 0 | AA56: =Table5[[#This Row],[Order Amount]]+Table5[[#This Row],[Delivery Fee]]-Table5[[#This Row],[Discount Amount]] -> 270 | AB56: =_xlfn.XLOOKUP(Table5[[#This Row],[RiderID]], Rider_Directory!$F$2:$F$26, Rider_Directory!$B$2:$B$26) -> Pokhara | AC56: {=_xlfn.IFS(Table5[[#This Row],[Final Amount]]<500, "Small", Table5[[#This Row],[Final Amount]]<=1000, "Medium", Table5[[#This Row],[Final Amount]]>1000, "Large")} -> Small | AD56: =_xlfn.LET(_xlpm.expiry,_xlfn.XLOOKUP(Table5[[#This Row],[PromoCode]],Promo_Codes!$A$2:$A$9,Promo_Codes!$F$2:$F$9,DATE(2099,1,1)),IF(Table5[[#This Row],[OrderDate]]>_xlpm.expiry,"Expired Code Used","Valid")) -> Valid
A57: ORD-1055 | B57: 45915 | C57: Ramesh Lama | D57: 9853-705656 | E57: 45877 | F57: =IF(B57-E57<=2,"New","Returning") -> Returning | G57: Butwal | H57: Thakali Ghar | I57: Thakali Set | J57: Chicken Thakali Set | K57: 2 | L57: R-120 | M57: Cash on Delivery | O57: Delivered | P57: =IF(O57=""," NEED REVIEW","") | Q57: 3 | R57: 31 | T57: =_xlfn.CONCAT(Table5[[#This Row],[OrderID]]," | ",Table5[[#This Row],[City]]," | ",Table5[[#This Row],[ItemName]]) -> ORD-1055 | Butwal | Chicken Thakali Set | U57: =UPPER(Table5[[#This Row],[City]]) -> BUTWAL | V57: =LOWER(Table5[[#This Row],[PaymentMethod]]) -> cash on delivery | W57: {=_xlfn.XLOOKUP(TRIM(Table5[[#This Row],[ItemName]]), TRIM(Menu_Price_List_tbl[ItemName]),Menu_Price_List_tbl[UnitPrice_NPR])} -> 480 | X57: =W57*K57 -> 960 | Y57: =_xlfn.XLOOKUP(Table5[[#This Row],[City]],City_Delivery_Fee_tbl[City],City_Delivery_Fee_tbl[BaseDeliveryFee_NPR]) -> 85 | Z57: =IF(ISBLANK(Table5[[#This Row],[PromoCode]]), 0, _xlfn.LET( _xlpm.type, _xlfn.XLOOKUP(Table5[[#This Row],[PromoCode]], Promo_Codes!$A$2:$A$9, Promo_Codes!$C$2:$C$9, "Flat"), _xlpm.val, _xlfn.XLOOKUP(Table5[[#This Row],[PromoCode]], Promo_Codes!$A$2:$A$9, Promo_Codes!$D$2:$D$9, 0), IF(_xlpm.type="Percentage", Table5[[#This Row],[Order Amount]]*(_xlpm.val/100), _xlpm.val) ) ) -> 0 | AA57: =Table5[[#This Row],[Order Amount]]+Table5[[#This Row],[Delivery Fee]]-Table5[[#This Row],[Discount Amount]] -> 1045 | AB57: =_xlfn.XLOOKUP(Table5[[#This Row],[RiderID]], Rider_Directory!$F$2:$F$26, Rider_Directory!$B$2:$B$26) -> Butwal | AC57: {=_xlfn.IFS(Table5[[#This Row],[Final Amount]]<500, "Small", Table5[[#This Row],[Final Amount]]<=1000, "Medium", Table5[[#This Row],[Final Amount]]>1000, "Large")} -> Large | AD57: =_xlfn.LET(_xlpm.expiry,_xlfn.XLOOKUP(Table5[[#This Row],[PromoCode]],Promo_Codes!$A$2:$A$9,Promo_Codes!$F$2:$F$9,DATE(2099,1,1)),IF(Table5[[#This Row],[OrderDate]]>_xlpm.expiry,"Expired Code Used","Valid")) -> Valid
A58: ORD-1056 | B58: 45916 | C58: Ramesh Poudel | D58: 9807-924402 | E58: 45916 | F58: =IF(B58-E58<=2,"New","Returning") -> New | G58: Bhaktapur | H58: Kathmandu Momo House | I58: Momo | J58: Veg Momo (Steamed) | K58: 3 | L58: R-111 | M58: IME Pay | N58: MOMO20 | O58: Delivered | P58: =IF(O58=""," NEED REVIEW","") | Q58: 5 | R58: 30 | S58: packaging was nice | T58: =_xlfn.CONCAT(Table5[[#This Row],[OrderID]]," | ",Table5[[#This Row],[City]]," | ",Table5[[#This Row],[ItemName]]) -> ORD-1056 | Bhaktapur | Veg Momo (Steamed) | U58: =UPPER(Table5[[#This Row],[City]]) -> BHAKTAPUR | V58: =LOWER(Table5[[#This Row],[PaymentMethod]]) -> ime pay | W58: {=_xlfn.XLOOKUP(TRIM(Table5[[#This Row],[ItemName]]), TRIM(Menu_Price_List_tbl[ItemName]),Menu_Price_List_tbl[UnitPrice_NPR])} -> 150 | X58: =W58*K58 -> 450 | Y58: =_xlfn.XLOOKUP(Table5[[#This Row],[City]],City_Delivery_Fee_tbl[City],City_Delivery_Fee_tbl[BaseDeliveryFee_NPR]) -> 55 | Z58: =IF(ISBLANK(Table5[[#This Row],[PromoCode]]), 0, _xlfn.LET( _xlpm.type, _xlfn.XLOOKUP(Table5[[#This Row],[PromoCode]], Promo_Codes!$A$2:$A$9, Promo_Codes!$C$2:$C$9, "Flat"), _xlpm.val, _xlfn.XLOOKUP(Table5[[#This Row],[PromoCode]], Promo_Codes!$A$2:$A$9, Promo_Codes!$D$2:$D$9, 0), IF(_xlpm.type="Percentage", Table5[[#This Row],[Order Amount]]*(_xlpm.val/100), _xlpm.val) ) ) -> 90 | AA58: =Table5[[#This Row],[Order Amount]]+Table5[[#This Row],[Delivery Fee]]-Table5[[#This Row],[Discount Amount]] -> 415 | AB58: =_xlfn.XLOOKUP(Table5[[#This Row],[RiderID]], Rider_Directory!$F$2:$F$26, Rider_Directory!$B$2:$B$26) -> Bhaktapur | AC58: {=_xlfn.IFS(Table5[[#This Row],[Final Amount]]<500, "Small", Table5[[#This Row],[Final Amount]]<=1000, "Medium", Table5[[#This Row],[Final Amount]]>1000, "Large")} -> Small | AD58: =_xlfn.LET(_xlpm.expiry,_xlfn.XLOOKUP(Table5[[#This Row],[PromoCode]],Promo_Codes!$A$2:$A$9,Promo_Codes!$F$2:$F$9,DATE(2099,1,1)),IF(Table5[[#This Row],[OrderDate]]>_xlpm.expiry,"Expired Code Used","Valid")) -> Valid
A59: ORD-1057 | B59: 45917 | C59: Nisha Shakya | D59: 9866-661760 | E59: 45917 | F59: =IF(B59-E59<=2,"New","Returning") -> New | G59: Biratnagar | H59: Golden Dragon Kitchen | I59: Chinese | J59: Veg Chopsuey | K59: 1 | L59: R-116 | M59: Khalti | O59: Cancelled | P59: =IF(O59=""," NEED REVIEW","") | R59: 46 | T59: =_xlfn.CONCAT(Table5[[#This Row],[OrderID]]," | ",Table5[[#This Row],[City]]," | ",Table5[[#This Row],[ItemName]]) -> ORD-1057 | Biratnagar | Veg Chopsuey | U59: =UPPER(Table5[[#This Row],[City]]) -> BIRATNAGAR | V59: =LOWER(Table5[[#This Row],[PaymentMethod]]) -> khalti | W59: {=_xlfn.XLOOKUP(TRIM(Table5[[#This Row],[ItemName]]), TRIM(Menu_Price_List_tbl[ItemName]),Menu_Price_List_tbl[UnitPrice_NPR])} -> 260 | X59: =W59*K59 -> 260 | Y59: =_xlfn.XLOOKUP(Table5[[#This Row],[City]],City_Delivery_Fee_tbl[City],City_Delivery_Fee_tbl[BaseDeliveryFee_NPR]) -> 90 | Z59: =IF(ISBLANK(Table5[[#This Row],[PromoCode]]), 0, _xlfn.LET( _xlpm.type, _xlfn.XLOOKUP(Table5[[#This Row],[PromoCode]], Promo_Codes!$A$2:$A$9, Promo_Codes!$C$2:$C$9, "Flat"), _xlpm.val, _xlfn.XLOOKUP(Table5[[#This Row],[PromoCode]], Promo_Codes!$A$2:$A$9, Promo_Codes!$D$2:$D$9, 0), IF(_xlpm.type="Percentage", Table5[[#This Row],[Order Amount]]*(_xlpm.val/100), _xlpm.val) ) ) -> 0 | AA59: =Table5[[#This Row],[Order Amount]]+Table5[[#This Row],[Delivery Fee]]-Table5[[#This Row],[Discount Amount]] -> 350 | AB59: =_xlfn.XLOOKUP(Table5[[#This Row],[RiderID]], Rider_Directory!$F$2:$F$26, Rider_Directory!$B$2:$B$26) -> Biratnagar | AC59: {=_xlfn.IFS(Table5[[#This Row],[Final Amount]]<500, "Small", Table5[[#This Row],[Final Amount]]<=1000, "Medium", Table5[[#This Row],[Final Amount]]>1000, "Large")} -> Small | AD59: =_xlfn.LET(_xlpm.expiry,_xlfn.XLOOKUP(Table5[[#This Row],[PromoCode]],Promo_Codes!$A$2:$A$9,Promo_Codes!$F$2:$F$9,DATE(2099,1,1)),IF(Table5[[#This Row],[OrderDate]]>_xlpm.expiry,"Expired Code Used","Valid")) -> Valid
A60: ORD-1058 | B60: 45918 | C60: Bishal Basnet | D60: 9878-245040 | E60: 45916 | F60: =IF(B60-E60<=2,"New","Returning") -> New | G60: Biratnagar | H60: Thakali Ghar | I60: Thakali Set | J60: Chicken Thakali Set | K60: 3 | L60: R-117 | M60: eSewa | O60: Delivered | P60: =IF(O60=""," NEED REVIEW","") | Q60: 5 | R60: 50 | S60: packaging was nice | T60: =_xlfn.CONCAT(Table5[[#This Row],[OrderID]]," | ",Table5[[#This Row],[City]]," | ",Table5[[#This Row],[ItemName]]) -> ORD-1058 | Biratnagar | Chicken Thakali Set | U60: =UPPER(Table5[[#This Row],[City]]) -> BIRATNAGAR | V60: =LOWER(Table5[[#This Row],[PaymentMethod]]) -> esewa | W60: {=_xlfn.XLOOKUP(TRIM(Table5[[#This Row],[ItemName]]), TRIM(Menu_Price_List_tbl[ItemName]),Menu_Price_List_tbl[UnitPrice_NPR])} -> 480 | X60: =W60*K60 -> 1440 | Y60: =_xlfn.XLOOKUP(Table5[[#This Row],[City]],City_Delivery_Fee_tbl[City],City_Delivery_Fee_tbl[BaseDeliveryFee_NPR]) -> 90 | Z60: =IF(ISBLANK(Table5[[#This Row],[PromoCode]]), 0, _xlfn.LET( _xlpm.type, _xlfn.XLOOKUP(Table5[[#This Row],[PromoCode]], Promo_Codes!$A$2:$A$9, Promo_Codes!$C$2:$C$9, "Flat"), _xlpm.val, _xlfn.XLOOKUP(Table5[[#This Row],[PromoCode]], Promo_Codes!$A$2:$A$9, Promo_Codes!$D$2:$D$9, 0), IF(_xlpm.type="Percentage", Table5[[#This Row],[Order Amount]]*(_xlpm.val/100), _xlpm.val) ) ) -> 0 | AA60: =Table5[[#This Row],[Order Amount]]+Table5[[#This Row],[Delivery Fee]]-Table5[[#This Row],[Discount Amount]] -> 1530 | AB60: =_xlfn.XLOOKUP(Table5[[#This Row],[RiderID]], Rider_Directory!$F$2:$F$26, Rider_Directory!$B$2:$B$26) -> Biratnagar | AC60: {=_xlfn.IFS(Table5[[#This Row],[Final Amount]]<500, "Small", Table5[[#This Row],[Final Amount]]<=1000, "Medium", Table5[[#This Row],[Final Amount]]>1000, "Large")} -> Large | AD60: =_xlfn.LET(_xlpm.expiry,_xlfn.XLOOKUP(Table5[[#This Row],[PromoCode]],Promo_Codes!$A$2:$A$9,Promo_Codes!$F$2:$F$9,DATE(2099,1,1)),IF(Table5[[#This Row],[OrderDate]]>_xlpm.expiry,"Expired Code Used","Valid")) -> Valid
A61: ORD-1059 | B61: 45918 | C61: Sita Maharjan | D61: 9880-021581 | E61: 45916 | F61: =IF(B61-E61<=2,"New","Returning") -> New | G61: Lalitpur | H61: Sweet Home Bakery | I61: Bakery | J61: Chocolate Pastry | K61: 2 | L61: R-108 | M61: Cash on Delivery | O61: Delivered | P61: =IF(O61=""," NEED REVIEW","") | Q61: 5 | R61: 23 | T61: =_xlfn.CONCAT(Table5[[#This Row],[OrderID]]," | ",Table5[[#This Row],[City]]," | ",Table5[[#This Row],[ItemName]]) -> ORD-1059 | Lalitpur | Chocolate Pastry | U61: =UPPER(Table5[[#This Row],[City]]) -> LALITPUR | V61: =LOWER(Table5[[#This Row],[PaymentMethod]]) -> cash on delivery | W61: {=_xlfn.XLOOKUP(TRIM(Table5[[#This Row],[ItemName]]), TRIM(Menu_Price_List_tbl[ItemName]),Menu_Price_List_tbl[UnitPrice_NPR])} -> 150 | X61: =W61*K61 -> 300 | Y61: =_xlfn.XLOOKUP(Table5[[#This Row],[City]],City_Delivery_Fee_tbl[City],City_Delivery_Fee_tbl[BaseDeliveryFee_NPR]) -> 50 | Z61: =IF(ISBLANK(Table5[[#This Row],[PromoCode]]), 0, _xlfn.LET( _xlpm.type, _xlfn.XLOOKUP(Table5[[#This Row],[PromoCode]], Promo_Codes!$A$2:$A$9, Promo_Codes!$C$2:$C$9, "Flat"), _xlpm.val, _xlfn.XLOOKUP(Table5[[#This Row],[PromoCode]], Promo_Codes!$A$2:$A$9, Promo_Codes!$D$2:$D$9, 0), IF(_xlpm.type="Percentage", Table5[[#This Row],[Order Amount]]*(_xlpm.val/100), _xlpm.val) ) ) -> 0 | AA61: =Table5[[#This Row],[Order Amount]]+Table5[[#This Row],[Delivery Fee]]-Table5[[#This Row],[Discount Amount]] -> 350 | AB61: =_xlfn.XLOOKUP(Table5[[#This Row],[RiderID]], Rider_Directory!$F$2:$F$26, Rider_Directory!$B$2:$B$26) -> Lalitpur | AC61: {=_xlfn.IFS(Table5[[#This Row],[Final Amount]]<500, "Small", Table5[[#This Row],[Final Amount]]<=1000, "Medium", Table5[[#This Row],[Final Amount]]>1000, "Large")} -> Small | AD61: =_xlfn.LET(_xlpm.expiry,_xlfn.XLOOKUP(Table5[[#This Row],[PromoCode]],Promo_Codes!$A$2:$A$9,Promo_Codes!$F$2:$F$9,DATE(2099,1,1)),IF(Table5[[#This Row],[OrderDate]]>_xlpm.expiry,"Expired Code Used","Valid")) -> Valid
A62: ORD-1060 | B62: 45918 | C62: Sujan Dahal | D62: 9809-378657 | E62: 45918 | F62: =IF(B62-E62<=2,"New","Returning") -> New | G62: Biratnagar | H62: Golden Dragon Kitchen | I62: Chinese | J62: chicken manchurian | K62: 1 | L62: R-116 | M62: IME Pay | O62: Delivered | P62: =IF(O62=""," NEED REVIEW","") | Q62: 4 | R62: 43 | S62: Fast delivery today | T62: =_xlfn.CONCAT(Table5[[#This Row],[OrderID]]," | ",Table5[[#This Row],[City]]," | ",Table5[[#This Row],[ItemName]]) -> ORD-1060 | Biratnagar | chicken manchurian | U62: =UPPER(Table5[[#This Row],[City]]) -> BIRATNAGAR | V62: =LOWER(Table5[[#This Row],[PaymentMethod]]) -> ime pay | W62: {=_xlfn.XLOOKUP(TRIM(Table5[[#This Row],[ItemName]]), TRIM(Menu_Price_List_tbl[ItemName]),Menu_Price_List_tbl[UnitPrice_NPR])} -> 320 | X62: =W62*K62 -> 320 | Y62: =_xlfn.XLOOKUP(Table5[[#This Row],[City]],City_Delivery_Fee_tbl[City],City_Delivery_Fee_tbl[BaseDeliveryFee_NPR]) -> 90 | Z62: =IF(ISBLANK(Table5[[#This Row],[PromoCode]]), 0, _xlfn.LET( _xlpm.type, _xlfn.XLOOKUP(Table5[[#This Row],[PromoCode]], Promo_Codes!$A$2:$A$9, Promo_Codes!$C$2:$C$9, "Flat"), _xlpm.val, _xlfn.XLOOKUP(Table5[[#This Row],[PromoCode]], Promo_Codes!$A$2:$A$9, Promo_Codes!$D$2:$D$9, 0), IF(_xlpm.type="Percentage", Table5[[#This Row],[Order Amount]]*(_xlpm.val/100), _xlpm.val) ) ) -> 0 | AA62: =Table5[[#This Row],[Order Amount]]+Table5[[#This Row],[Delivery Fee]]-Table5[[#This Row],[Discount Amount]] -> 410 | AB62: =_xlfn.XLOOKUP(Table5[[#This Row],[RiderID]], Rider_Directory!$F$2:$F$26, Rider_Directory!$B$2:$B$26) -> Biratnagar | AC62: {=_xlfn.IFS(Table5[[#This Row],[Final Amount]]<500, "Small", Table5[[#This Row],[Final Amount]]<=1000, "Medium", Table5[[#This Row],[Final Amount]]>1000, "Large")} -> Small | AD62: =_xlfn.LET(_xlpm.expiry,_xlfn.XLOOKUP(Table5[[#This Row],[PromoCode]],Promo_Codes!$A$2:$A$9,Promo_Codes!$F$2:$F$9,DATE(2099,1,1)),IF(Table5[[#This Row],[OrderDate]]>_xlpm.expiry,"Expired Code Used","Valid")) -> Valid
A63: ORD-1061 | B63: 45919 | C63: Suresh Magar | D63: 9822-791805 | E63: 45871 | F63: =IF(B63-E63<=2,"New","Returning") -> Returning | G63: Kathmandu | H63: Golden Dragon Kitchen | I63: Chinese | J63: Chicken Fried Rice | K63: 1 | L63: R-105 | M63: IME Pay | N63: FIRSTORDER | O63: Delivered | P63: =IF(O63=""," NEED REVIEW","") | Q63: 5 | R63: 33 | S63: Fast delivery today | T63: =_xlfn.CONCAT(Table5[[#This Row],[OrderID]]," | ",Table5[[#This Row],[City]]," | ",Table5[[#This Row],[ItemName]]) -> ORD-1061 | Kathmandu | Chicken Fried Rice | U63: =UPPER(Table5[[#This Row],[City]]) -> KATHMANDU | V63: =LOWER(Table5[[#This Row],[PaymentMethod]]) -> ime pay | W63: {=_xlfn.XLOOKUP(TRIM(Table5[[#This Row],[ItemName]]), TRIM(Menu_Price_List_tbl[ItemName]),Menu_Price_List_tbl[UnitPrice_NPR])} -> 260 | X63: =W63*K63 -> 260 | Y63: =_xlfn.XLOOKUP(Table5[[#This Row],[City]],City_Delivery_Fee_tbl[City],City_Delivery_Fee_tbl[BaseDeliveryFee_NPR]) -> 50 | Z63: =IF(ISBLANK(Table5[[#This Row],[PromoCode]]), 0, _xlfn.LET( _xlpm.type, _xlfn.XLOOKUP(Table5[[#This Row],[PromoCode]], Promo_Codes!$A$2:$A$9, Promo_Codes!$C$2:$C$9, "Flat"), _xlpm.val, _xlfn.XLOOKUP(Table5[[#This Row],[PromoCode]], Promo_Codes!$A$2:$A$9, Promo_Codes!$D$2:$D$9, 0), IF(_xlpm.type="Percentage", Table5[[#This Row],[Order Amount]]*(_xlpm.val/100), _xlpm.val) ) ) -> 100 | AA63: =Table5[[#This Row],[Order Amount]]+Table5[[#This Row],[Delivery Fee]]-Table5[[#This Row],[Discount Amount]] -> 210 | AB63: =_xlfn.XLOOKUP(Table5[[#This Row],[RiderID]], Rider_Directory!$F$2:$F$26, Rider_Directory!$B$2:$B$26) -> Kathmandu | AC63: {=_xlfn.IFS(Table5[[#This Row],[Final Amount]]<500, "Small", Table5[[#This Row],[Final Amount]]<=1000, "Medium", Table5[[#This Row],[Final Amount]]>1000, "Large")} -> Small | AD63: =_xlfn.LET(_xlpm.expiry,_xlfn.XLOOKUP(Table5[[#This Row],[PromoCode]],Promo_Codes!$A$2:$A$9,Promo_Codes!$F$2:$F$9,DATE(2099,1,1)),IF(Table5[[#This Row],[OrderDate]]>_xlpm.expiry,"Expired Code Used","Valid")) -> Valid
A64: ORD-1062 | B64: 45921 | C64: Nisha Shakya | D64: 9866-661760 | E64: 45917 | F64: =IF(B64-E64<=2,"New","Returning") -> Returning | G64: Biratnagar | H64: Fast Bites | I64: Fast Food | J64: Chicken Pizza | K64: 1 | L64: R-117 | M64: ConnectIPS | O64: Delivered | P64: =IF(O64=""," NEED REVIEW","") | Q64: 5 | R64: 53 | S64: good food, will order again | T64: =_xlfn.CONCAT(Table5[[#This Row],[OrderID]]," | ",Table5[[#This Row],[City]]," | ",Table5[[#This Row],[ItemName]]) -> ORD-1062 | Biratnagar | Chicken Pizza | U64: =UPPER(Table5[[#This Row],[City]]) -> BIRATNAGAR | V64: =LOWER(Table5[[#This Row],[PaymentMethod]]) -> connectips | W64: {=_xlfn.XLOOKUP(TRIM(Table5[[#This Row],[ItemName]]), TRIM(Menu_Price_List_tbl[ItemName]),Menu_Price_List_tbl[UnitPrice_NPR])} -> 650 | X64: =W64*K64 -> 650 | Y64: =_xlfn.XLOOKUP(Table5[[#This Row],[City]],City_Delivery_Fee_tbl[City],City_Delivery_Fee_tbl[BaseDeliveryFee_NPR]) -> 90 | Z64: =IF(ISBLANK(Table5[[#This Row],[PromoCode]]), 0, _xlfn.LET( _xlpm.type, _xlfn.XLOOKUP(Table5[[#This Row],[PromoCode]], Promo_Codes!$A$2:$A$9, Promo_Codes!$C$2:$C$9, "Flat"), _xlpm.val, _xlfn.XLOOKUP(Table5[[#This Row],[PromoCode]], Promo_Codes!$A$2:$A$9, Promo_Codes!$D$2:$D$9, 0), IF(_xlpm.type="Percentage", Table5[[#This Row],[Order Amount]]*(_xlpm.val/100), _xlpm.val) ) ) -> 0 | AA64: =Table5[[#This Row],[Order Amount]]+Table5[[#This Row],[Delivery Fee]]-Table5[[#This Row],[Discount Amount]] -> 740 | AB64: =_xlfn.XLOOKUP(Table5[[#This Row],[RiderID]], Rider_Directory!$F$2:$F$26, Rider_Directory!$B$2:$B$26) -> Biratnagar | AC64: {=_xlfn.IFS(Table5[[#This Row],[Final Amount]]<500, "Small", Table5[[#This Row],[Final Amount]]<=1000, "Medium", Table5[[#This Row],[Final Amount]]>1000, "Large")} -> Medium | AD64: =_xlfn.LET(_xlpm.expiry,_xlfn.XLOOKUP(Table5[[#This Row],[PromoCode]],Promo_Codes!$A$2:$A$9,Promo_Codes!$F$2:$F$9,DATE(2099,1,1)),IF(Table5[[#This Row],[OrderDate]]>_xlpm.expiry,"Expired Code Used","Valid")) -> Valid
A65: ORD-1063 | B65: 45921 | C65: Rina Adhikari | D65: 9867-272042 | E65: 45743 | F65: =IF(B65-E65<=2,"New","Returning") -> Returning | G65: Bhaktapur | H65: Quick Snacks Corner | I65: Fast Food | J65: Chicken Burger | K65: 2 | L65: R-111 | M65: ConnectIPS | N65: DASHAIN10 | O65: Delivered | P65: =IF(O65=""," NEED REVIEW","") | Q65: 4 | R65: 31 | S65: Fast delivery today | T65: =_xlfn.CONCAT(Table5[[#This Row],[OrderID]]," | ",Table5[[#This Row],[City]]," | ",Table5[[#This Row],[ItemName]]) -> ORD-1063 | Bhaktapur | Chicken Burger | U65: =UPPER(Table5[[#This Row],[City]]) -> BHAKTAPUR | V65: =LOWER(Table5[[#This Row],[PaymentMethod]]) -> connectips | W65: {=_xlfn.XLOOKUP(TRIM(Table5[[#This Row],[ItemName]]), TRIM(Menu_Price_List_tbl[ItemName]),Menu_Price_List_tbl[UnitPrice_NPR])} -> 280 | X65: =W65*K65 -> 560 | Y65: =_xlfn.XLOOKUP(Table5[[#This Row],[City]],City_Delivery_Fee_tbl[City],City_Delivery_Fee_tbl[BaseDeliveryFee_NPR]) -> 55 | Z65: =IF(ISBLANK(Table5[[#This Row],[PromoCode]]), 0, _xlfn.LET( _xlpm.type, _xlfn.XLOOKUP(Table5[[#This Row],[PromoCode]], Promo_Codes!$A$2:$A$9, Promo_Codes!$C$2:$C$9, "Flat"), _xlpm.val, _xlfn.XLOOKUP(Table5[[#This Row],[PromoCode]], Promo_Codes!$A$2:$A$9, Promo_Codes!$D$2:$D$9, 0), IF(_xlpm.type="Percentage", Table5[[#This Row],[Order Amount]]*(_xlpm.val/100), _xlpm.val) ) ) -> 56 | AA65: =Table5[[#This Row],[Order Amount]]+Table5[[#This Row],[Delivery Fee]]-Table5[[#This Row],[Discount Amount]] -> 559 | AB65: =_xlfn.XLOOKUP(Table5[[#This Row],[RiderID]], Rider_Directory!$F$2:$F$26, Rider_Directory!$B$2:$B$26) -> Bhaktapur | AC65: {=_xlfn.IFS(Table5[[#This Row],[Final Amount]]<500, "Small", Table5[[#This Row],[Final Amount]]<=1000, "Medium", Table5[[#This Row],[Final Amount]]>1000, "Large")} -> Medium | AD65: =_xlfn.LET(_xlpm.expiry,_xlfn.XLOOKUP(Table5[[#This Row],[PromoCode]],Promo_Codes!$A$2:$A$9,Promo_Codes!$F$2:$F$9,DATE(2099,1,1)),IF(Table5[[#This Row],[OrderDate]]>_xlpm.expiry,"Expired Code Used","Valid")) -> Valid
A66: ORD-1064 | B66: 45922 | C66: Milan Poudel | D66: 9820-109832 | E66: 45921 | F66: =IF(B66-E66<=2,"New","Returning") -> New | G66: Kathmandu | H66: Fast Bites | I66: Fast Food | J66: Margherita Pizza | K66: 4 | L66: R-106 | M66: eSewa | N66: DASHAIN10 | O66: Delivered | P66: =IF(O66=""," NEED REVIEW","") | Q66: 5 | R66: 33 | T66: =_xlfn.CONCAT(Table5[[#This Row],[OrderID]]," | ",Table5[[#This Row],[City]]," | ",Table5[[#This Row],[ItemName]]) -> ORD-1064 | Kathmandu | Margherita Pizza | U66: =UPPER(Table5[[#This Row],[City]]) -> KATHMANDU | V66: =LOWER(Table5[[#This Row],[PaymentMethod]]) -> esewa | W66: {=_xlfn.XLOOKUP(TRIM(Table5[[#This Row],[ItemName]]), TRIM(Menu_Price_List_tbl[ItemName]),Menu_Price_List_tbl[UnitPrice_NPR])} -> 550 | X66: =W66*K66 -> 2200 | Y66: =_xlfn.XLOOKUP(Table5[[#This Row],[City]],City_Delivery_Fee_tbl[City],City_Delivery_Fee_tbl[BaseDeliveryFee_NPR]) -> 50 | Z66: =IF(ISBLANK(Table5[[#This Row],[PromoCode]]), 0, _xlfn.LET( _xlpm.type, _xlfn.XLOOKUP(Table5[[#This Row],[PromoCode]], Promo_Codes!$A$2:$A$9, Promo_Codes!$C$2:$C$9, "Flat"), _xlpm.val, _xlfn.XLOOKUP(Table5[[#This Row],[PromoCode]], Promo_Codes!$A$2:$A$9, Promo_Codes!$D$2:$D$9, 0), IF(_xlpm.type="Percentage", Table5[[#This Row],[Order Amount]]*(_xlpm.val/100), _xlpm.val) ) ) -> 220 | AA66: =Table5[[#This Row],[Order Amount]]+Table5[[#This Row],[Delivery Fee]]-Table5[[#This Row],[Discount Amount]] -> 2030 | AB66: =_xlfn.XLOOKUP(Table5[[#This Row],[RiderID]], Rider_Directory!$F$2:$F$26, Rider_Directory!$B$2:$B$26) -> Kathmandu | AC66: {=_xlfn.IFS(Table5[[#This Row],[Final Amount]]<500, "Small", Table5[[#This Row],[Final Amount]]<=1000, "Medium", Table5[[#This Row],[Final Amount]]>1000, "Large")} -> Large | AD66: =_xlfn.LET(_xlpm.expiry,_xlfn.XLOOKUP(Table5[[#This Row],[PromoCode]],Promo_Codes!$A$2:$A$9,Promo_Codes!$F$2:$F$9,DATE(2099,1,1)),IF(Table5[[#This Row],[OrderDate]]>_xlpm.expiry,"Expired Code Used","Valid")) -> Valid
A67: ORD-1065 | B67: 45924 | C67: Pradeep Maharjan | D67: 9848-372616 | E67: 45889 | F67: =IF(B67-E67<=2,"New","Returning") -> Returning | G67: Bhaktapur | H67: Cafe Cup | I67: Beverages | J67: Black Coffee | K67: 3 | L67: R-110 | M67: Khalti | N67: DASHAIN10 | O67: Delivered | P67: =IF(O67=""," NEED REVIEW","") | Q67: 4 | R67: 20 | T67: =_xlfn.CONCAT(Table5[[#This Row],[OrderID]]," | ",Table5[[#This Row],[City]]," | ",Table5[[#This Row],[ItemName]]) -> ORD-1065 | Bhaktapur | Black Coffee | U67: =UPPER(Table5[[#This Row],[City]]) -> BHAKTAPUR | V67: =LOWER(Table5[[#This Row],[PaymentMethod]]) -> khalti | W67: {=_xlfn.XLOOKUP(TRIM(Table5[[#This Row],[ItemName]]), TRIM(Menu_Price_List_tbl[ItemName]),Menu_Price_List_tbl[UnitPrice_NPR])} -> 90 | X67: =W67*K67 -> 270 | Y67: =_xlfn.XLOOKUP(Table5[[#This Row],[City]],City_Delivery_Fee_tbl[City],City_Delivery_Fee_tbl[BaseDeliveryFee_NPR]) -> 55 | Z67: =IF(ISBLANK(Table5[[#This Row],[PromoCode]]), 0, _xlfn.LET( _xlpm.type, _xlfn.XLOOKUP(Table5[[#This Row],[PromoCode]], Promo_Codes!$A$2:$A$9, Promo_Codes!$C$2:$C$9, "Flat"), _xlpm.val, _xlfn.XLOOKUP(Table5[[#This Row],[PromoCode]], Promo_Codes!$A$2:$A$9, Promo_Codes!$D$2:$D$9, 0), IF(_xlpm.type="Percentage", Table5[[#This Row],[Order Amount]]*(_xlpm.val/100), _xlpm.val) ) ) -> 27 | AA67: =Table5[[#This Row],[Order Amount]]+Table5[[#This Row],[Delivery Fee]]-Table5[[#This Row],[Discount Amount]] -> 298 | AB67: =_xlfn.XLOOKUP(Table5[[#This Row],[RiderID]], Rider_Directory!$F$2:$F$26, Rider_Directory!$B$2:$B$26) -> Bhaktapur | AC67: {=_xlfn.IFS(Table5[[#This Row],[Final Amount]]<500, "Small", Table5[[#This Row],[Final Amount]]<=1000, "Medium", Table5[[#This Row],[Final Amount]]>1000, "Large")} -> Small | AD67: =_xlfn.LET(_xlpm.expiry,_xlfn.XLOOKUP(Table5[[#This Row],[PromoCode]],Promo_Codes!$A$2:$A$9,Promo_Codes!$F$2:$F$9,DATE(2099,1,1)),IF(Table5[[#This Row],[OrderDate]]>_xlpm.expiry,"Expired Code Used","Valid")) -> Valid
A68: ORD-1066 | B68: 45926 | C68: Anish Shakya | D68: 9836-546107 | E68: 45926 | F68: =IF(B68-E68<=2,"New","Returning") -> New | G68: Pokhara | H68: Himalayan Bakers | I68: Bakery | J68: CHEESE CAKE SLICE | K68: 1 | L68: R-115 | M68: ConnectIPS | N68: DASHAIN10 | O68: Delivered | P68: =IF(O68=""," NEED REVIEW","") | Q68: 5 | R68: 15 | S68: quality was great as always | T68: =_xlfn.CONCAT(Table5[[#This Row],[OrderID]]," | ",Table5[[#This Row],[City]]," | ",Table5[[#This Row],[ItemName]]) -> ORD-1066 | Pokhara | CHEESE CAKE SLICE | U68: =UPPER(Table5[[#This Row],[City]]) -> POKHARA | V68: =LOWER(Table5[[#This Row],[PaymentMethod]]) -> connectips | W68: {=_xlfn.XLOOKUP(TRIM(Table5[[#This Row],[ItemName]]), TRIM(Menu_Price_List_tbl[ItemName]),Menu_Price_List_tbl[UnitPrice_NPR])} -> 250 | X68: =W68*K68 -> 250 | Y68: =_xlfn.XLOOKUP(Table5[[#This Row],[City]],City_Delivery_Fee_tbl[City],City_Delivery_Fee_tbl[BaseDeliveryFee_NPR]) -> 70 | Z68: =IF(ISBLANK(Table5[[#This Row],[PromoCode]]), 0, _xlfn.LET( _xlpm.type, _xlfn.XLOOKUP(Table5[[#This Row],[PromoCode]], Promo_Codes!$A$2:$A$9, Promo_Codes!$C$2:$C$9, "Flat"), _xlpm.val, _xlfn.XLOOKUP(Table5[[#This Row],[PromoCode]], Promo_Codes!$A$2:$A$9, Promo_Codes!$D$2:$D$9, 0), IF(_xlpm.type="Percentage", Table5[[#This Row],[Order Amount]]*(_xlpm.val/100), _xlpm.val) ) ) -> 25 | AA68: =Table5[[#This Row],[Order Amount]]+Table5[[#This Row],[Delivery Fee]]-Table5[[#This Row],[Discount Amount]] -> 295 | AB68: =_xlfn.XLOOKUP(Table5[[#This Row],[RiderID]], Rider_Directory!$F$2:$F$26, Rider_Directory!$B$2:$B$26) -> Pokhara | AC68: {=_xlfn.IFS(Table5[[#This Row],[Final Amount]]<500, "Small", Table5[[#This Row],[Final Amount]]<=1000, "Medium", Table5[[#This Row],[Final Amount]]>1000, "Large")} -> Small | AD68: =_xlfn.LET(_xlpm.expiry,_xlfn.XLOOKUP(Table5[[#This Row],[PromoCode]],Promo_Codes!$A$2:$A$9,Promo_Codes!$F$2:$F$9,DATE(2099,1,1)),IF(Table5[[#This Row],[OrderDate]]>_xlpm.expiry,"Expired Code Used","Valid")) -> Valid
A69: ORD-1067 | B69: 45927 | C69: Suresh Thapa | D69: 9888-387371 | E69: 45926 | F69: =IF(B69-E69<=2,"New","Returning") -> New | G69: Kathmandu | H69: Fast Bites | I69: Fast Food | J69: VEG FRIED RICE | K69: 1 | L69: R-101 | M69: eSewa | N69: WEEKEND10 | O69: Cancelled | P69: =IF(O69=""," NEED REVIEW","") | R69: 28 | T69: =_xlfn.CONCAT(Table5[[#This Row],[OrderID]]," | ",Table5[[#This Row],[City]]," | ",Table5[[#This Row],[ItemName]]) -> ORD-1067 | Kathmandu | VEG FRIED RICE | U69: =UPPER(Table5[[#This Row],[City]]) -> KATHMANDU | V69: =LOWER(Table5[[#This Row],[PaymentMethod]]) -> esewa | W69: {=_xlfn.XLOOKUP(TRIM(Table5[[#This Row],[ItemName]]), TRIM(Menu_Price_List_tbl[ItemName]),Menu_Price_List_tbl[UnitPrice_NPR])} -> 220 | X69: =W69*K69 -> 220 | Y69: =_xlfn.XLOOKUP(Table5[[#This Row],[City]],City_Delivery_Fee_tbl[City],City_Delivery_Fee_tbl[BaseDeliveryFee_NPR]) -> 50 | Z69: =IF(ISBLANK(Table5[[#This Row],[PromoCode]]), 0, _xlfn.LET( _xlpm.type, _xlfn.XLOOKUP(Table5[[#This Row],[PromoCode]], Promo_Codes!$A$2:$A$9, Promo_Codes!$C$2:$C$9, "Flat"), _xlpm.val, _xlfn.XLOOKUP(Table5[[#This Row],[PromoCode]], Promo_Codes!$A$2:$A$9, Promo_Codes!$D$2:$D$9, 0), IF(_xlpm.type="Percentage", Table5[[#This Row],[Order Amount]]*(_xlpm.val/100), _xlpm.val) ) ) -> 22 | AA69: =Table5[[#This Row],[Order Amount]]+Table5[[#This Row],[Delivery Fee]]-Table5[[#This Row],[Discount Amount]] -> 248 | AB69: =_xlfn.XLOOKUP(Table5[[#This Row],[RiderID]], Rider_Directory!$F$2:$F$26, Rider_Directory!$B$2:$B$26) -> Kathmandu | AC69: {=_xlfn.IFS(Table5[[#This Row],[Final Amount]]<500, "Small", Table5[[#This Row],[Final Amount]]<=1000, "Medium", Table5[[#This Row],[Final Amount]]>1000, "Large")} -> Small | AD69: =_xlfn.LET(_xlpm.expiry,_xlfn.XLOOKUP(Table5[[#This Row],[PromoCode]],Promo_Codes!$A$2:$A$9,Promo_Codes!$F$2:$F$9,DATE(2099,1,1)),IF(Table5[[#This Row],[OrderDate]]>_xlpm.expiry,"Expired Code Used","Valid")) -> Valid
A70: ORD-1068 | B70: 45927 | C70: Bandana Bhattarai | D70: 9800-474395 | E70: 45901 | F70: =IF(B70-E70<=2,"New","Returning") -> Returning | G70: Kathmandu | H70: Newa Kitchen | I70: Newari Khana | J70: Bara | K70: 1 | L70: R-104 | M70: Khalti | N70: DASHAIN10 | O70: Delivered | P70: =IF(O70=""," NEED REVIEW","") | R70: 36 | S70: okay experience | T70: =_xlfn.CONCAT(Table5[[#This Row],[OrderID]]," | ",Table5[[#This Row],[City]]," | ",Table5[[#This Row],[ItemName]]) -> ORD-1068 | Kathmandu | Bara | U70: =UPPER(Table5[[#This Row],[City]]) -> KATHMANDU | V70: =LOWER(Table5[[#This Row],[PaymentMethod]]) -> khalti | W70: {=_xlfn.XLOOKUP(TRIM(Table5[[#This Row],[ItemName]]), TRIM(Menu_Price_List_tbl[ItemName]),Menu_Price_List_tbl[UnitPrice_NPR])} -> 160 | X70: =W70*K70 -> 160 | Y70: =_xlfn.XLOOKUP(Table5[[#This Row],[City]],City_Delivery_Fee_tbl[City],City_Delivery_Fee_tbl[BaseDeliveryFee_NPR]) -> 50 | Z70: =IF(ISBLANK(Table5[[#This Row],[PromoCode]]), 0, _xlfn.LET( _xlpm.type, _xlfn.XLOOKUP(Table5[[#This Row],[PromoCode]], Promo_Codes!$A$2:$A$9, Promo_Codes!$C$2:$C$9, "Flat"), _xlpm.val, _xlfn.XLOOKUP(Table5[[#This Row],[PromoCode]], Promo_Codes!$A$2:$A$9, Promo_Codes!$D$2:$D$9, 0), IF(_xlpm.type="Percentage", Table5[[#This Row],[Order Amount]]*(_xlpm.val/100), _xlpm.val) ) ) -> 16 | AA70: =Table5[[#This Row],[Order Amount]]+Table5[[#This Row],[Delivery Fee]]-Table5[[#This Row],[Discount Amount]] -> 194 | AB70: =_xlfn.XLOOKUP(Table5[[#This Row],[RiderID]], Rider_Directory!$F$2:$F$26, Rider_Directory!$B$2:$B$26) -> Kathmandu | AC70: {=_xlfn.IFS(Table5[[#This Row],[Final Amount]]<500, "Small", Table5[[#This Row],[Final Amount]]<=1000, "Medium", Table5[[#This Row],[Final Amount]]>1000, "Large")} -> Small | AD70: =_xlfn.LET(_xlpm.expiry,_xlfn.XLOOKUP(Table5[[#This Row],[PromoCode]],Promo_Codes!$A$2:$A$9,Promo_Codes!$F$2:$F$9,DATE(2099,1,1)),IF(Table5[[#This Row],[OrderDate]]>_xlpm.expiry,"Expired Code Used","Valid")) -> Valid
A71: ORD-1069 | B71: 45928 | C71: Sushmita Acharya | D71: 9883-478878 | E71: 45928 | F71: =IF(B71-E71<=2,"New","Returning") -> New | G71: Kathmandu | H71: Cafe Cup | I71: Beverages | J71: Black Coffee | K71: 3 | L71: R-102 | M71: Khalti | N71: DASHAIN10 | O71: Delivered | P71: =IF(O71=""," NEED REVIEW","") | Q71: 4 | R71: 29 | T71: =_xlfn.CONCAT(Table5[[#This Row],[OrderID]]," | ",Table5[[#This Row],[City]]," | ",Table5[[#This Row],[ItemName]]) -> ORD-1069 | Kathmandu | Black Coffee | U71: =UPPER(Table5[[#This Row],[City]]) -> KATHMANDU | V71: =LOWER(Table5[[#This Row],[PaymentMethod]]) -> khalti | W71: {=_xlfn.XLOOKUP(TRIM(Table5[[#This Row],[ItemName]]), TRIM(Menu_Price_List_tbl[ItemName]),Menu_Price_List_tbl[UnitPrice_NPR])} -> 90 | X71: =W71*K71 -> 270 | Y71: =_xlfn.XLOOKUP(Table5[[#This Row],[City]],City_Delivery_Fee_tbl[City],City_Delivery_Fee_tbl[BaseDeliveryFee_NPR]) -> 50 | Z71: =IF(ISBLANK(Table5[[#This Row],[PromoCode]]), 0, _xlfn.LET( _xlpm.type, _xlfn.XLOOKUP(Table5[[#This Row],[PromoCode]], Promo_Codes!$A$2:$A$9, Promo_Codes!$C$2:$C$9, "Flat"), _xlpm.val, _xlfn.XLOOKUP(Table5[[#This Row],[PromoCode]], Promo_Codes!$A$2:$A$9, Promo_Codes!$D$2:$D$9, 0), IF(_xlpm.type="Percentage", Table5[[#This Row],[Order Amount]]*(_xlpm.val/100), _xlpm.val) ) ) -> 27 | AA71: =Table5[[#This Row],[Order Amount]]+Table5[[#This Row],[Delivery Fee]]-Table5[[#This Row],[Discount Amount]] -> 293 | AB71: =_xlfn.XLOOKUP(Table5[[#This Row],[RiderID]], Rider_Directory!$F$2:$F$26, Rider_Directory!$B$2:$B$26) -> Kathmandu | AC71: {=_xlfn.IFS(Table5[[#This Row],[Final Amount]]<500, "Small", Table5[[#This Row],[Final Amount]]<=1000, "Medium", Table5[[#This Row],[Final Amount]]>1000, "Large")} -> Small | AD71: =_xlfn.LET(_xlpm.expiry,_xlfn.XLOOKUP(Table5[[#This Row],[PromoCode]],Promo_Codes!$A$2:$A$9,Promo_Codes!$F$2:$F$9,DATE(2099,1,1)),IF(Table5[[#This Row],[OrderDate]]>_xlpm.expiry,"Expired Code Used","Valid")) -> Valid
A72: ORD-1070 | B72: 45928 | C72: Sujan Acharya | D72: 9825-449920 | E72: 45927 | F72: =IF(B72-E72<=2,"New","Returning") -> New | G72: Kathmandu | H72: Yeti Newari Bhoj | I72: Newari Khana | J72: Choila (Buff) | K72: 1 | L72: R-105 | M72: Cash on Delivery | O72: Delivered | P72: =IF(O72=""," NEED REVIEW","") | Q72: 4 | R72: 45 | S72: best momo in town | T72: =_xlfn.CONCAT(Table5[[#This Row],[OrderID]]," | ",Table5[[#This Row],[City]]," | ",Table5[[#This Row],[ItemName]]) -> ORD-1070 | Kathmandu | Choila (Buff) | U72: =UPPER(Table5[[#This Row],[City]]) -> KATHMANDU | V72: =LOWER(Table5[[#This Row],[PaymentMethod]]) -> cash on delivery | W72: {=_xlfn.XLOOKUP(TRIM(Table5[[#This Row],[ItemName]]), TRIM(Menu_Price_List_tbl[ItemName]),Menu_Price_List_tbl[UnitPrice_NPR])} -> 320 | X72: =W72*K72 -> 320 | Y72: =_xlfn.XLOOKUP(Table5[[#This Row],[City]],City_Delivery_Fee_tbl[City],City_Delivery_Fee_tbl[BaseDeliveryFee_NPR]) -> 50 | Z72: =IF(ISBLANK(Table5[[#This Row],[PromoCode]]), 0, _xlfn.LET( _xlpm.type, _xlfn.XLOOKUP(Table5[[#This Row],[PromoCode]], Promo_Codes!$A$2:$A$9, Promo_Codes!$C$2:$C$9, "Flat"), _xlpm.val, _xlfn.XLOOKUP(Table5[[#This Row],[PromoCode]], Promo_Codes!$A$2:$A$9, Promo_Codes!$D$2:$D$9, 0), IF(_xlpm.type="Percentage", Table5[[#This Row],[Order Amount]]*(_xlpm.val/100), _xlpm.val) ) ) -> 0 | AA72: =Table5[[#This Row],[Order Amount]]+Table5[[#This Row],[Delivery Fee]]-Table5[[#This Row],[Discount Amount]] -> 370 | AB72: =_xlfn.XLOOKUP(Table5[[#This Row],[RiderID]], Rider_Directory!$F$2:$F$26, Rider_Directory!$B$2:$B$26) -> Kathmandu | AC72: {=_xlfn.IFS(Table5[[#This Row],[Final Amount]]<500, "Small", Table5[[#This Row],[Final Amount]]<=1000, "Medium", Table5[[#This Row],[Final Amount]]>1000, "Large")} -> Small | AD72: =_xlfn.LET(_xlpm.expiry,_xlfn.XLOOKUP(Table5[[#This Row],[PromoCode]],Promo_Codes!$A$2:$A$9,Promo_Codes!$F$2:$F$9,DATE(2099,1,1)),IF(Table5[[#This Row],[OrderDate]]>_xlpm.expiry,"Expired Code Used","Valid")) -> Valid
A73: ORD-1071 | B73: 45928 | C73: Ramesh Poudel | D73: 9807-924402 | E73: 45916 | F73: =IF(B73-E73<=2,"New","Returning") -> Returning | G73: Bhaktapur | H73: Yeti Newari Bhoj | I73: Newari Khana | J73: Bara | K73: 2 | L73: R-111 | M73: Khalti | O73: Cancelled | P73: =IF(O73=""," NEED REVIEW","") | R73: 40 | S73: okay experience | T73: =_xlfn.CONCAT(Table5[[#This Row],[OrderID]]," | ",Table5[[#This Row],[City]]," | ",Table5[[#This Row],[ItemName]]) -> ORD-1071 | Bhaktapur | Bara | U73: =UPPER(Table5[[#This Row],[City]]) -> BHAKTAPUR | V73: =LOWER(Table5[[#This Row],[PaymentMethod]]) -> khalti | W73: {=_xlfn.XLOOKUP(TRIM(Table5[[#This Row],[ItemName]]), TRIM(Menu_Price_List_tbl[ItemName]),Menu_Price_List_tbl[UnitPrice_NPR])} -> 160 | X73: =W73*K73 -> 320 | Y73: =_xlfn.XLOOKUP(Table5[[#This Row],[City]],City_Delivery_Fee_tbl[City],City_Delivery_Fee_tbl[BaseDeliveryFee_NPR]) -> 55 | Z73: =IF(ISBLANK(Table5[[#This Row],[PromoCode]]), 0, _xlfn.LET( _xlpm.type, _xlfn.XLOOKUP(Table5[[#This Row],[PromoCode]], Promo_Codes!$A$2:$A$9, Promo_Codes!$C$2:$C$9, "Flat"), _xlpm.val, _xlfn.XLOOKUP(Table5[[#This Row],[PromoCode]], Promo_Codes!$A$2:$A$9, Promo_Codes!$D$2:$D$9, 0), IF(_xlpm.type="Percentage", Table5[[#This Row],[Order Amount]]*(_xlpm.val/100), _xlpm.val) ) ) -> 0 | AA73: =Table5[[#This Row],[Order Amount]]+Table5[[#This Row],[Delivery Fee]]-Table5[[#This Row],[Discount Amount]] -> 375 | AB73: =_xlfn.XLOOKUP(Table5[[#This Row],[RiderID]], Rider_Directory!$F$2:$F$26, Rider_Directory!$B$2:$B$26) -> Bhaktapur | AC73: {=_xlfn.IFS(Table5[[#This Row],[Final Amount]]<500, "Small", Table5[[#This Row],[Final Amount]]<=1000, "Medium", Table5[[#This Row],[Final Amount]]>1000, "Large")} -> Small | AD73: =_xlfn.LET(_xlpm.expiry,_xlfn.XLOOKUP(Table5[[#This Row],[PromoCode]],Promo_Codes!$A$2:$A$9,Promo_Codes!$F$2:$F$9,DATE(2099,1,1)),IF(Table5[[#This Row],[OrderDate]]>_xlpm.expiry,"Expired Code Used","Valid")) -> Valid
A74: ORD-1072 | B74: 45962 | C74: Deepak Chhetri | D74: 9818-746331 | E74: 45928 | F74: =IF(B74-E74<=2,"New","Returning") -> Returning | G74: Butwal | H74: Yeti Newari Bhoj | I74: Newari Khana | J74: Bara | K74: 1 | L74: R-120 | M74: Khalti | N74: DASHAIN10 | O74: Delivered | P74: =IF(O74=""," NEED REVIEW","") | Q74: 4 | R74: 44 | S74: quality was great as always | T74: =_xlfn.CONCAT(Table5[[#This Row],[OrderID]]," | ",Table5[[#This Row],[City]]," | ",Table5[[#This Row],[ItemName]]) -> ORD-1072 | Butwal | Bara | U74: =UPPER(Table5[[#This Row],[City]]) -> BUTWAL | V74: =LOWER(Table5[[#This Row],[PaymentMethod]]) -> khalti | W74: {=_xlfn.XLOOKUP(TRIM(Table5[[#This Row],[ItemName]]), TRIM(Menu_Price_List_tbl[ItemName]),Menu_Price_List_tbl[UnitPrice_NPR])} -> 160 | X74: =W74*K74 -> 160 | Y74: =_xlfn.XLOOKUP(Table5[[#This Row],[City]],City_Delivery_Fee_tbl[City],City_Delivery_Fee_tbl[BaseDeliveryFee_NPR]) -> 85 | Z74: =IF(ISBLANK(Table5[[#This Row],[PromoCode]]), 0, _xlfn.LET( _xlpm.type, _xlfn.XLOOKUP(Table5[[#This Row],[PromoCode]], Promo_Codes!$A$2:$A$9, Promo_Codes!$C$2:$C$9, "Flat"), _xlpm.val, _xlfn.XLOOKUP(Table5[[#This Row],[PromoCode]], Promo_Codes!$A$2:$A$9, Promo_Codes!$D$2:$D$9, 0), IF(_xlpm.type="Percentage", Table5[[#This Row],[Order Amount]]*(_xlpm.val/100), _xlpm.val) ) ) -> 16 | AA74: =Table5[[#This Row],[Order Amount]]+Table5[[#This Row],[Delivery Fee]]-Table5[[#This Row],[Discount Amount]] -> 229 | AB74: =_xlfn.XLOOKUP(Table5[[#This Row],[RiderID]], Rider_Directory!$F$2:$F$26, Rider_Directory!$B$2:$B$26) -> Butwal | AC74: {=_xlfn.IFS(Table5[[#This Row],[Final Amount]]<500, "Small", Table5[[#This Row],[Final Amount]]<=1000, "Medium", Table5[[#This Row],[Final Amount]]>1000, "Large")} -> Small | AD74: =_xlfn.LET(_xlpm.expiry,_xlfn.XLOOKUP(Table5[[#This Row],[PromoCode]],Promo_Codes!$A$2:$A$9,Promo_Codes!$F$2:$F$9,DATE(2099,1,1)),IF(Table5[[#This Row],[OrderDate]]>_xlpm.expiry,"Expired Code Used","Valid")) -> Expired Code Used
A75: ORD-1073 | B75: 45930 | C75: Gopal Shakya | D75: 9821-993518 | E75: 45930 | F75: =IF(B75-E75<=2,"New","Returning") -> New | G75: Lalitpur | H75: Fast Bites | I75: Fast Food | J75: Chicken Chowmein | K75: 1 | L75: R-107 | M75: eSewa | N75: DASHAIN10 | O75: Delivered | P75: =IF(O75=""," NEED REVIEW","") | Q75: 5 | R75: 30 | T75: =_xlfn.CONCAT(Table5[[#This Row],[OrderID]]," | ",Table5[[#This Row],[City]]," | ",Table5[[#This Row],[ItemName]]) -> ORD-1073 | Lalitpur | Chicken Chowmein | U75: =UPPER(Table5[[#This Row],[City]]) -> LALITPUR | V75: =LOWER(Table5[[#This Row],[PaymentMethod]]) -> esewa | W75: {=_xlfn.XLOOKUP(TRIM(Table5[[#This Row],[ItemName]]), TRIM(Menu_Price_List_tbl[ItemName]),Menu_Price_List_tbl[UnitPrice_NPR])} -> 250 | X75: =W75*K75 -> 250 | Y75: =_xlfn.XLOOKUP(Table5[[#This Row],[City]],City_Delivery_Fee_tbl[City],City_Delivery_Fee_tbl[BaseDeliveryFee_NPR]) -> 50 | Z75: =IF(ISBLANK(Table5[[#This Row],[PromoCode]]), 0, _xlfn.LET( _xlpm.type, _xlfn.XLOOKUP(Table5[[#This Row],[PromoCode]], Promo_Codes!$A$2:$A$9, Promo_Codes!$C$2:$C$9, "Flat"), _xlpm.val, _xlfn.XLOOKUP(Table5[[#This Row],[PromoCode]], Promo_Codes!$A$2:$A$9, Promo_Codes!$D$2:$D$9, 0), IF(_xlpm.type="Percentage", Table5[[#This Row],[Order Amount]]*(_xlpm.val/100), _xlpm.val) ) ) -> 25 | AA75: =Table5[[#This Row],[Order Amount]]+Table5[[#This Row],[Delivery Fee]]-Table5[[#This Row],[Discount Amount]] -> 275 | AB75: =_xlfn.XLOOKUP(Table5[[#This Row],[RiderID]], Rider_Directory!$F$2:$F$26, Rider_Directory!$B$2:$B$26) -> Lalitpur | AC75: {=_xlfn.IFS(Table5[[#This Row],[Final Amount]]<500, "Small", Table5[[#This Row],[Final Amount]]<=1000, "Medium", Table5[[#This Row],[Final Amount]]>1000, "Large")} -> Small | AD75: =_xlfn.LET(_xlpm.expiry,_xlfn.XLOOKUP(Table5[[#This Row],[PromoCode]],Promo_Codes!$A$2:$A$9,Promo_Codes!$F$2:$F$9,DATE(2099,1,1)),IF(Table5[[#This Row],[OrderDate]]>_xlpm.expiry,"Expired Code Used","Valid")) -> Valid
A76: ORD-1074 | B76: 45931 | C76: Rajan Basnet | D76: 9897-465075 | E76: 45911 | F76: =IF(B76-E76<=2,"New","Returning") -> Returning | G76: Biratnagar | H76: Bhattarai Momo Center | I76: Momo | J76: chicken momo (fried) | K76: 2 | L76: R-118 | M76: Cash on Delivery | N76: FIRSTORDER | O76: Delivered | P76: =IF(O76=""," NEED REVIEW","") | Q76: 4 | R76: 36 | S76: packaging was nice | T76: =_xlfn.CONCAT(Table5[[#This Row],[OrderID]]," | ",Table5[[#This Row],[City]]," | ",Table5[[#This Row],[ItemName]]) -> ORD-1074 | Biratnagar | chicken momo (fried) | U76: =UPPER(Table5[[#This Row],[City]]) -> BIRATNAGAR | V76: =LOWER(Table5[[#This Row],[PaymentMethod]]) -> cash on delivery | W76: {=_xlfn.XLOOKUP(TRIM(Table5[[#This Row],[ItemName]]), TRIM(Menu_Price_List_tbl[ItemName]),Menu_Price_List_tbl[UnitPrice_NPR])} -> 210 | X76: =W76*K76 -> 420 | Y76: =_xlfn.XLOOKUP(Table5[[#This Row],[City]],City_Delivery_Fee_tbl[City],City_Delivery_Fee_tbl[BaseDeliveryFee_NPR]) -> 90 | Z76: =IF(ISBLANK(Table5[[#This Row],[PromoCode]]), 0, _xlfn.LET( _xlpm.type, _xlfn.XLOOKUP(Table5[[#This Row],[PromoCode]], Promo_Codes!$A$2:$A$9, Promo_Codes!$C$2:$C$9, "Flat"), _xlpm.val, _xlfn.XLOOKUP(Table5[[#This Row],[PromoCode]], Promo_Codes!$A$2:$A$9, Promo_Codes!$D$2:$D$9, 0), IF(_xlpm.type="Percentage", Table5[[#This Row],[Order Amount]]*(_xlpm.val/100), _xlpm.val) ) ) -> 100 | AA76: =Table5[[#This Row],[Order Amount]]+Table5[[#This Row],[Delivery Fee]]-Table5[[#This Row],[Discount Amount]] -> 410 | AB76: =_xlfn.XLOOKUP(Table5[[#This Row],[RiderID]], Rider_Directory!$F$2:$F$26, Rider_Directory!$B$2:$B$26) -> Biratnagar | AC76: {=_xlfn.IFS(Table5[[#This Row],[Final Amount]]<500, "Small", Table5[[#This Row],[Final Amount]]<=1000, "Medium", Table5[[#This Row],[Final Amount]]>1000, "Large")} -> Small | AD76: =_xlfn.LET(_xlpm.expiry,_xlfn.XLOOKUP(Table5[[#This Row],[PromoCode]],Promo_Codes!$A$2:$A$9,Promo_Codes!$F$2:$F$9,DATE(2099,1,1)),IF(Table5[[#This Row],[OrderDate]]>_xlpm.expiry,"Expired Code Used","Valid")) -> Valid
A77: ORD-1075 | B77: 45931 | C77: Sita Maharjan | D77: 9880-021581 | E77: 45916 | F77: =IF(B77-E77<=2,"New","Returning") -> Returning | G77: Lalitpur | H77: Wok Point | I77: Chinese | J77: CHICKEN MANCHURIAN | K77: 2 | L77: R-108 | M77: eSewa | N77: DASHAIN10 | O77: Delivered | P77: =IF(O77=""," NEED REVIEW","") | Q77: 3 | R77: 25 | S77: rider could not find my house | T77: =_xlfn.CONCAT(Table5[[#This Row],[OrderID]]," | ",Table5[[#This Row],[City]]," | ",Table5[[#This Row],[ItemName]]) -> ORD-1075 | Lalitpur | CHICKEN MANCHURIAN | U77: =UPPER(Table5[[#This Row],[City]]) -> LALITPUR | V77: =LOWER(Table5[[#This Row],[PaymentMethod]]) -> esewa | W77: {=_xlfn.XLOOKUP(TRIM(Table5[[#This Row],[ItemName]]), TRIM(Menu_Price_List_tbl[ItemName]),Menu_Price_List_tbl[UnitPrice_NPR])} -> 320 | X77: =W77*K77 -> 640 | Y77: =_xlfn.XLOOKUP(Table5[[#This Row],[City]],City_Delivery_Fee_tbl[City],City_Delivery_Fee_tbl[BaseDeliveryFee_NPR]) -> 50 | Z77: =IF(ISBLANK(Table5[[#This Row],[PromoCode]]), 0, _xlfn.LET( _xlpm.type, _xlfn.XLOOKUP(Table5[[#This Row],[PromoCode]], Promo_Codes!$A$2:$A$9, Promo_Codes!$C$2:$C$9, "Flat"), _xlpm.val, _xlfn.XLOOKUP(Table5[[#This Row],[PromoCode]], Promo_Codes!$A$2:$A$9, Promo_Codes!$D$2:$D$9, 0), IF(_xlpm.type="Percentage", Table5[[#This Row],[Order Amount]]*(_xlpm.val/100), _xlpm.val) ) ) -> 64 | AA77: =Table5[[#This Row],[Order Amount]]+Table5[[#This Row],[Delivery Fee]]-Table5[[#This Row],[Discount Amount]] -> 626 | AB77: =_xlfn.XLOOKUP(Table5[[#This Row],[RiderID]], Rider_Directory!$F$2:$F$26, Rider_Directory!$B$2:$B$26) -> Lalitpur | AC77: {=_xlfn.IFS(Table5[[#This Row],[Final Amount]]<500, "Small", Table5[[#This Row],[Final Amount]]<=1000, "Medium", Table5[[#This Row],[Final Amount]]>1000, "Large")} -> Medium | AD77: =_xlfn.LET(_xlpm.expiry,_xlfn.XLOOKUP(Table5[[#This Row],[PromoCode]],Promo_Codes!$A$2:$A$9,Promo_Codes!$F$2:$F$9,DATE(2099,1,1)),IF(Table5[[#This Row],[OrderDate]]>_xlpm.expiry,"Expired Code Used","Valid")) -> Valid
A78: ORD-1076 | B78: 45933 | C78: Kiran Bhattarai | D78: 9851-732904 | E78: 45886 | F78: =IF(B78-E78<=2,"New","Returning") -> Returning | G78: Dharan | H78: Sekuwa Point | I78: Sekuwa | J78: Chicken Sekuwa | K78: 3 | L78: R-124 | M78: eSewa | N78: DASHAIN10 | O78: Delivered | P78: =IF(O78=""," NEED REVIEW","") | Q78: 4 | R78: 56 | T78: =_xlfn.CONCAT(Table5[[#This Row],[OrderID]]," | ",Table5[[#This Row],[City]]," | ",Table5[[#This Row],[ItemName]]) -> ORD-1076 | Dharan | Chicken Sekuwa | U78: =UPPER(Table5[[#This Row],[City]]) -> DHARAN | V78: =LOWER(Table5[[#This Row],[PaymentMethod]]) -> esewa | W78: {=_xlfn.XLOOKUP(TRIM(Table5[[#This Row],[ItemName]]), TRIM(Menu_Price_List_tbl[ItemName]),Menu_Price_List_tbl[UnitPrice_NPR])} -> 420 | X78: =W78*K78 -> 1260 | Y78: =_xlfn.XLOOKUP(Table5[[#This Row],[City]],City_Delivery_Fee_tbl[City],City_Delivery_Fee_tbl[BaseDeliveryFee_NPR]) -> 95 | Z78: =IF(ISBLANK(Table5[[#This Row],[PromoCode]]), 0, _xlfn.LET( _xlpm.type, _xlfn.XLOOKUP(Table5[[#This Row],[PromoCode]], Promo_Codes!$A$2:$A$9, Promo_Codes!$C$2:$C$9, "Flat"), _xlpm.val, _xlfn.XLOOKUP(Table5[[#This Row],[PromoCode]], Promo_Codes!$A$2:$A$9, Promo_Codes!$D$2:$D$9, 0), IF(_xlpm.type="Percentage", Table5[[#This Row],[Order Amount]]*(_xlpm.val/100), _xlpm.val) ) ) -> 126 | AA78: =Table5[[#This Row],[Order Amount]]+Table5[[#This Row],[Delivery Fee]]-Table5[[#This Row],[Discount Amount]] -> 1229 | AB78: =_xlfn.XLOOKUP(Table5[[#This Row],[RiderID]], Rider_Directory!$F$2:$F$26, Rider_Directory!$B$2:$B$26) -> Dharan | AC78: {=_xlfn.IFS(Table5[[#This Row],[Final Amount]]<500, "Small", Table5[[#This Row],[Final Amount]]<=1000, "Medium", Table5[[#This Row],[Final Amount]]>1000, "Large")} -> Large | AD78: =_xlfn.LET(_xlpm.expiry,_xlfn.XLOOKUP(Table5[[#This Row],[PromoCode]],Promo_Codes!$A$2:$A$9,Promo_Codes!$F$2:$F$9,DATE(2099,1,1)),IF(Table5[[#This Row],[OrderDate]]>_xlpm.expiry,"Expired Code Used","Valid")) -> Valid
A79: ORD-1077 | B79: 45933 | C79: Rajan Poudel | D79: 9808-246281 | E79: 45909 | F79: =IF(B79-E79<=2,"New","Returning") -> Returning | G79: Kathmandu | H79: Himalayan Bakers | I79: Bakery | J79: Sel Roti (4 pcs) | K79: 1 | L79: R-102 | M79: Cash on Delivery | N79: DASHAIN10 | O79: Delivered | P79: =IF(O79=""," NEED REVIEW","") | Q79: 4 | R79: 27 | T79: =_xlfn.CONCAT(Table5[[#This Row],[OrderID]]," | ",Table5[[#This Row],[City]]," | ",Table5[[#This Row],[ItemName]]) -> ORD-1077 | Kathmandu | Sel Roti (4 pcs) | U79: =UPPER(Table5[[#This Row],[City]]) -> KATHMANDU | V79: =LOWER(Table5[[#This Row],[PaymentMethod]]) -> cash on delivery | W79: {=_xlfn.XLOOKUP(TRIM(Table5[[#This Row],[ItemName]]), TRIM(Menu_Price_List_tbl[ItemName]),Menu_Price_List_tbl[UnitPrice_NPR])} -> 140 | X79: =W79*K79 -> 140 | Y79: =_xlfn.XLOOKUP(Table5[[#This Row],[City]],City_Delivery_Fee_tbl[City],City_Delivery_Fee_tbl[BaseDeliveryFee_NPR]) -> 50 | Z79: =IF(ISBLANK(Table5[[#This Row],[PromoCode]]), 0, _xlfn.LET( _xlpm.type, _xlfn.XLOOKUP(Table5[[#This Row],[PromoCode]], Promo_Codes!$A$2:$A$9, Promo_Codes!$C$2:$C$9, "Flat"), _xlpm.val, _xlfn.XLOOKUP(Table5[[#This Row],[PromoCode]], Promo_Codes!$A$2:$A$9, Promo_Codes!$D$2:$D$9, 0), IF(_xlpm.type="Percentage", Table5[[#This Row],[Order Amount]]*(_xlpm.val/100), _xlpm.val) ) ) -> 14 | AA79: =Table5[[#This Row],[Order Amount]]+Table5[[#This Row],[Delivery Fee]]-Table5[[#This Row],[Discount Amount]] -> 176 | AB79: =_xlfn.XLOOKUP(Table5[[#This Row],[RiderID]], Rider_Directory!$F$2:$F$26, Rider_Directory!$B$2:$B$26) -> Kathmandu | AC79: {=_xlfn.IFS(Table5[[#This Row],[Final Amount]]<500, "Small", Table5[[#This Row],[Final Amount]]<=1000, "Medium", Table5[[#This Row],[Final Amount]]>1000, "Large")} -> Small | AD79: =_xlfn.LET(_xlpm.expiry,_xlfn.XLOOKUP(Table5[[#This Row],[PromoCode]],Promo_Codes!$A$2:$A$9,Promo_Codes!$F$2:$F$9,DATE(2099,1,1)),IF(Table5[[#This Row],[OrderDate]]>_xlpm.expiry,"Expired Code Used","Valid")) -> Valid
A80: ORD-1078 | B80: 45937 | C80: Anish Shakya | D80: 9836-546107 | E80: 45926 | F80: =IF(B80-E80<=2,"New","Returning") -> Returning | G80: Pokhara | H80: Yeti Newari Bhoj | I80: Newari Khana | J80: Choila (Buff) | K80: 1 | L80: R-113 | M80: IME Pay | N80: DASHAIN10 | O80: Returned | P80: =IF(O80=""," NEED REVIEW","") | R80: 51 | T80: =_xlfn.CONCAT(Table5[[#This Row],[OrderID]]," | ",Table5[[#This Row],[City]]," | ",Table5[[#This Row],[ItemName]]) -> ORD-1078 | Pokhara | Choila (Buff) | U80: =UPPER(Table5[[#This Row],[City]]) -> POKHARA | V80: =LOWER(Table5[[#This Row],[PaymentMethod]]) -> ime pay | W80: {=_xlfn.XLOOKUP(TRIM(Table5[[#This Row],[ItemName]]), TRIM(Menu_Price_List_tbl[ItemName]),Menu_Price_List_tbl[UnitPrice_NPR])} -> 320 | X80: =W80*K80 -> 320 | Y80: =_xlfn.XLOOKUP(Table5[[#This Row],[City]],City_Delivery_Fee_tbl[City],City_Delivery_Fee_tbl[BaseDeliveryFee_NPR]) -> 70 | Z80: =IF(ISBLANK(Table5[[#This Row],[PromoCode]]), 0, _xlfn.LET( _xlpm.type, _xlfn.XLOOKUP(Table5[[#This Row],[PromoCode]], Promo_Codes!$A$2:$A$9, Promo_Codes!$C$2:$C$9, "Flat"), _xlpm.val, _xlfn.XLOOKUP(Table5[[#This Row],[PromoCode]], Promo_Codes!$A$2:$A$9, Promo_Codes!$D$2:$D$9, 0), IF(_xlpm.type="Percentage", Table5[[#This Row],[Order Amount]]*(_xlpm.val/100), _xlpm.val) ) ) -> 32 | AA80: =Table5[[#This Row],[Order Amount]]+Table5[[#This Row],[Delivery Fee]]-Table5[[#This Row],[Discount Amount]] -> 358 | AB80: =_xlfn.XLOOKUP(Table5[[#This Row],[RiderID]], Rider_Directory!$F$2:$F$26, Rider_Directory!$B$2:$B$26) -> Pokhara | AC80: {=_xlfn.IFS(Table5[[#This Row],[Final Amount]]<500, "Small", Table5[[#This Row],[Final Amount]]<=1000, "Medium", Table5[[#This Row],[Final Amount]]>1000, "Large")} -> Small | AD80: =_xlfn.LET(_xlpm.expiry,_xlfn.XLOOKUP(Table5[[#This Row],[PromoCode]],Promo_Codes!$A$2:$A$9,Promo_Codes!$F$2:$F$9,DATE(2099,1,1)),IF(Table5[[#This Row],[OrderDate]]>_xlpm.expiry,"Expired Code Used","Valid")) -> Valid
A81: ORD-1079 | B81: 45939 | C81: Ramesh Chhetri | D81: 9876-174093 | E81: 45937 | F81: =IF(B81-E81<=2,"New","Returning") -> New | G81: Chitwan | H81: Quick Snacks Corner | I81: Fast Food | J81: Veg Burger | K81: 3 | L81: R-121 | M81: Khalti | N81: DASHAIN10 | O81: Delivered | P81: =IF(O81=""," NEED REVIEW","") | Q81: 3 | R81: 52 | T81: =_xlfn.CONCAT(Table5[[#This Row],[OrderID]]," | ",Table5[[#This Row],[City]]," | ",Table5[[#This Row],[ItemName]]) -> ORD-1079 | Chitwan | Veg Burger | U81: =UPPER(Table5[[#This Row],[City]]) -> CHITWAN | V81: =LOWER(Table5[[#This Row],[PaymentMethod]]) -> khalti | W81: {=_xlfn.XLOOKUP(TRIM(Table5[[#This Row],[ItemName]]), TRIM(Menu_Price_List_tbl[ItemName]),Menu_Price_List_tbl[UnitPrice_NPR])} -> 220 | X81: =W81*K81 -> 660 | Y81: =_xlfn.XLOOKUP(Table5[[#This Row],[City]],City_Delivery_Fee_tbl[City],City_Delivery_Fee_tbl[BaseDeliveryFee_NPR]) -> 80 | Z81: =IF(ISBLANK(Table5[[#This Row],[PromoCode]]), 0, _xlfn.LET( _xlpm.type, _xlfn.XLOOKUP(Table5[[#This Row],[PromoCode]], Promo_Codes!$A$2:$A$9, Promo_Codes!$C$2:$C$9, "Flat"), _xlpm.val, _xlfn.XLOOKUP(Table5[[#This Row],[PromoCode]], Promo_Codes!$A$2:$A$9, Promo_Codes!$D$2:$D$9, 0), IF(_xlpm.type="Percentage", Table5[[#This Row],[Order Amount]]*(_xlpm.val/100), _xlpm.val) ) ) -> 66 | AA81: =Table5[[#This Row],[Order Amount]]+Table5[[#This Row],[Delivery Fee]]-Table5[[#This Row],[Discount Amount]] -> 674 | AB81: =_xlfn.XLOOKUP(Table5[[#This Row],[RiderID]], Rider_Directory!$F$2:$F$26, Rider_Directory!$B$2:$B$26) -> Chitwan | AC81: {=_xlfn.IFS(Table5[[#This Row],[Final Amount]]<500, "Small", Table5[[#This Row],[Final Amount]]<=1000, "Medium", Table5[[#This Row],[Final Amount]]>1000, "Large")} -> Medium | AD81: =_xlfn.LET(_xlpm.expiry,_xlfn.XLOOKUP(Table5[[#This Row],[PromoCode]],Promo_Codes!$A$2:$A$9,Promo_Codes!$F$2:$F$9,DATE(2099,1,1)),IF(Table5[[#This Row],[OrderDate]]>_xlpm.expiry,"Expired Code Used","Valid")) -> Valid
A82: ORD-1080 | B82: 45942 | C82: Sita Maharjan | D82: 9880-021581 | E82: 45916 | F82: =IF(B82-E82<=2,"New","Returning") -> Returning | G82: Dharan | H82: Himalayan Thakali Kitchen | I82: Thakali Set | J82: Veg Thakali Set | K82: 1 | L82: R-125 | M82: Cash on Delivery | N82: FIRSTORDER | O82: Returned | P82: =IF(O82=""," NEED REVIEW","") | R82: 53 | S82: okay experience | T82: =_xlfn.CONCAT(Table5[[#This Row],[OrderID]]," | ",Table5[[#This Row],[City]]," | ",Table5[[#This Row],[ItemName]]) -> ORD-1080 | Dharan | Veg Thakali Set | U82: =UPPER(Table5[[#This Row],[City]]) -> DHARAN | V82: =LOWER(Table5[[#This Row],[PaymentMethod]]) -> cash on delivery | W82: {=_xlfn.XLOOKUP(TRIM(Table5[[#This Row],[ItemName]]), TRIM(Menu_Price_List_tbl[ItemName]),Menu_Price_List_tbl[UnitPrice_NPR])} -> 380 | X82: =W82*K82 -> 380 | Y82: =_xlfn.XLOOKUP(Table5[[#This Row],[City]],City_Delivery_Fee_tbl[City],City_Delivery_Fee_tbl[BaseDeliveryFee_NPR]) -> 95 | Z82: =IF(ISBLANK(Table5[[#This Row],[PromoCode]]), 0, _xlfn.LET( _xlpm.type, _xlfn.XLOOKUP(Table5[[#This Row],[PromoCode]], Promo_Codes!$A$2:$A$9, Promo_Codes!$C$2:$C$9, "Flat"), _xlpm.val, _xlfn.XLOOKUP(Table5[[#This Row],[PromoCode]], Promo_Codes!$A$2:$A$9, Promo_Codes!$D$2:$D$9, 0), IF(_xlpm.type="Percentage", Table5[[#This Row],[Order Amount]]*(_xlpm.val/100), _xlpm.val) ) ) -> 100 | AA82: =Table5[[#This Row],[Order Amount]]+Table5[[#This Row],[Delivery Fee]]-Table5[[#This Row],[Discount Amount]] -> 375 | AB82: =_xlfn.XLOOKUP(Table5[[#This Row],[RiderID]], Rider_Directory!$F$2:$F$26, Rider_Directory!$B$2:$B$26) -> Dharan | AC82: {=_xlfn.IFS(Table5[[#This Row],[Final Amount]]<500, "Small", Table5[[#This Row],[Final Amount]]<=1000, "Medium", Table5[[#This Row],[Final Amount]]>1000, "Large")} -> Small | AD82: =_xlfn.LET(_xlpm.expiry,_xlfn.XLOOKUP(Table5[[#This Row],[PromoCode]],Promo_Codes!$A$2:$A$9,Promo_Codes!$F$2:$F$9,DATE(2099,1,1)),IF(Table5[[#This Row],[OrderDate]]>_xlpm.expiry,"Expired Code Used","Valid")) -> Valid
A83: ORD-1081 | B83: 45942 | C83: Sarita Karki | D83: 9889-869284 | E83: 45940 | F83: =IF(B83-E83<=2,"New","Returning") -> New | G83: Lalitpur | H83: Newa Kitchen | I83: Newari Khana | J83: Bara | K83: 4 | L83: R-108 | M83: Khalti | N83: DASHAIN10 | O83: Delivered | P83: =IF(O83=""," NEED REVIEW","") | Q83: 4 | R83: 33 | S83: packaging was nice | T83: =_xlfn.CONCAT(Table5[[#This Row],[OrderID]]," | ",Table5[[#This Row],[City]]," | ",Table5[[#This Row],[ItemName]]) -> ORD-1081 | Lalitpur | Bara | U83: =UPPER(Table5[[#This Row],[City]]) -> LALITPUR | V83: =LOWER(Table5[[#This Row],[PaymentMethod]]) -> khalti | W83: {=_xlfn.XLOOKUP(TRIM(Table5[[#This Row],[ItemName]]), TRIM(Menu_Price_List_tbl[ItemName]),Menu_Price_List_tbl[UnitPrice_NPR])} -> 160 | X83: =W83*K83 -> 640 | Y83: =_xlfn.XLOOKUP(Table5[[#This Row],[City]],City_Delivery_Fee_tbl[City],City_Delivery_Fee_tbl[BaseDeliveryFee_NPR]) -> 50 | Z83: =IF(ISBLANK(Table5[[#This Row],[PromoCode]]), 0, _xlfn.LET( _xlpm.type, _xlfn.XLOOKUP(Table5[[#This Row],[PromoCode]], Promo_Codes!$A$2:$A$9, Promo_Codes!$C$2:$C$9, "Flat"), _xlpm.val, _xlfn.XLOOKUP(Table5[[#This Row],[PromoCode]], Promo_Codes!$A$2:$A$9, Promo_Codes!$D$2:$D$9, 0), IF(_xlpm.type="Percentage", Table5[[#This Row],[Order Amount]]*(_xlpm.val/100), _xlpm.val) ) ) -> 64 | AA83: =Table5[[#This Row],[Order Amount]]+Table5[[#This Row],[Delivery Fee]]-Table5[[#This Row],[Discount Amount]] -> 626 | AB83: =_xlfn.XLOOKUP(Table5[[#This Row],[RiderID]], Rider_Directory!$F$2:$F$26, Rider_Directory!$B$2:$B$26) -> Lalitpur | AC83: {=_xlfn.IFS(Table5[[#This Row],[Final Amount]]<500, "Small", Table5[[#This Row],[Final Amount]]<=1000, "Medium", Table5[[#This Row],[Final Amount]]>1000, "Large")} -> Medium | AD83: =_xlfn.LET(_xlpm.expiry,_xlfn.XLOOKUP(Table5[[#This Row],[PromoCode]],Promo_Codes!$A$2:$A$9,Promo_Codes!$F$2:$F$9,DATE(2099,1,1)),IF(Table5[[#This Row],[OrderDate]]>_xlpm.expiry,"Expired Code Used","Valid")) -> Valid
A84: ORD-1082 | B84: 45944 | C84: Bina Shrestha | D84: 9881-741433 | E84: 45700 | F84: =IF(B84-E84<=2,"New","Returning") -> Returning | G84: Lalitpur | H84: Fast Bites | I84: Fast Food | J84: Chicken Chowmein | K84: 1 | L84: R-107 | M84: Khalti | O84: Delivered | P84: =IF(O84=""," NEED REVIEW","") | Q84: 4 | R84: 33 | T84: =_xlfn.CONCAT(Table5[[#This Row],[OrderID]]," | ",Table5[[#This Row],[City]]," | ",Table5[[#This Row],[ItemName]]) -> ORD-1082 | Lalitpur | Chicken Chowmein | U84: =UPPER(Table5[[#This Row],[City]]) -> LALITPUR | V84: =LOWER(Table5[[#This Row],[PaymentMethod]]) -> khalti | W84: {=_xlfn.XLOOKUP(TRIM(Table5[[#This Row],[ItemName]]), TRIM(Menu_Price_List_tbl[ItemName]),Menu_Price_List_tbl[UnitPrice_NPR])} -> 250 | X84: =W84*K84 -> 250 | Y84: =_xlfn.XLOOKUP(Table5[[#This Row],[City]],City_Delivery_Fee_tbl[City],City_Delivery_Fee_tbl[BaseDeliveryFee_NPR]) -> 50 | Z84: =IF(ISBLANK(Table5[[#This Row],[PromoCode]]), 0, _xlfn.LET( _xlpm.type, _xlfn.XLOOKUP(Table5[[#This Row],[PromoCode]], Promo_Codes!$A$2:$A$9, Promo_Codes!$C$2:$C$9, "Flat"), _xlpm.val, _xlfn.XLOOKUP(Table5[[#This Row],[PromoCode]], Promo_Codes!$A$2:$A$9, Promo_Codes!$D$2:$D$9, 0), IF(_xlpm.type="Percentage", Table5[[#This Row],[Order Amount]]*(_xlpm.val/100), _xlpm.val) ) ) -> 0 | AA84: =Table5[[#This Row],[Order Amount]]+Table5[[#This Row],[Delivery Fee]]-Table5[[#This Row],[Discount Amount]] -> 300 | AB84: =_xlfn.XLOOKUP(Table5[[#This Row],[RiderID]], Rider_Directory!$F$2:$F$26, Rider_Directory!$B$2:$B$26) -> Lalitpur | AC84: {=_xlfn.IFS(Table5[[#This Row],[Final Amount]]<500, "Small", Table5[[#This Row],[Final Amount]]<=1000, "Medium", Table5[[#This Row],[Final Amount]]>1000, "Large")} -> Small | AD84: =_xlfn.LET(_xlpm.expiry,_xlfn.XLOOKUP(Table5[[#This Row],[PromoCode]],Promo_Codes!$A$2:$A$9,Promo_Codes!$F$2:$F$9,DATE(2099,1,1)),IF(Table5[[#This Row],[OrderDate]]>_xlpm.expiry,"Expired Code Used","Valid")) -> Valid
A85: ORD-1083 | B85: 45945 | C85: Anita Adhikari | D85: 9886-205798 | E85: 45944 | F85: =IF(B85-E85<=2,"New","Returning") -> New | G85: Dharan | H85: Kathmandu Momo House | I85: Momo | J85: Buff Momo (Steamed) | K85: 3 | L85: R-125 | M85: Cash on Delivery | N85: DASHAIN10 | O85: Delivered | P85: =IF(O85=""," NEED REVIEW","") | Q85: 3 | R85: 59 | T85: =_xlfn.CONCAT(Table5[[#This Row],[OrderID]]," | ",Table5[[#This Row],[City]]," | ",Table5[[#This Row],[ItemName]]) -> ORD-1083 | Dharan | Buff Momo (Steamed) | U85: =UPPER(Table5[[#This Row],[City]]) -> DHARAN | V85: =LOWER(Table5[[#This Row],[PaymentMethod]]) -> cash on delivery | W85: {=_xlfn.XLOOKUP(TRIM(Table5[[#This Row],[ItemName]]), TRIM(Menu_Price_List_tbl[ItemName]),Menu_Price_List_tbl[UnitPrice_NPR])} -> 170 | X85: =W85*K85 -> 510 | Y85: =_xlfn.XLOOKUP(Table5[[#This Row],[City]],City_Delivery_Fee_tbl[City],City_Delivery_Fee_tbl[BaseDeliveryFee_NPR]) -> 95 | Z85: =IF(ISBLANK(Table5[[#This Row],[PromoCode]]), 0, _xlfn.LET( _xlpm.type, _xlfn.XLOOKUP(Table5[[#This Row],[PromoCode]], Promo_Codes!$A$2:$A$9, Promo_Codes!$C$2:$C$9, "Flat"), _xlpm.val, _xlfn.XLOOKUP(Table5[[#This Row],[PromoCode]], Promo_Codes!$A$2:$A$9, Promo_Codes!$D$2:$D$9, 0), IF(_xlpm.type="Percentage", Table5[[#This Row],[Order Amount]]*(_xlpm.val/100), _xlpm.val) ) ) -> 51 | AA85: =Table5[[#This Row],[Order Amount]]+Table5[[#This Row],[Delivery Fee]]-Table5[[#This Row],[Discount Amount]] -> 554 | AB85: =_xlfn.XLOOKUP(Table5[[#This Row],[RiderID]], Rider_Directory!$F$2:$F$26, Rider_Directory!$B$2:$B$26) -> Dharan | AC85: {=_xlfn.IFS(Table5[[#This Row],[Final Amount]]<500, "Small", Table5[[#This Row],[Final Amount]]<=1000, "Medium", Table5[[#This Row],[Final Amount]]>1000, "Large")} -> Medium | AD85: =_xlfn.LET(_xlpm.expiry,_xlfn.XLOOKUP(Table5[[#This Row],[PromoCode]],Promo_Codes!$A$2:$A$9,Promo_Codes!$F$2:$F$9,DATE(2099,1,1)),IF(Table5[[#This Row],[OrderDate]]>_xlpm.expiry,"Expired Code Used","Valid")) -> Valid
A86: ORD-1084 | B86: 45945 | C86: Gopal Shakya | D86: 9821-993518 | E86: 45930 | F86: =IF(B86-E86<=2,"New","Returning") -> Returning | G86: Dharan | H86: Bhatti Sekuwa Corner | I86: Sekuwa | J86: Chicken Sekuwa | K86: 1 | L86: R-124 | M86: Cash on Delivery | N86: DASHAIN10 | O86: Cancelled | P86: =IF(O86=""," NEED REVIEW","") | R86: 63 | T86: =_xlfn.CONCAT(Table5[[#This Row],[OrderID]]," | ",Table5[[#This Row],[City]]," | ",Table5[[#This Row],[ItemName]]) -> ORD-1084 | Dharan | Chicken Sekuwa | U86: =UPPER(Table5[[#This Row],[City]]) -> DHARAN | V86: =LOWER(Table5[[#This Row],[PaymentMethod]]) -> cash on delivery | W86: {=_xlfn.XLOOKUP(TRIM(Table5[[#This Row],[ItemName]]), TRIM(Menu_Price_List_tbl[ItemName]),Menu_Price_List_tbl[UnitPrice_NPR])} -> 420 | X86: =W86*K86 -> 420 | Y86: =_xlfn.XLOOKUP(Table5[[#This Row],[City]],City_Delivery_Fee_tbl[City],City_Delivery_Fee_tbl[BaseDeliveryFee_NPR]) -> 95 | Z86: =IF(ISBLANK(Table5[[#This Row],[PromoCode]]), 0, _xlfn.LET( _xlpm.type, _xlfn.XLOOKUP(Table5[[#This Row],[PromoCode]], Promo_Codes!$A$2:$A$9, Promo_Codes!$C$2:$C$9, "Flat"), _xlpm.val, _xlfn.XLOOKUP(Table5[[#This Row],[PromoCode]], Promo_Codes!$A$2:$A$9, Promo_Codes!$D$2:$D$9, 0), IF(_xlpm.type="Percentage", Table5[[#This Row],[Order Amount]]*(_xlpm.val/100), _xlpm.val) ) ) -> 42 | AA86: =Table5[[#This Row],[Order Amount]]+Table5[[#This Row],[Delivery Fee]]-Table5[[#This Row],[Discount Amount]] -> 473 | AB86: =_xlfn.XLOOKUP(Table5[[#This Row],[RiderID]], Rider_Directory!$F$2:$F$26, Rider_Directory!$B$2:$B$26) -> Dharan | AC86: {=_xlfn.IFS(Table5[[#This Row],[Final Amount]]<500, "Small", Table5[[#This Row],[Final Amount]]<=1000, "Medium", Table5[[#This Row],[Final Amount]]>1000, "Large")} -> Small | AD86: =_xlfn.LET(_xlpm.expiry,_xlfn.XLOOKUP(Table5[[#This Row],[PromoCode]],Promo_Codes!$A$2:$A$9,Promo_Codes!$F$2:$F$9,DATE(2099,1,1)),IF(Table5[[#This Row],[OrderDate]]>_xlpm.expiry,"Expired Code Used","Valid")) -> Valid
A87: ORD-1085 | B87: 45947 | C87: Kiran Lama | D87: 9800-267511 | E87: 45947 | F87: =IF(B87-E87<=2,"New","Returning") -> New | G87: Kathmandu | H87: Sweet Home Bakery | I87: Bakery | J87: cheese cake slice | K87: 2 | L87: R-103 | M87: Khalti | N87: DASHAIN10 | O87: Delivered | P87: =IF(O87=""," NEED REVIEW","") | R87: 20 | T87: =_xlfn.CONCAT(Table5[[#This Row],[OrderID]]," | ",Table5[[#This Row],[City]]," | ",Table5[[#This Row],[ItemName]]) -> ORD-1085 | Kathmandu | cheese cake slice | U87: =UPPER(Table5[[#This Row],[City]]) -> KATHMANDU | V87: =LOWER(Table5[[#This Row],[PaymentMethod]]) -> khalti | W87: {=_xlfn.XLOOKUP(TRIM(Table5[[#This Row],[ItemName]]), TRIM(Menu_Price_List_tbl[ItemName]),Menu_Price_List_tbl[UnitPrice_NPR])} -> 250 | X87: =W87*K87 -> 500 | Y87: =_xlfn.XLOOKUP(Table5[[#This Row],[City]],City_Delivery_Fee_tbl[City],City_Delivery_Fee_tbl[BaseDeliveryFee_NPR]) -> 50 | Z87: =IF(ISBLANK(Table5[[#This Row],[PromoCode]]), 0, _xlfn.LET( _xlpm.type, _xlfn.XLOOKUP(Table5[[#This Row],[PromoCode]], Promo_Codes!$A$2:$A$9, Promo_Codes!$C$2:$C$9, "Flat"), _xlpm.val, _xlfn.XLOOKUP(Table5[[#This Row],[PromoCode]], Promo_Codes!$A$2:$A$9, Promo_Codes!$D$2:$D$9, 0), IF(_xlpm.type="Percentage", Table5[[#This Row],[Order Amount]]*(_xlpm.val/100), _xlpm.val) ) ) -> 50 | AA87: =Table5[[#This Row],[Order Amount]]+Table5[[#This Row],[Delivery Fee]]-Table5[[#This Row],[Discount Amount]] -> 500 | AB87: =_xlfn.XLOOKUP(Table5[[#This Row],[RiderID]], Rider_Directory!$F$2:$F$26, Rider_Directory!$B$2:$B$26) -> Kathmandu | AC87: {=_xlfn.IFS(Table5[[#This Row],[Final Amount]]<500, "Small", Table5[[#This Row],[Final Amount]]<=1000, "Medium", Table5[[#This Row],[Final Amount]]>1000, "Large")} -> Medium | AD87: =_xlfn.LET(_xlpm.expiry,_xlfn.XLOOKUP(Table5[[#This Row],[PromoCode]],Promo_Codes!$A$2:$A$9,Promo_Codes!$F$2:$F$9,DATE(2099,1,1)),IF(Table5[[#This Row],[OrderDate]]>_xlpm.expiry,"Expired Code Used","Valid")) -> Valid
A88: ORD-1086 | B88: 45947 | C88: Sujan Basnet | D88: 9807-806671 | E88: 45945 | F88: =IF(B88-E88<=2,"New","Returning") -> New | G88: Kathmandu | H88: Cafe Cup | I88: Beverages | J88: Mango Juice | K88: 3 | L88: R-106 | M88: ConnectIPS | O88: Delivered | P88: =IF(O88=""," NEED REVIEW","") | Q88: 3 | R88: 33 | T88: =_xlfn.CONCAT(Table5[[#This Row],[OrderID]]," | ",Table5[[#This Row],[City]]," | ",Table5[[#This Row],[ItemName]]) -> ORD-1086 | Kathmandu | Mango Juice | U88: =UPPER(Table5[[#This Row],[City]]) -> KATHMANDU | V88: =LOWER(Table5[[#This Row],[PaymentMethod]]) -> connectips | W88: {=_xlfn.XLOOKUP(TRIM(Table5[[#This Row],[ItemName]]), TRIM(Menu_Price_List_tbl[ItemName]),Menu_Price_List_tbl[UnitPrice_NPR])} -> 120 | X88: =W88*K88 -> 360 | Y88: =_xlfn.XLOOKUP(Table5[[#This Row],[City]],City_Delivery_Fee_tbl[City],City_Delivery_Fee_tbl[BaseDeliveryFee_NPR]) -> 50 | Z88: =IF(ISBLANK(Table5[[#This Row],[PromoCode]]), 0, _xlfn.LET( _xlpm.type, _xlfn.XLOOKUP(Table5[[#This Row],[PromoCode]], Promo_Codes!$A$2:$A$9, Promo_Codes!$C$2:$C$9, "Flat"), _xlpm.val, _xlfn.XLOOKUP(Table5[[#This Row],[PromoCode]], Promo_Codes!$A$2:$A$9, Promo_Codes!$D$2:$D$9, 0), IF(_xlpm.type="Percentage", Table5[[#This Row],[Order Amount]]*(_xlpm.val/100), _xlpm.val) ) ) -> 0 | AA88: =Table5[[#This Row],[Order Amount]]+Table5[[#This Row],[Delivery Fee]]-Table5[[#This Row],[Discount Amount]] -> 410 | AB88: =_xlfn.XLOOKUP(Table5[[#This Row],[RiderID]], Rider_Directory!$F$2:$F$26, Rider_Directory!$B$2:$B$26) -> Kathmandu | AC88: {=_xlfn.IFS(Table5[[#This Row],[Final Amount]]<500, "Small", Table5[[#This Row],[Final Amount]]<=1000, "Medium", Table5[[#This Row],[Final Amount]]>1000, "Large")} -> Small | AD88: =_xlfn.LET(_xlpm.expiry,_xlfn.XLOOKUP(Table5[[#This Row],[PromoCode]],Promo_Codes!$A$2:$A$9,Promo_Codes!$F$2:$F$9,DATE(2099,1,1)),IF(Table5[[#This Row],[OrderDate]]>_xlpm.expiry,"Expired Code Used","Valid")) -> Valid
A89: ORD-1087 | B89: 45947 | C89: Ashok Shrestha | D89: 9837-215901 | E89: 45947 | F89: =IF(B89-E89<=2,"New","Returning") -> New | G89: Biratnagar | H89: Thakali Ghar | I89: Thakali Set | J89: veg thakali set | K89: 1 | L89: R-116 | M89: eSewa | N89: MONSOON30 | O89: Returned | P89: =IF(O89=""," NEED REVIEW","") | R89: 46 | T89: =_xlfn.CONCAT(Table5[[#This Row],[OrderID]]," | ",Table5[[#This Row],[City]]," | ",Table5[[#This Row],[ItemName]]) -> ORD-1087 | Biratnagar | veg thakali set | U89: =UPPER(Table5[[#This Row],[City]]) -> BIRATNAGAR | V89: =LOWER(Table5[[#This Row],[PaymentMethod]]) -> esewa | W89: {=_xlfn.XLOOKUP(TRIM(Table5[[#This Row],[ItemName]]), TRIM(Menu_Price_List_tbl[ItemName]),Menu_Price_List_tbl[UnitPrice_NPR])} -> 380 | X89: =W89*K89 -> 380 | Y89: =_xlfn.XLOOKUP(Table5[[#This Row],[City]],City_Delivery_Fee_tbl[City],City_Delivery_Fee_tbl[BaseDeliveryFee_NPR]) -> 90 | Z89: =IF(ISBLANK(Table5[[#This Row],[PromoCode]]), 0, _xlfn.LET( _xlpm.type, _xlfn.XLOOKUP(Table5[[#This Row],[PromoCode]], Promo_Codes!$A$2:$A$9, Promo_Codes!$C$2:$C$9, "Flat"), _xlpm.val, _xlfn.XLOOKUP(Table5[[#This Row],[PromoCode]], Promo_Codes!$A$2:$A$9, Promo_Codes!$D$2:$D$9, 0), IF(_xlpm.type="Percentage", Table5[[#This Row],[Order Amount]]*(_xlpm.val/100), _xlpm.val) ) ) -> 30 | AA89: =Table5[[#This Row],[Order Amount]]+Table5[[#This Row],[Delivery Fee]]-Table5[[#This Row],[Discount Amount]] -> 440 | AB89: =_xlfn.XLOOKUP(Table5[[#This Row],[RiderID]], Rider_Directory!$F$2:$F$26, Rider_Directory!$B$2:$B$26) -> Biratnagar | AC89: {=_xlfn.IFS(Table5[[#This Row],[Final Amount]]<500, "Small", Table5[[#This Row],[Final Amount]]<=1000, "Medium", Table5[[#This Row],[Final Amount]]>1000, "Large")} -> Small | AD89: =_xlfn.LET(_xlpm.expiry,_xlfn.XLOOKUP(Table5[[#This Row],[PromoCode]],Promo_Codes!$A$2:$A$9,Promo_Codes!$F$2:$F$9,DATE(2099,1,1)),IF(Table5[[#This Row],[OrderDate]]>_xlpm.expiry,"Expired Code Used","Valid")) -> Expired Code Used
A90: ORD-1088 | B90: 45948 | C90: Rajan Basnet | D90: 9897-465075 | E90: 45911 | F90: =IF(B90-E90<=2,"New","Returning") -> Returning | G90: Kathmandu | H90: Golden Dragon Kitchen | I90: Chinese | J90: Chicken Manchurian | K90: 1 | L90: R-103 | M90: eSewa | N90: DASHAIN10 | O90: Delivered | P90: =IF(O90=""," NEED REVIEW","") | Q90: 4 | R90: 33 | T90: =_xlfn.CONCAT(Table5[[#This Row],[OrderID]]," | ",Table5[[#This Row],[City]]," | ",Table5[[#This Row],[ItemName]]) -> ORD-1088 | Kathmandu | Chicken Manchurian | U90: =UPPER(Table5[[#This Row],[City]]) -> KATHMANDU | V90: =LOWER(Table5[[#This Row],[PaymentMethod]]) -> esewa | W90: {=_xlfn.XLOOKUP(TRIM(Table5[[#This Row],[ItemName]]), TRIM(Menu_Price_List_tbl[ItemName]),Menu_Price_List_tbl[UnitPrice_NPR])} -> 320 | X90: =W90*K90 -> 320 | Y90: =_xlfn.XLOOKUP(Table5[[#This Row],[City]],City_Delivery_Fee_tbl[City],City_Delivery_Fee_tbl[BaseDeliveryFee_NPR]) -> 50 | Z90: =IF(ISBLANK(Table5[[#This Row],[PromoCode]]), 0, _xlfn.LET( _xlpm.type, _xlfn.XLOOKUP(Table5[[#This Row],[PromoCode]], Promo_Codes!$A$2:$A$9, Promo_Codes!$C$2:$C$9, "Flat"), _xlpm.val, _xlfn.XLOOKUP(Table5[[#This Row],[PromoCode]], Promo_Codes!$A$2:$A$9, Promo_Codes!$D$2:$D$9, 0), IF(_xlpm.type="Percentage", Table5[[#This Row],[Order Amount]]*(_xlpm.val/100), _xlpm.val) ) ) -> 32 | AA90: =Table5[[#This Row],[Order Amount]]+Table5[[#This Row],[Delivery Fee]]-Table5[[#This Row],[Discount Amount]] -> 338 | AB90: =_xlfn.XLOOKUP(Table5[[#This Row],[RiderID]], Rider_Directory!$F$2:$F$26, Rider_Directory!$B$2:$B$26) -> Kathmandu | AC90: {=_xlfn.IFS(Table5[[#This Row],[Final Amount]]<500, "Small", Table5[[#This Row],[Final Amount]]<=1000, "Medium", Table5[[#This Row],[Final Amount]]>1000, "Large")} -> Small | AD90: =_xlfn.LET(_xlpm.expiry,_xlfn.XLOOKUP(Table5[[#This Row],[PromoCode]],Promo_Codes!$A$2:$A$9,Promo_Codes!$F$2:$F$9,DATE(2099,1,1)),IF(Table5[[#This Row],[OrderDate]]>_xlpm.expiry,"Expired Code Used","Valid")) -> Valid
A91: ORD-1089 | B91: 45948 | C91: Rita Gurung | D91: 9874-137484 | E91: 45947 | F91: =IF(B91-E91<=2,"New","Returning") -> New | G91: Pokhara | H91: Chiya Adda | I91: Beverages | J91: Milk Tea | K91: 2 | L91: R-112 | M91: eSewa | N91: DASHAIN10 | O91: Delivered | P91: =IF(O91=""," NEED REVIEW","") | Q91: 4 | R91: 35 | S91: Tasty and fresh, loved it | T91: =_xlfn.CONCAT(Table5[[#This Row],[OrderID]]," | ",Table5[[#This Row],[City]]," | ",Table5[[#This Row],[ItemName]]) -> ORD-1089 | Pokhara | Milk Tea | U91: =UPPER(Table5[[#This Row],[City]]) -> POKHARA | V91: =LOWER(Table5[[#This Row],[PaymentMethod]]) -> esewa | W91: {=_xlfn.XLOOKUP(TRIM(Table5[[#This Row],[ItemName]]), TRIM(Menu_Price_List_tbl[ItemName]),Menu_Price_List_tbl[UnitPrice_NPR])} -> 60 | X91: =W91*K91 -> 120 | Y91: =_xlfn.XLOOKUP(Table5[[#This Row],[City]],City_Delivery_Fee_tbl[City],City_Delivery_Fee_tbl[BaseDeliveryFee_NPR]) -> 70 | Z91: =IF(ISBLANK(Table5[[#This Row],[PromoCode]]), 0, _xlfn.LET( _xlpm.type, _xlfn.XLOOKUP(Table5[[#This Row],[PromoCode]], Promo_Codes!$A$2:$A$9, Promo_Codes!$C$2:$C$9, "Flat"), _xlpm.val, _xlfn.XLOOKUP(Table5[[#This Row],[PromoCode]], Promo_Codes!$A$2:$A$9, Promo_Codes!$D$2:$D$9, 0), IF(_xlpm.type="Percentage", Table5[[#This Row],[Order Amount]]*(_xlpm.val/100), _xlpm.val) ) ) -> 12 | AA91: =Table5[[#This Row],[Order Amount]]+Table5[[#This Row],[Delivery Fee]]-Table5[[#This Row],[Discount Amount]] -> 178 | AB91: =_xlfn.XLOOKUP(Table5[[#This Row],[RiderID]], Rider_Directory!$F$2:$F$26, Rider_Directory!$B$2:$B$26) -> Pokhara | AC91: {=_xlfn.IFS(Table5[[#This Row],[Final Amount]]<500, "Small", Table5[[#This Row],[Final Amount]]<=1000, "Medium", Table5[[#This Row],[Final Amount]]>1000, "Large")} -> Small | AD91: =_xlfn.LET(_xlpm.expiry,_xlfn.XLOOKUP(Table5[[#This Row],[PromoCode]],Promo_Codes!$A$2:$A$9,Promo_Codes!$F$2:$F$9,DATE(2099,1,1)),IF(Table5[[#This Row],[OrderDate]]>_xlpm.expiry,"Expired Code Used","Valid")) -> Valid
A92: ORD-1090 | B92: 45948 | C92: Anita Limbu | D92: 9824-180578 | E92: 45947 | F92: =IF(B92-E92<=2,"New","Returning") -> New | G92: Butwal | H92: Sweet Home Bakery | I92: Bakery | J92: Barfi (5 pcs) | K92: 2 | L92: R-119 | M92: Khalti | O92: Delivered | P92: =IF(O92=""," NEED REVIEW","") | Q92: 3 | R92: 54 | T92: =_xlfn.CONCAT(Table5[[#This Row],[OrderID]]," | ",Table5[[#This Row],[City]]," | ",Table5[[#This Row],[ItemName]]) -> ORD-1090 | Butwal | Barfi (5 pcs) | U92: =UPPER(Table5[[#This Row],[City]]) -> BUTWAL | V92: =LOWER(Table5[[#This Row],[PaymentMethod]]) -> khalti | W92: {=_xlfn.XLOOKUP(TRIM(Table5[[#This Row],[ItemName]]), TRIM(Menu_Price_List_tbl[ItemName]),Menu_Price_List_tbl[UnitPrice_NPR])} -> 220 | X92: =W92*K92 -> 440 | Y92: =_xlfn.XLOOKUP(Table5[[#This Row],[City]],City_Delivery_Fee_tbl[City],City_Delivery_Fee_tbl[BaseDeliveryFee_NPR]) -> 85 | Z92: =IF(ISBLANK(Table5[[#This Row],[PromoCode]]), 0, _xlfn.LET( _xlpm.type, _xlfn.XLOOKUP(Table5[[#This Row],[PromoCode]], Promo_Codes!$A$2:$A$9, Promo_Codes!$C$2:$C$9, "Flat"), _xlpm.val, _xlfn.XLOOKUP(Table5[[#This Row],[PromoCode]], Promo_Codes!$A$2:$A$9, Promo_Codes!$D$2:$D$9, 0), IF(_xlpm.type="Percentage", Table5[[#This Row],[Order Amount]]*(_xlpm.val/100), _xlpm.val) ) ) -> 0 | AA92: =Table5[[#This Row],[Order Amount]]+Table5[[#This Row],[Delivery Fee]]-Table5[[#This Row],[Discount Amount]] -> 525 | AB92: =_xlfn.XLOOKUP(Table5[[#This Row],[RiderID]], Rider_Directory!$F$2:$F$26, Rider_Directory!$B$2:$B$26) -> Butwal | AC92: {=_xlfn.IFS(Table5[[#This Row],[Final Amount]]<500, "Small", Table5[[#This Row],[Final Amount]]<=1000, "Medium", Table5[[#This Row],[Final Amount]]>1000, "Large")} -> Medium | AD92: =_xlfn.LET(_xlpm.expiry,_xlfn.XLOOKUP(Table5[[#This Row],[PromoCode]],Promo_Codes!$A$2:$A$9,Promo_Codes!$F$2:$F$9,DATE(2099,1,1)),IF(Table5[[#This Row],[OrderDate]]>_xlpm.expiry,"Expired Code Used","Valid")) -> Valid
A93: ORD-1091 | B93: 45948 | C93: Anita Khadka | D93: 9861-304451 | E93: 45948 | F93: =IF(B93-E93<=2,"New","Returning") -> New | G93: Pokhara | H93: Fast Bites | I93: Fast Food | J93: Veg Fried Rice | K93: 3 | L93: R-113 | M93: Cash on Delivery | N93: DASHAIN10 | O93: Cancelled | P93: =IF(O93=""," NEED REVIEW","") | R93: 50 | T93: =_xlfn.CONCAT(Table5[[#This Row],[OrderID]]," | ",Table5[[#This Row],[City]]," | ",Table5[[#This Row],[ItemName]]) -> ORD-1091 | Pokhara | Veg Fried Rice | U93: =UPPER(Table5[[#This Row],[City]]) -> POKHARA | V93: =LOWER(Table5[[#This Row],[PaymentMethod]]) -> cash on delivery | W93: {=_xlfn.XLOOKUP(TRIM(Table5[[#This Row],[ItemName]]), TRIM(Menu_Price_List_tbl[ItemName]),Menu_Price_List_tbl[UnitPrice_NPR])} -> 220 | X93: =W93*K93 -> 660 | Y93: =_xlfn.XLOOKUP(Table5[[#This Row],[City]],City_Delivery_Fee_tbl[City],City_Delivery_Fee_tbl[BaseDeliveryFee_NPR]) -> 70 | Z93: =IF(ISBLANK(Table5[[#This Row],[PromoCode]]), 0, _xlfn.LET( _xlpm.type, _xlfn.XLOOKUP(Table5[[#This Row],[PromoCode]], Promo_Codes!$A$2:$A$9, Promo_Codes!$C$2:$C$9, "Flat"), _xlpm.val, _xlfn.XLOOKUP(Table5[[#This Row],[PromoCode]], Promo_Codes!$A$2:$A$9, Promo_Codes!$D$2:$D$9, 0), IF(_xlpm.type="Percentage", Table5[[#This Row],[Order Amount]]*(_xlpm.val/100), _xlpm.val) ) ) -> 66 | AA93: =Table5[[#This Row],[Order Amount]]+Table5[[#This Row],[Delivery Fee]]-Table5[[#This Row],[Discount Amount]] -> 664 | AB93: =_xlfn.XLOOKUP(Table5[[#This Row],[RiderID]], Rider_Directory!$F$2:$F$26, Rider_Directory!$B$2:$B$26) -> Pokhara | AC93: {=_xlfn.IFS(Table5[[#This Row],[Final Amount]]<500, "Small", Table5[[#This Row],[Final Amount]]<=1000, "Medium", Table5[[#This Row],[Final Amount]]>1000, "Large")} -> Medium | AD93: =_xlfn.LET(_xlpm.expiry,_xlfn.XLOOKUP(Table5[[#This Row],[PromoCode]],Promo_Codes!$A$2:$A$9,Promo_Codes!$F$2:$F$9,DATE(2099,1,1)),IF(Table5[[#This Row],[OrderDate]]>_xlpm.expiry,"Expired Code Used","Valid")) -> Valid
A94: ORD-1092 | B94: 45949 | C94: Rohit Limbu | D94: 9850-201462 | E94: 45874 | F94: =IF(B94-E94<=2,"New","Returning") -> Returning | G94: Pokhara | H94: Quick Snacks Corner | I94: Fast Food | J94: Chicken Chowmein | K94: 2 | L94: R-114 | M94: eSewa | O94: Delivered | P94: =IF(O94=""," NEED REVIEW","") | Q94: 5 | R94: 36 | S94: Fast delivery today | T94: =_xlfn.CONCAT(Table5[[#This Row],[OrderID]]," | ",Table5[[#This Row],[City]]," | ",Table5[[#This Row],[ItemName]]) -> ORD-1092 | Pokhara | Chicken Chowmein | U94: =UPPER(Table5[[#This Row],[City]]) -> POKHARA | V94: =LOWER(Table5[[#This Row],[PaymentMethod]]) -> esewa | W94: {=_xlfn.XLOOKUP(TRIM(Table5[[#This Row],[ItemName]]), TRIM(Menu_Price_List_tbl[ItemName]),Menu_Price_List_tbl[UnitPrice_NPR])} -> 250 | X94: =W94*K94 -> 500 | Y94: =_xlfn.XLOOKUP(Table5[[#This Row],[City]],City_Delivery_Fee_tbl[City],City_Delivery_Fee_tbl[BaseDeliveryFee_NPR]) -> 70 | Z94: =IF(ISBLANK(Table5[[#This Row],[PromoCode]]), 0, _xlfn.LET( _xlpm.type, _xlfn.XLOOKUP(Table5[[#This Row],[PromoCode]], Promo_Codes!$A$2:$A$9, Promo_Codes!$C$2:$C$9, "Flat"), _xlpm.val, _xlfn.XLOOKUP(Table5[[#This Row],[PromoCode]], Promo_Codes!$A$2:$A$9, Promo_Codes!$D$2:$D$9, 0), IF(_xlpm.type="Percentage", Table5[[#This Row],[Order Amount]]*(_xlpm.val/100), _xlpm.val) ) ) -> 0 | AA94: =Table5[[#This Row],[Order Amount]]+Table5[[#This Row],[Delivery Fee]]-Table5[[#This Row],[Discount Amount]] -> 570 | AB94: =_xlfn.XLOOKUP(Table5[[#This Row],[RiderID]], Rider_Directory!$F$2:$F$26, Rider_Directory!$B$2:$B$26) -> Pokhara | AC94: {=_xlfn.IFS(Table5[[#This Row],[Final Amount]]<500, "Small", Table5[[#This Row],[Final Amount]]<=1000, "Medium", Table5[[#This Row],[Final Amount]]>1000, "Large")} -> Medium | AD94: =_xlfn.LET(_xlpm.expiry,_xlfn.XLOOKUP(Table5[[#This Row],[PromoCode]],Promo_Codes!$A$2:$A$9,Promo_Codes!$F$2:$F$9,DATE(2099,1,1)),IF(Table5[[#This Row],[OrderDate]]>_xlpm.expiry,"Expired Code Used","Valid")) -> Valid
A95: ORD-1093 | B95: 45949 | C95: Sujan Acharya | D95: 9855-459045 | E95: 45701 | F95: =IF(B95-E95<=2,"New","Returning") -> Returning | G95: Butwal | H95: Fast Bites | I95: Fast Food | J95: Chicken Pizza | K95: 4 | L95: R-119 | M95: ConnectIPS | N95: FIRSTORDER | O95: Delivered | P95: =IF(O95=""," NEED REVIEW","") | Q95: 2 | R95: 28 | S95: food was cold when it arrived | T95: =_xlfn.CONCAT(Table5[[#This Row],[OrderID]]," | ",Table5[[#This Row],[City]]," | ",Table5[[#This Row],[ItemName]]) -> ORD-1093 | Butwal | Chicken Pizza | U95: =UPPER(Table5[[#This Row],[City]]) -> BUTWAL | V95: =LOWER(Table5[[#This Row],[PaymentMethod]]) -> connectips | W95: {=_xlfn.XLOOKUP(TRIM(Table5[[#This Row],[ItemName]]), TRIM(Menu_Price_List_tbl[ItemName]),Menu_Price_List_tbl[UnitPrice_NPR])} -> 650 | X95: =W95*K95 -> 2600 | Y95: =_xlfn.XLOOKUP(Table5[[#This Row],[City]],City_Delivery_Fee_tbl[City],City_Delivery_Fee_tbl[BaseDeliveryFee_NPR]) -> 85 | Z95: =IF(ISBLANK(Table5[[#This Row],[PromoCode]]), 0, _xlfn.LET( _xlpm.type, _xlfn.XLOOKUP(Table5[[#This Row],[PromoCode]], Promo_Codes!$A$2:$A$9, Promo_Codes!$C$2:$C$9, "Flat"), _xlpm.val, _xlfn.XLOOKUP(Table5[[#This Row],[PromoCode]], Promo_Codes!$A$2:$A$9, Promo_Codes!$D$2:$D$9, 0), IF(_xlpm.type="Percentage", Table5[[#This Row],[Order Amount]]*(_xlpm.val/100), _xlpm.val) ) ) -> 100 | AA95: =Table5[[#This Row],[Order Amount]]+Table5[[#This Row],[Delivery Fee]]-Table5[[#This Row],[Discount Amount]] -> 2585 | AB95: =_xlfn.XLOOKUP(Table5[[#This Row],[RiderID]], Rider_Directory!$F$2:$F$26, Rider_Directory!$B$2:$B$26) -> Butwal | AC95: {=_xlfn.IFS(Table5[[#This Row],[Final Amount]]<500, "Small", Table5[[#This Row],[Final Amount]]<=1000, "Medium", Table5[[#This Row],[Final Amount]]>1000, "Large")} -> Large | AD95: =_xlfn.LET(_xlpm.expiry,_xlfn.XLOOKUP(Table5[[#This Row],[PromoCode]],Promo_Codes!$A$2:$A$9,Promo_Codes!$F$2:$F$9,DATE(2099,1,1)),IF(Table5[[#This Row],[OrderDate]]>_xlpm.expiry,"Expired Code Used","Valid")) -> Expired Code Used
A96: ORD-1094 | B96: 45949 | C96: Ramesh Tamang | D96: 9868-656355 | E96: 45885 | F96: =IF(B96-E96<=2,"New","Returning") -> Returning | G96: Dharan | H96: Bhattarai Momo Center | I96: Momo | J96: Chicken Momo (Steamed) | K96: 3 | L96: R-124 | M96: Khalti | N96: DASHAIN10 | O96: Delivered | P96: =IF(O96=""," NEED REVIEW","") | Q96: 5 | R96: 36 | T96: =_xlfn.CONCAT(Table5[[#This Row],[OrderID]]," | ",Table5[[#This Row],[City]]," | ",Table5[[#This Row],[ItemName]]) -> ORD-1094 | Dharan | Chicken Momo (Steamed) | U96: =UPPER(Table5[[#This Row],[City]]) -> DHARAN | V96: =LOWER(Table5[[#This Row],[PaymentMethod]]) -> khalti | W96: {=_xlfn.XLOOKUP(TRIM(Table5[[#This Row],[ItemName]]), TRIM(Menu_Price_List_tbl[ItemName]),Menu_Price_List_tbl[UnitPrice_NPR])} -> 190 | X96: =W96*K96 -> 570 | Y96: =_xlfn.XLOOKUP(Table5[[#This Row],[City]],City_Delivery_Fee_tbl[City],City_Delivery_Fee_tbl[BaseDeliveryFee_NPR]) -> 95 | Z96: =IF(ISBLANK(Table5[[#This Row],[PromoCode]]), 0, _xlfn.LET( _xlpm.type, _xlfn.XLOOKUP(Table5[[#This Row],[PromoCode]], Promo_Codes!$A$2:$A$9, Promo_Codes!$C$2:$C$9, "Flat"), _xlpm.val, _xlfn.XLOOKUP(Table5[[#This Row],[PromoCode]], Promo_Codes!$A$2:$A$9, Promo_Codes!$D$2:$D$9, 0), IF(_xlpm.type="Percentage", Table5[[#This Row],[Order Amount]]*(_xlpm.val/100), _xlpm.val) ) ) -> 57 | AA96: =Table5[[#This Row],[Order Amount]]+Table5[[#This Row],[Delivery Fee]]-Table5[[#This Row],[Discount Amount]] -> 608 | AB96: =_xlfn.XLOOKUP(Table5[[#This Row],[RiderID]], Rider_Directory!$F$2:$F$26, Rider_Directory!$B$2:$B$26) -> Dharan | AC96: {=_xlfn.IFS(Table5[[#This Row],[Final Amount]]<500, "Small", Table5[[#This Row],[Final Amount]]<=1000, "Medium", Table5[[#This Row],[Final Amount]]>1000, "Large")} -> Medium | AD96: =_xlfn.LET(_xlpm.expiry,_xlfn.XLOOKUP(Table5[[#This Row],[PromoCode]],Promo_Codes!$A$2:$A$9,Promo_Codes!$F$2:$F$9,DATE(2099,1,1)),IF(Table5[[#This Row],[OrderDate]]>_xlpm.expiry,"Expired Code Used","Valid")) -> Valid
A97: ORD-1095 | B97: 45950 | C97: Kiran Bhattarai | D97: 9851-732904 | E97: 45886 | F97: =IF(B97-E97<=2,"New","Returning") -> Returning | G97: Kathmandu | H97: Wok Point | I97: Chinese | J97: Veg Chopsuey | K97: 1 | L97: R-105 | M97: Cash on Delivery | N97: MOMO20 | O97: Delivered | P97: =IF(O97=""," NEED REVIEW","") | Q97: 4 | R97: 27 | S97: packaging was nice | T97: =_xlfn.CONCAT(Table5[[#This Row],[OrderID]]," | ",Table5[[#This Row],[City]]," | ",Table5[[#This Row],[ItemName]]) -> ORD-1095 | Kathmandu | Veg Chopsuey | U97: =UPPER(Table5[[#This Row],[City]]) -> KATHMANDU | V97: =LOWER(Table5[[#This Row],[PaymentMethod]]) -> cash on delivery | W97: {=_xlfn.XLOOKUP(TRIM(Table5[[#This Row],[ItemName]]), TRIM(Menu_Price_List_tbl[ItemName]),Menu_Price_List_tbl[UnitPrice_NPR])} -> 260 | X97: =W97*K97 -> 260 | Y97: =_xlfn.XLOOKUP(Table5[[#This Row],[City]],City_Delivery_Fee_tbl[City],City_Delivery_Fee_tbl[BaseDeliveryFee_NPR]) -> 50 | Z97: =IF(ISBLANK(Table5[[#This Row],[PromoCode]]), 0, _xlfn.LET( _xlpm.type, _xlfn.XLOOKUP(Table5[[#This Row],[PromoCode]], Promo_Codes!$A$2:$A$9, Promo_Codes!$C$2:$C$9, "Flat"), _xlpm.val, _xlfn.XLOOKUP(Table5[[#This Row],[PromoCode]], Promo_Codes!$A$2:$A$9, Promo_Codes!$D$2:$D$9, 0), IF(_xlpm.type="Percentage", Table5[[#This Row],[Order Amount]]*(_xlpm.val/100), _xlpm.val) ) ) -> 52 | AA97: =Table5[[#This Row],[Order Amount]]+Table5[[#This Row],[Delivery Fee]]-Table5[[#This Row],[Discount Amount]] -> 258 | AB97: =_xlfn.XLOOKUP(Table5[[#This Row],[RiderID]], Rider_Directory!$F$2:$F$26, Rider_Directory!$B$2:$B$26) -> Kathmandu | AC97: {=_xlfn.IFS(Table5[[#This Row],[Final Amount]]<500, "Small", Table5[[#This Row],[Final Amount]]<=1000, "Medium", Table5[[#This Row],[Final Amount]]>1000, "Large")} -> Small | AD97: =_xlfn.LET(_xlpm.expiry,_xlfn.XLOOKUP(Table5[[#This Row],[PromoCode]],Promo_Codes!$A$2:$A$9,Promo_Codes!$F$2:$F$9,DATE(2099,1,1)),IF(Table5[[#This Row],[OrderDate]]>_xlpm.expiry,"Expired Code Used","Valid")) -> Valid
A98: ORD-1096 | B98: 45950 | C98: Nirmala Dahal | D98: 9814-865465 | E98: 45948 | F98: =IF(B98-E98<=2,"New","Returning") -> New | G98: Lalitpur | H98: Himalayan Thakali Kitchen | I98: Thakali Set | J98: Chicken Thakali Set | K98: 2 | L98: R-108 | M98: eSewa | O98: Delivered | P98: =IF(O98=""," NEED REVIEW","") | Q98: 5 | R98: 36 | T98: =_xlfn.CONCAT(Table5[[#This Row],[OrderID]]," | ",Table5[[#This Row],[City]]," | ",Table5[[#This Row],[ItemName]]) -> ORD-1096 | Lalitpur | Chicken Thakali Set | U98: =UPPER(Table5[[#This Row],[City]]) -> LALITPUR | V98: =LOWER(Table5[[#This Row],[PaymentMethod]]) -> esewa | W98: {=_xlfn.XLOOKUP(TRIM(Table5[[#This Row],[ItemName]]), TRIM(Menu_Price_List_tbl[ItemName]),Menu_Price_List_tbl[UnitPrice_NPR])} -> 480 | X98: =W98*K98 -> 960 | Y98: =_xlfn.XLOOKUP(Table5[[#This Row],[City]],City_Delivery_Fee_tbl[City],City_Delivery_Fee_tbl[BaseDeliveryFee_NPR]) -> 50 | Z98: =IF(ISBLANK(Table5[[#This Row],[PromoCode]]), 0, _xlfn.LET( _xlpm.type, _xlfn.XLOOKUP(Table5[[#This Row],[PromoCode]], Promo_Codes!$A$2:$A$9, Promo_Codes!$C$2:$C$9, "Flat"), _xlpm.val, _xlfn.XLOOKUP(Table5[[#This Row],[PromoCode]], Promo_Codes!$A$2:$A$9, Promo_Codes!$D$2:$D$9, 0), IF(_xlpm.type="Percentage", Table5[[#This Row],[Order Amount]]*(_xlpm.val/100), _xlpm.val) ) ) -> 0 | AA98: =Table5[[#This Row],[Order Amount]]+Table5[[#This Row],[Delivery Fee]]-Table5[[#This Row],[Discount Amount]] -> 1010 | AB98: =_xlfn.XLOOKUP(Table5[[#This Row],[RiderID]], Rider_Directory!$F$2:$F$26, Rider_Directory!$B$2:$B$26) -> Lalitpur | AC98: {=_xlfn.IFS(Table5[[#This Row],[Final Amount]]<500, "Small", Table5[[#This Row],[Final Amount]]<=1000, "Medium", Table5[[#This Row],[Final Amount]]>1000, "Large")} -> Large | AD98: =_xlfn.LET(_xlpm.expiry,_xlfn.XLOOKUP(Table5[[#This Row],[PromoCode]],Promo_Codes!$A$2:$A$9,Promo_Codes!$F$2:$F$9,DATE(2099,1,1)),IF(Table5[[#This Row],[OrderDate]]>_xlpm.expiry,"Expired Code Used","Valid")) -> Valid
